Workbook

Sheet Introduction
B1: Financial Projection Model
B3: This spreadsheet walks you through the process of developing an integrated set of financial projections.
B5: To use this model, simply complete any information asked for found in the color yellow.
B6: Example: Fill in boxes that look like this | C6: 0
B8: A number found in the color green is optional information that you can complete.
B9: Example: Check these assumptions | C9: 0
B11: Otherwise, any information found in black type is automatically calculated for you.
B12: Although the cells that are calculated are locked (or protected), you can turn off this protection to modify the sheets.
B13: To do this, select "Tools" from the menu bar at the top of the screen. Then select, "Protection."
B14: Finally, select "Unprotect Sheet" and you will be able to edit any labels or formulas.
B16: Before you begin, we need some information about your business to best customize your financial statements.
B17: Please enter the name of your business in the box below:
B19: Enter Your Business Name Here
B22: The first six worksheets in this workbook are steps you will need to complete. They are titled:
B23: 1. Required Start-Up Funds
B24: 2. Salaries and Wages
B25: 3. Fixed Operating Expenses
B26: 4. Projected Sales Forecast (2 sheets)
... B32: q

Sheet 1. Required Start-Up Funds
A1: =Introduction!B19 | M1: =NOW()
A2: Required Start-Up Funds
A6: Required Start-Up Funds | E6: Amount | G6: Totals | H6: Depreciation | J6: Notes
B7: Fixed Assets
C8: Real Estate | E8: 0
C9: Buildings | E9: 0 | H9: 20 | I9: years
C10: Leasehold Improvements | E10: 0 | H10: 7 | I10: years
C11: Equipment | E11: 0 | H11: 7 | I11: years
C12: Furniture and Fixtures | E12: 0 | H12: 5 | I12: years
C13: Vehicles | E13: 0 | H13: 5 | I13: years
C14: Other Fixed Assets | E14: 0 | H14: 5 | I14: years
B15: Total Fixed Assets | G15: =SUM(E8:E14)
B17: Operating Capital
C18: Pre-Opening Salaries and Wages | E18: 0
C19: Prepaid Insurance Premiums | E19: 0
C20: Beginning Inventory | E20: 0
C21: Legal and Accounting Fees | E21: 0
C22: Rent Deposits | E22: 0
C23: Utility Deposits | E23: 0
C24: Supplies | E24: 0
C25: Advertising and Promotions | E25: 0
C26: Licenses | E26: 0
C27: Other Initial Start-Up Costs | E27: 0
C28: Working Capital (Cash On Hand) | E28: 0
B29: Total Operating Capital | G29: =SUM(E18:E28)
A31: Total Required Funds | G31: =G15+G29
A36: Sources of Funding | E36: Amount | G36: Totals | H36: Loan Rate | I36: Term in Months | J36: Monthly Payments
B37: Owner's Cash Injection | E37: =IF(G37=0,0,G37/G42) | G37: 0
B38: Outside Investors | E38: =IF(G38=0,0,G38/G42) | G38: 0
B39: Additional Loans or Debt
C40: Commercial Loan | E40: =IF(G40=0,0,G40/G42) | G40: =(G31-E8-E9)-((G37+G38)-(E8+E9-G41)) | H40: 0.09 | I40: =7*12 | J40: =ABS(PMT(H40/12,I40,G40))
C41: Commercial Mortgage | E41: =IF(G41=0,0,G41/G42) | G41: =IF((G31-G37+G38)<(E8+E9)*0.8,G31-G37+G38,(E8+E9)*0.8) | H41: 0.09 | I41: =20*12 | J41: =ABS(PMT(H41/12,I41,G41))
A42: Total Sources of Funding | E42: =SUM(E37:E41) | G42: =SUM(G37:G41) | J42: =J40+J41
A44: =IF('9. Cash Flow Statement'!Q35>0,"A line of credit is also required in the amount of","") | G44: =IF('9. Cash Flow Statement'!Q35>0,'9. Cash Flow Statement'!Q35,"")

Sheet 2. Salaries and Wages
A1: ='1. Required Start-Up Funds'!A1 | R1: =NOW()
A2: Salaries and Wages
A6: Salaries and Related Expenses | F6: # | G6: Assumptions | I6: Wage Base | K6: Monthly | M6: Year One | N6: Year Two | O6: Year Three
A8: Percent Change | N8: 0.03 | O8: 0.03
A10: Salaries and Wages
B11: Owner's Compensation | F11: 0 | K11: 0 | M11: =K11*12 | N11: =M11*(1+$N$8) | O11: =N11*(1+$O$8)
B12: Salaries | F12: 0 | K12: 0 | M12: =K12*12 | N12: =M12*(1+$N$8) | O12: =N12*(1+$O$8)
B13: Wages
C14: Full-Time Employees | F14: 0 | K14: =M14/12 | M14: =G15*G16*52*F14 | N14: =M14*(1+$N$8) | O14: =N14*(1+$O$8)
D15: Estimated Hours Per Week | G15: 40
D16: Estimated Rate Per Hour | G16: 9
C17: Part-Time Employees | F17: 0 | K17: =M17/12 | M17: =G18*G19*52*F17 | N17: =M17*(1+$N$8) | O17: =N17*(1+$O$8)
D18: Estimated Hours Per Week | G18: 20
D19: Estimated Rate Per Hour | G19: 9
B20: Independent Contractors | K20: 0 | M20: =K20*12 | N20: =M20*(1+$N$8) | O20: =N20*(1+$O$8)
A21: Total Salaries and Wages | F21: =SUM(F11:F20) | K21: =SUM(K11:K20) | M21: =SUM(M11:M20) | N21: =SUM(N11:N20) | O21: =SUM(O11:O20)
A23: Payroll Taxes and Benefits
B24: Social Security | G24: 0.062 | I24: 102000 | K24: =K21*$G$24 | M24: =M21*$G$24 | N24: =N21*$G$24 | O24: =O21*$G$24
B25: Medicare | G25: 0.0145 | K25: =K21*$G$25 | M25: =M21*$G$25 | N25: =N21*$G$25 | O25: =O21*$G$25
B26: Federal Unemployment Tax (FUTA) | G26: 0.008 | I26: 7000 | K26: =F21*I26*G26/12 | M26: =K26*12 | N26: =M26 | O26: =N26
B27: State Unemployment Tax (SUTA) | G27: 0.027 | I27: 7000 | K27: =F21*I27*G27/12 | M27: =K27*12 | N27: =M27 | O27: =N27
B28: Employee Pension Programs | G28: 0 | K28: =G28*K21 | M28: =K28*12 | N28: =M28 | O28: =N28
B29: Worker's Compensation | G29: 0 | K29: =G29*$K$21 | M29: =K29*12 | N29: =M29*(1+N8) | O29: =N29*(1+O8)
B30: Employee Health Insurance | G30: 0 | K30: =G30*$K$21 | M30: =K30*12 | N30: =M30*(1+N8) | O30: =N30*(1+O8)
B31: Other Employee Benefit Programs | G31: 0 | K31: =G31*$K$21 | M31: =K31*12 | N31: =M31*(1+N8) | O31: =N31*(1+O8)
A32: Total Payroll Taxes and Benefits | K32: =SUM(K24:K31) | M32: =SUM(M24:M31) | N32: =SUM(N24:N31) | O32: =SUM(O24:O31)
A35: Total Salaries and Related Expenses | K35: =K21+K32 | M35: =M21+M32 | N35: =N21+N32 | O35: =O21+O32

Sheet 3. Fixed Operating Expenses
A1: ='1. Required Start-Up Funds'!A1 | Q1: =NOW()
A2: Fixed Operating Expenses
A6: Fixed Operating Expenses | G6: Monthly | I6: Year One | J6: Year Two | K6: Year Three | M6: Notes
A8: Percent Change | J8: 0.03 | K8: 0.03
A10: Expenses
B11: Advertising | G11: 0 | I11: =G11*12 | J11: =I11*(1+$J$8) | K11: =J11*(1+$K$8)
B12: Car and Truck Expenses | G12: 0 | I12: =G12*12 | J12: =I12*(1+$J$8) | K12: =J12*(1+$K$8)
B13: Commissions and Fees | G13: 0 | I13: =G13*12 | J13: =I13*(1+$J$8) | K13: =J13*(1+$K$8)
B14: Contract Labor | G14: 0 | I14: =G14*12 | J14: =I14*(1+$J$8) | K14: =J14*(1+$K$8)
B15: Credit Card and Bank Charges | G15: 0 | I15: =G15*12 | J15: =I15*(1+$J$8) | K15: =J15*(1+$K$8)
B16: Customer Discounts and Refunds | G16: 0 | I16: =G16*12 | J16: =I16*(1+$J$8) | K16: =J16*(1+$K$8)
B17: Dues and Subscriptions | G17: 0 | I17: =G17*12 | J17: =I17*(1+$J$8) | K17: =J17*(1+$K$8)
B18: Entertainment | G18: 0 | I18: =G18*12 | J18: =I18*(1+$J$8) | K18: =J18*(1+$K$8)
B19: Insurance (Liability and Property) | G19: 0 | I19: =G19*12 | J19: =I19*(1+$J$8) | K19: =J19*(1+$K$8)
B20: Internet | G20: 0 | I20: =G20*12 | J20: =I20*(1+$J$8) | K20: =J20*(1+$K$8)
B21: Legal and Professional Fees | G21: 0 | I21: =G21*12 | J21: =I21*(1+$J$8) | K21: =J21*(1+$K$8)
B22: Office Expenses | G22: 0 | I22: =G22*12 | J22: =I22*(1+$J$8) | K22: =J22*(1+$K$8)
... B30: Utilities | G30: 0 | I30: =G30*12 | J30: =I30*(1+$J$8) | K30: =J30*(1+$K$8)
A31: Total Expenses | G31: =SUM(G11:G30) | I31: =SUM(I11:I30) | J31: =SUM(J11:J30) | K31: =SUM(K11:K30)
A33: Other Expenses
B34: Depreciation | G34: =('1. Required Start-Up Funds'!E9/'1. Required Start-Up Funds'!H9)/12+('1. Required Start-Up Funds'!E10/'1. Required Start-Up Funds'!H10)/12+('1. Required Start-Up Funds'!E11/'1. Required Start-Up Funds'!H11)/12+('1. Required Start-Up Funds'!E12/'1. Required Start-Up Funds'!H12)/12+('1. Required Start-Up Funds'!E13/'1. Required Start-Up Funds'!H13)/12+('1. Required Start-Up Funds'!E14/'1. Required Start-Up Funds'!H14)/12 | I34: =G34*12 | J34: =I34 | K34: =J34
B35: Interest
C36: Commercial Loan | G36: ='20. Amoritization Schedule'!S15/12 | I36: ='20. Amoritization Schedule'!S15 | J36: ='20. Amoritization Schedule'!S19 | K36: ='20. Amoritization Schedule'!S23
C37: Commercial Mortgage | G37: ='20. Amoritization Schedule'!S35/12 | I37: ='20. Amoritization Schedule'!S35 | J37: ='20. Amoritization Schedule'!S39 | K37: ='20. Amoritization Schedule'!S43
C38: Line of Credit | G38: ='8. Income Statement'!Q62/12 | I38: ='8. Income Statement'!Q62 | J38: 0 | K38: 0
A39: Total Other Expenses | G39: =SUM(G34:G38) | I39: =SUM(I34:I38) | J39: =SUM(J34:J38) | K39: =SUM(K34:K38)
A41: Total Fixed Operating Expenses | G41: =G31+G39 | I41: =I31+I39 | J41: =J31+J39 | K41: =K31+K39

Sheet 4. Projected Sales Forecast
A1: ='1. Required Start-Up Funds'!A1 | T1: =NOW()
A2: Projected Sales Forecast
A6: Products and Services | E6: Assumptions | F6: % | H6: Month 1 | I6: Month 2 | J6: Month 3 | K6: Month 4 | L6: Month 5 | M6: Month 6 | N6: Month 7 | O6: Month 8 | P6: Month 9 | Q6: Month 10 | R6: Month 11 | S6: Month 12 | T6: Totals
A8: Product/Service A
B9: Price Per Unit | E9: 0 | F9: 1
B10: Variable Cost Per Unit | E10: 0 | F10: =IF(E9>0,E10/E9,0)
B11: Gross Margin Per Unit | E11: =E9-E10 | F11: =IF(E9>0,E11/E9,0)
B12: Projected Unit Sales
C13: Seasonality Factor | H13: =IF(H14=0,0,H14/$T$14) | I13: =IF(I14=0,0,I14/$T$14) | J13: =IF(J14=0,0,J14/$T$14) | K13: =IF(K14=0,0,K14/$T$14) | L13: =IF(L14=0,0,L14/$T$14) | M13: =IF(M14=0,0,M14/$T$14) | N13: =IF(N14=0,0,N14/$T$14) | O13: =IF(O14=0,0,O14/$T$14) | ... S13: =IF(S14=0,0,S14/$T$14) | T13: =SUM(H13:S13)
C14: Year One | H14: 0 | I14: 0 | J14: 0 | K14: 0 | L14: 0 | M14: 0 | N14: 0 | O14: 0 | P14: 0 | Q14: 0 | R14: 0 | S14: 0 | T14: =SUM(H14:S14)
C15: Year Two Growth | E15: 0.1 | H15: =IF($E$15=0,H14,(1+$E$15)*H14) | I15: =IF($E$15=0,I14,(1+$E$15)*I14) | J15: =IF($E$15=0,J14,(1+$E$15)*J14) | K15: =IF($E$15=0,K14,(1+$E$15)*K14) | L15: =IF($E$15=0,L14,(1+$E$15)*L14) | M15: =IF($E$15=0,M14,(1+$E$15)*M14) | N15: =IF($E$15=0,N14,(1+$E$15)*N14) | O15: =IF($E$15=0,O14,(1+$E$15)*O14) | ... S15: =IF($E$15=0,S14,(1+$E$15)*S14) | T15: =SUM(H15:S15)
C16: Year Three Growth | E16: 0.1 | H16: =IF($E$16=0,H15,(1+$E$16)*H15) | I16: =IF($E$16=0,I15,(1+$E$16)*I15) | J16: =IF($E$16=0,J15,(1+$E$16)*J15) | K16: =IF($E$16=0,K15,(1+$E$16)*K15) | L16: =IF($E$16=0,L15,(1+$E$16)*L15) | M16: =IF($E$16=0,M15,(1+$E$16)*M15) | N16: =IF($E$16=0,N15,(1+$E$16)*N15) | O16: =IF($E$16=0,O15,(1+$E$16)*O15) | ... S16: =IF($E$16=0,S15,(1+$E$16)*S15) | T16: =SUM(H16:S16)
B17: Fixed Expense Allocation | E17: 0.5
B19: Projected Revenue | E19: =T14*E9
B20: Variable Costs | E20: =E10*T14
B21: Gross Margin | E21: =E19-E20
B22: Fixed Expenses | E22: =E17*'3. Fixed Operating Expenses'!I41
B23: Profit | E23: =E21-E22 | F23: =IF(E9>0,E23/E19,0)
B25: Breakeven Sales Revenue | E25: =IF(E9>0,E22/F11,0)
B26: Breakeven Sales Units | E26: =IF(E9>0,E25/E9,0)
A30: Product/Service B
B31: Price Per Unit | E31: 0 | F31: 1
B32: Variable Cost Per Unit | E32: 0 | F32: =IF(E31>0,E32/E31,0)
B33: Gross Margin Per Unit | E33: =E31-E32 | F33: =IF(E31>0,E33/E31,0)
B34: Projected Unit Sales
C35: Seasonality Factor | H35: =IF(H36=0,0,H36/$T$36) | I35: =IF(I36=0,0,I36/$T$36) | J35: =IF(J36=0,0,J36/$T$36) | K35: =IF(K36=0,0,K36/$T$36) | L35: =IF(L36=0,0,L36/$T$36) | M35: =IF(M36=0,0,M36/$T$36) | N35: =IF(N36=0,0,N36/$T$36) | O35: =IF(O36=0,0,O36/$T$36) | ... S35: =IF(S36=0,0,S36/$T$36) | T35: =SUM(H35:S35)
C36: Year One | H36: 0 | I36: 0 | J36: 0 | K36: 0 | L36: 0 | M36: 0 | N36: 0 | O36: 0 | P36: 0 | Q36: 0 | R36: 0 | S36: 0 | T36: =SUM(H36:S36)
C37: Year Two Growth | E37: 0.1 | H37: =IF($E$15=0,H36,(1+$E$37)*H36) | I37: =IF($E$15=0,I36,(1+$E$37)*I36) | J37: =IF($E$15=0,J36,(1+$E$37)*J36) | K37: =IF($E$15=0,K36,(1+$E$37)*K36) | L37: =IF($E$15=0,L36,(1+$E$37)*L36) | M37: =IF($E$15=0,M36,(1+$E$37)*M36) | N37: =IF($E$15=0,N36,(1+$E$37)*N36) | O37: =IF($E$15=0,O36,(1+$E$37)*O36) | ... S37: =IF($E$15=0,S36,(1+$E$37)*S36) | T37: =SUM(H37:S37)
C38: Year Three Growth | E38: 0.1 | H38: =IF($E$16=0,H37,(1+$E$38)*H37) | I38: =IF($E$16=0,I37,(1+$E$38)*I37) | J38: =IF($E$16=0,J37,(1+$E$38)*J37) | K38: =IF($E$16=0,K37,(1+$E$38)*K37) | L38: =IF($E$16=0,L37,(1+$E$38)*L37) | M38: =IF($E$16=0,M37,(1+$E$38)*M37) | N38: =IF($E$16=0,N37,(1+$E$38)*N37) | O38: =IF($E$16=0,O37,(1+$E$38)*O37) | ... S38: =IF($E$16=0,S37,(1+$E$38)*S37) | T38: =SUM(H38:S38)
B39: Fixed Expense Allocation | E39: =(1-E17)/3
B41: Projected Revenue | E41: =T36*E31
B42: Variable Costs | E42: =E32*T36
B43: Gross Margin | E43: =E41-E42
B44: Fixed Expenses | E44: =E39*'3. Fixed Operating Expenses'!I41
B45: Profit | E45: =E43-E44 | F45: =IF(E31>0,E45/E41,0)
B47: Breakeven Sales Revenue | E47: =IF(E31>0,E44/F33,0)
B48: Breakeven Sales Units | E48: =IF(E31>0,E47/E31,0)

Sheet 5. Projected Sales Forecast (2)
A1: ='1. Required Start-Up Funds'!A1 | T1: =NOW()
A2: Projected Sales Forecast - Page 2
A6: Products and Services | E6: Assumptions | F6: % | H6: ='4. Projected Sales Forecast'!H6 | I6: ='4. Projected Sales Forecast'!I6 | J6: ='4. Projected Sales Forecast'!J6 | K6: ='4. Projected Sales Forecast'!K6 | L6: ='4. Projected Sales Forecast'!L6 | M6: ='4. Projected Sales Forecast'!M6 | N6: ='4. Projected Sales Forecast'!N6 | O6: ='4. Projected Sales Forecast'!O6 | ... S6: ='4. Projected Sales Forecast'!S6 | T6: Totals
A8: Product/Service C
B9: Price Per Unit | E9: 0 | F9: 1
B10: Variable Cost Per Unit | E10: 0 | F10: =IF(E9>0,E10/E9,0)
B11: Gross Margin Per Unit | E11: =E9-E10 | F11: =IF(E9>0,E11/E9,0)
B12: Projected Unit Sales
C13: Seasonality Factor | H13: =IF(H14=0,0,H14/$T$14) | I13: =IF(I14=0,0,I14/$T$14) | J13: =IF(J14=0,0,J14/$T$14) | K13: =IF(K14=0,0,K14/$T$14) | L13: =IF(L14=0,0,L14/$T$14) | M13: =IF(M14=0,0,M14/$T$14) | N13: =IF(N14=0,0,N14/$T$14) | O13: =IF(O14=0,0,O14/$T$14) | ... S13: =IF(S14=0,0,S14/$T$14) | T13: =SUM(H13:S13)
C14: Year One | H14: 0 | I14: 0 | J14: 0 | K14: 0 | L14: 0 | M14: 0 | N14: 0 | O14: 0 | P14: 0 | Q14: 0 | R14: 0 | S14: 0 | T14: =SUM(H14:S14)
C15: Year Two Growth | E15: 0.1 | H15: =IF($E$15=0,H14,(1+$E$15)*H14) | I15: =IF($E$15=0,I14,(1+$E$15)*I14) | J15: =IF($E$15=0,J14,(1+$E$15)*J14) | K15: =IF($E$15=0,K14,(1+$E$15)*K14) | L15: =IF($E$15=0,L14,(1+$E$15)*L14) | M15: =IF($E$15=0,M14,(1+$E$15)*M14) | N15: =IF($E$15=0,N14,(1+$E$15)*N14) | O15: =IF($E$15=0,O14,(1+$E$15)*O14) | ... S15: =IF($E$15=0,S14,(1+$E$15)*S14) | T15: =SUM(H15:S15)
C16: Year Three Growth | E16: 0.1 | H16: =IF($E$16=0,H15,(1+$E$16)*H15) | I16: =IF($E$16=0,I15,(1+$E$16)*I15) | J16: =IF($E$16=0,J15,(1+$E$16)*J15) | K16: =IF($E$16=0,K15,(1+$E$16)*K15) | L16: =IF($E$16=0,L15,(1+$E$16)*L15) | M16: =IF($E$16=0,M15,(1+$E$16)*M15) | N16: =IF($E$16=0,N15,(1+$E$16)*N15) | O16: =IF($E$16=0,O15,(1+$E$16)*O15) | ... S16: =IF($E$16=0,S15,(1+$E$16)*S15) | T16: =SUM(H16:S16)
B17: Fixed Expense Allocation | E17: =(1-('4. Projected Sales Forecast'!E17+'4. Projected Sales Forecast'!E39))/2
B19: Projected Revenue | E19: =T14*E9
B20: Variable Costs | E20: =E10*T14
B21: Gross Margin | E21: =E19-E20
B22: Fixed Expenses | E22: =E17*'3. Fixed Operating Expenses'!I41
B23: Profit | E23: =E21-E22 | F23: =IF(E9>0,E23/E19,0)
B25: Breakeven Sales Revenue | E25: =IF(E9>0,E22/F11,0)
B26: Breakeven Sales Units | E26: =IF(E9>0,E25/E9,0)
A30: Product/Service D
B31: Price Per Unit | E31: 0 | F31: 1
B32: Variable Cost Per Unit | E32: 0 | F32: =IF(E31>0,E32/E31,0)
B33: Gross Margin Per Unit | E33: =E31-E32 | F33: =IF(E31>0,E33/E31,0)
B34: Projected Unit Sales
C35: Seasonality Factor | H35: =IF(H36=0,0,H36/$T$36) | I35: =IF(I36=0,0,I36/$T$36) | J35: =IF(J36=0,0,J36/$T$36) | K35: =IF(K36=0,0,K36/$T$36) | L35: =IF(L36=0,0,L36/$T$36) | M35: =IF(M36=0,0,M36/$T$36) | N35: =IF(N36=0,0,N36/$T$36) | O35: =IF(O36=0,0,O36/$T$36) | ... S35: =IF(S36=0,0,S36/$T$36) | T35: =SUM(H35:S35)
C36: Year One | H36: 0 | I36: 0 | J36: 0 | K36: 0 | L36: 0 | M36: 0 | N36: 0 | O36: 0 | P36: 0 | Q36: 0 | R36: 0 | S36: 0 | T36: =SUM(H36:S36)
C37: Year Two Growth | E37: 0.1 | H37: =IF($E$15=0,H36,(1+$E$37)*H36) | I37: =IF($E$15=0,I36,(1+$E$37)*I36) | J37: =IF($E$15=0,J36,(1+$E$37)*J36) | K37: =IF($E$15=0,K36,(1+$E$37)*K36) | L37: =IF($E$15=0,L36,(1+$E$37)*L36) | M37: =IF($E$15=0,M36,(1+$E$37)*M36) | N37: =IF($E$15=0,N36,(1+$E$37)*N36) | O37: =IF($E$15=0,O36,(1+$E$37)*O36) | ... S37: =IF($E$15=0,S36,(1+$E$37)*S36) | T37: =SUM(H37:S37)
C38: Year Three Growth | E38: 0.1 | H38: =IF($E$16=0,H37,(1+$E$38)*H37) | I38: =IF($E$16=0,I37,(1+$E$38)*I37) | J38: =IF($E$16=0,J37,(1+$E$38)*J37) | K38: =IF($E$16=0,K37,(1+$E$38)*K37) | L38: =IF($E$16=0,L37,(1+$E$38)*L37) | M38: =IF($E$16=0,M37,(1+$E$38)*M37) | N38: =IF($E$16=0,N37,(1+$E$38)*N37) | O38: =IF($E$16=0,O37,(1+$E$38)*O37) | ... S38: =IF($E$16=0,S37,(1+$E$38)*S37) | T38: =SUM(H38:S38)
B39: Fixed Expense Allocation | E39: =1-('4. Projected Sales Forecast'!E17+'4. Projected Sales Forecast'!E39+'5. Projected Sales Forecast (2)'!E17)
B41: Projected Revenue | E41: =T36*E31
B42: Variable Costs | E42: =E32*T36
B43: Gross Margin | E43: =E41-E42
B44: Fixed Expenses | E44: =E39*'3. Fixed Operating Expenses'!I41
B45: Profit | E45: =E43-E44 | F45: =IF(E31>0,E45/E41,0)
B47: Breakeven Sales Revenue | E47: =IF(E31>0,E44/F33,0)
B48: Breakeven Sales Units | E48: =IF(E31>0,E47/E31,0)

Sheet 6. Cash Receipts-Disbursements
A1: ='1. Required Start-Up Funds'!A1 | Q1: =NOW()
A2: Cash Receipts and Disbursements
A6: Accounts Receivable Collections
B7: Percent of Collections
C8: 0 to 30 days | G8: 1
C9: 31 to 60 days | G9: 0
C10: More than 60 days | G10: 0
B11: Total Collections Percentage | G11: =SUM(G8:G10)
A13: Accounts Payable Disbursements
B14: Number of Days to Pay Suppliers
C15: 0 to 30 days | G15: 1
C16: 31 to 60 days | G16: 0
C17: More than 60 days | G17: 0
B18: Total Disbursements Percentage | G18: =SUM(G15:G17)
A20: Line of Credit Assumptions
B21: Desired Minimum Cash Balance | G21: 0
B22: Line of Credit Interest Rate | G22: 0.09
A24: Income Tax Assumptions
B25: Effective Income Tax Rate | G25: 0
J26: =IF(G28=0,0,(('1. Required Start-Up Funds'!G29-'1. Required Start-Up Funds'!E28-'1. Required Start-Up Funds'!E20-'1. Required Start-Up Funds'!E27)/'6. Cash Receipts-Disbursements'!G28)) | K26: =J26/12
A27: Amortization of Start-Up Expenses | J27: =IF(G28=0,0,('1. Required Start-Up Funds'!E27/'6. Cash Receipts-Disbursements'!G28)) | K27: =J27/12
B28: Amortization Period in Years | G28: 3 | K28: =K26+K27

Sheet 7. Beginning Balance Sheet
A1: ='1. Required Start-Up Funds'!A1
A2: Balance Sheet (For Existing Businesses Only)
F6: 39082 | G6: %
A8: Assets
B9: Current Assets
C10: Cash | F10: 0
C11: Accounts Receivable | F11: 0
C12: Inventory | F12: 0
C13: Prepaid Expenses | F13: 0
C14: Other Current | F14: 0
B15: Total Current Assets | F15: =SUM(F10:F14)
B17: Fixed Assets
C18: ='1. Required Start-Up Funds'!C8 | F18: 0
C19: ='1. Required Start-Up Funds'!C9 | F19: 0
C20: ='1. Required Start-Up Funds'!C10 | F20: 0
C21: ='1. Required Start-Up Funds'!C11 | F21: 0
C22: ='1. Required Start-Up Funds'!C12 | F22: 0
C23: ='1. Required Start-Up Funds'!C13 | F23: 0
C24: ='1. Required Start-Up Funds'!C14 | F24: 0
B25: Total Fixed Assets | F25: =SUM(F18:F24)
B27: Less: Accumulated Depreciation | F27: 0
A29: Total Assets | F29: =INT(F15+F25-F27)
A33: Liabilities and Owner's Equity
B34: Liabilities
C35: Accounts Payable | F35: 0
C36: Notes Payable | F36: 0
C37: Mortgage Payable | F37: 0
C38: Line of Credit Balance | F38: 0
B39: Total Liabilities | F39: =SUM(F35:F38)
B41: Owner's Equity
C42: Common Stock | F42: 0
C43: Retained Earnings | F43: 0
C44: Dividends Dispersed | F44: 0
B45: Total Owner's Equity | F45: =F42+F43-F44
A47: Total Liabilities and Owner's Equity | F47: =INT(F39+F45)
F50: =IF(F29=F47,"Statement Balances","Does Not Balance")

Sheet 8. Income Statement
A1: ='1. Required Start-Up Funds'!A1
A2: Projected Income Statement - Year One
E6: ='4. Projected Sales Forecast'!H6 | F6: ='4. Projected Sales Forecast'!I6 | G6: ='4. Projected Sales Forecast'!J6 | H6: ='4. Projected Sales Forecast'!K6 | I6: ='4. Projected Sales Forecast'!L6 | J6: ='4. Projected Sales Forecast'!M6 | K6: ='4. Projected Sales Forecast'!N6 | L6: ='4. Projected Sales Forecast'!O6 | ... P6: ='4. Projected Sales Forecast'!S6 | Q6: Totals
A8: Income
B9: ='4. Projected Sales Forecast'!A8 | E9: ='4. Projected Sales Forecast'!$E$9*'4. Projected Sales Forecast'!H14 | F9: ='4. Projected Sales Forecast'!$E$9*'4. Projected Sales Forecast'!I14 | G9: ='4. Projected Sales Forecast'!$E$9*'4. Projected Sales Forecast'!J14 | H9: ='4. Projected Sales Forecast'!$E$9*'4. Projected Sales Forecast'!K14 | I9: ='4. Projected Sales Forecast'!$E$9*'4. Projected Sales Forecast'!L14 | J9: ='4. Projected Sales Forecast'!$E$9*'4. Projected Sales Forecast'!M14 | K9: ='4. Projected Sales Forecast'!$E$9*'4. Projected Sales Forecast'!N14 | L9: ='4. Projected Sales Forecast'!$E$9*'4. Projected Sales Forecast'!O14 | ... P9: ='4. Projected Sales Forecast'!$E$9*'4. Projected Sales Forecast'!S14 | Q9: =SUM(E9:P9)
B10: ='4. Projected Sales Forecast'!A30 | E10: ='4. Projected Sales Forecast'!$E$31*'4. Projected Sales Forecast'!H36 | F10: ='4. Projected Sales Forecast'!$E$31*'4. Projected Sales Forecast'!I36 | G10: ='4. Projected Sales Forecast'!$E$31*'4. Projected Sales Forecast'!J36 | H10: ='4. Projected Sales Forecast'!$E$31*'4. Projected Sales Forecast'!K36 | I10: ='4. Projected Sales Forecast'!$E$31*'4. Projected Sales Forecast'!L36 | J10: ='4. Projected Sales Forecast'!$E$31*'4. Projected Sales Forecast'!M36 | K10: ='4. Projected Sales Forecast'!$E$31*'4. Projected Sales Forecast'!N36 | L10: ='4. Projected Sales Forecast'!$E$31*'4. Projected Sales Forecast'!O36 | ... P10: ='4. Projected Sales Forecast'!$E$31*'4. Projected Sales Forecast'!S36 | Q10: =SUM(E10:P10)
B11: =IF('5. Projected Sales Forecast (2)'!E9>0,'5. Projected Sales Forecast (2)'!A8,"") | E11: =IF('5. Projected Sales Forecast (2)'!$E$9>0,'5. Projected Sales Forecast (2)'!$E$9*'5. Projected Sales Forecast (2)'!H14,"") | F11: =IF('5. Projected Sales Forecast (2)'!$E$9>0,'5. Projected Sales Forecast (2)'!$E$9*'5. Projected Sales Forecast (2)'!I14,"") | G11: =IF('5. Projected Sales Forecast (2)'!$E$9>0,'5. Projected Sales Forecast (2)'!$E$9*'5. Projected Sales Forecast (2)'!J14,"") | H11: =IF('5. Projected Sales Forecast (2)'!$E$9>0,'5. Projected Sales Forecast (2)'!$E$9*'5. Projected Sales Forecast (2)'!K14,"") | I11: =IF('5. Projected Sales Forecast (2)'!$E$9>0,'5. Projected Sales Forecast (2)'!$E$9*'5. Projected Sales Forecast (2)'!L14,"") | J11: =IF('5. Projected Sales Forecast (2)'!$E$9>0,'5. Projected Sales Forecast (2)'!$E$9*'5. Projected Sales Forecast (2)'!M14,"") | K11: =IF('5. Projected Sales Forecast (2)'!$E$9>0,'5. Projected Sales Forecast (2)'!$E$9*'5. Projected Sales Forecast (2)'!N14,"") | L11: =IF('5. Projected Sales Forecast (2)'!$E$9>0,'5. Projected Sales Forecast (2)'!$E$9*'5. Projected Sales Forecast (2)'!O14,"") | ... P11: =IF('5. Projected Sales Forecast (2)'!$E$9>0,'5. Projected Sales Forecast (2)'!$E$9*'5. Projected Sales Forecast (2)'!S14,"") | Q11: =SUM(E11:P11)
B12: =IF('5. Projected Sales Forecast (2)'!E31>0,'5. Projected Sales Forecast (2)'!A30,"") | E12: =IF('5. Projected Sales Forecast (2)'!$E$31>0,'5. Projected Sales Forecast (2)'!$E$31*'5. Projected Sales Forecast (2)'!H36,"") | F12: =IF('5. Projected Sales Forecast (2)'!$E$31>0,'5. Projected Sales Forecast (2)'!$E$31*'5. Projected Sales Forecast (2)'!I36,"") | G12: =IF('5. Projected Sales Forecast (2)'!$E$31>0,'5. Projected Sales Forecast (2)'!$E$31*'5. Projected Sales Forecast (2)'!J36,"") | H12: =IF('5. Projected Sales Forecast (2)'!$E$31>0,'5. Projected Sales Forecast (2)'!$E$31*'5. Projected Sales Forecast (2)'!K36,"") | I12: =IF('5. Projected Sales Forecast (2)'!$E$31>0,'5. Projected Sales Forecast (2)'!$E$31*'5. Projected Sales Forecast (2)'!L36,"") | J12: =IF('5. Projected Sales Forecast (2)'!$E$31>0,'5. Projected Sales Forecast (2)'!$E$31*'5. Projected Sales Forecast (2)'!M36,"") | K12: =IF('5. Projected Sales Forecast (2)'!$E$31>0,'5. Projected Sales Forecast (2)'!$E$31*'5. Projected Sales Forecast (2)'!N36,"") | L12: =IF('5. Projected Sales Forecast (2)'!$E$31>0,'5. Projected Sales Forecast (2)'!$E$31*'5. Projected Sales Forecast (2)'!O36,"") | ... P12: =IF('5. Projected Sales Forecast (2)'!$E$31>0,'5. Projected Sales Forecast (2)'!$E$31*'5. Projected Sales Forecast (2)'!S36,"") | Q12: =SUM(E12:P12)
A13: Total Income | E13: =SUM(E9:E12) | F13: =SUM(F9:F12) | G13: =SUM(G9:G12) | H13: =SUM(H9:H12) | I13: =SUM(I9:I12) | J13: =SUM(J9:J12) | K13: =SUM(K9:K12) | L13: =SUM(L9:L12) | ... Q13: =SUM(Q9:Q12)
A15: Cost of Sales
B16: =B9 | E16: ='4. Projected Sales Forecast'!$E$10*'4. Projected Sales Forecast'!H14 | F16: ='4. Projected Sales Forecast'!$E$10*'4. Projected Sales Forecast'!I14 | G16: ='4. Projected Sales Forecast'!$E$10*'4. Projected Sales Forecast'!J14 | H16: ='4. Projected Sales Forecast'!$E$10*'4. Projected Sales Forecast'!K14 | I16: ='4. Projected Sales Forecast'!$E$10*'4. Projected Sales Forecast'!L14 | J16: ='4. Projected Sales Forecast'!$E$10*'4. Projected Sales Forecast'!M14 | K16: ='4. Projected Sales Forecast'!$E$10*'4. Projected Sales Forecast'!N14 | L16: ='4. Projected Sales Forecast'!$E$10*'4. Projected Sales Forecast'!O14 | ... P16: ='4. Projected Sales Forecast'!$E$10*'4. Projected Sales Forecast'!S14 | Q16: =SUM(E16:P16)
B17: =B10 | E17: ='4. Projected Sales Forecast'!$E$32*'4. Projected Sales Forecast'!H36 | F17: ='4. Projected Sales Forecast'!$E$32*'4. Projected Sales Forecast'!I36 | G17: ='4. Projected Sales Forecast'!$E$32*'4. Projected Sales Forecast'!J36 | H17: ='4. Projected Sales Forecast'!$E$32*'4. Projected Sales Forecast'!K36 | I17: ='4. Projected Sales Forecast'!$E$32*'4. Projected Sales Forecast'!L36 | J17: ='4. Projected Sales Forecast'!$E$32*'4. Projected Sales Forecast'!M36 | K17: ='4. Projected Sales Forecast'!$E$32*'4. Projected Sales Forecast'!N36 | L17: ='4. Projected Sales Forecast'!$E$32*'4. Projected Sales Forecast'!O36 | ... P17: ='4. Projected Sales Forecast'!$E$32*'4. Projected Sales Forecast'!S36 | Q17: =SUM(E17:P17)
B18: =B11 | E18: =IF('5. Projected Sales Forecast (2)'!$E$10>0,'5. Projected Sales Forecast (2)'!$E$10*'5. Projected Sales Forecast (2)'!H14,"") | F18: =IF('5. Projected Sales Forecast (2)'!$E$10>0,'5. Projected Sales Forecast (2)'!$E$10*'5. Projected Sales Forecast (2)'!I14,"") | G18: =IF('5. Projected Sales Forecast (2)'!$E$10>0,'5. Projected Sales Forecast (2)'!$E$10*'5. Projected Sales Forecast (2)'!J14,"") | H18: =IF('5. Projected Sales Forecast (2)'!$E$10>0,'5. Projected Sales Forecast (2)'!$E$10*'5. Projected Sales Forecast (2)'!K14,"") | I18: =IF('5. Projected Sales Forecast (2)'!$E$10>0,'5. Projected Sales Forecast (2)'!$E$10*'5. Projected Sales Forecast (2)'!L14,"") | J18: =IF('5. Projected Sales Forecast (2)'!$E$10>0,'5. Projected Sales Forecast (2)'!$E$10*'5. Projected Sales Forecast (2)'!M14,"") | K18: =IF('5. Projected Sales Forecast (2)'!$E$10>0,'5. Projected Sales Forecast (2)'!$E$10*'5. Projected Sales Forecast (2)'!N14,"") | L18: =IF('5. Projected Sales Forecast (2)'!$E$10>0,'5. Projected Sales Forecast (2)'!$E$10*'5. Projected Sales Forecast (2)'!O14,"") | ... P18: =IF('5. Projected Sales Forecast (2)'!$E$10>0,'5. Projected Sales Forecast (2)'!$E$10*'5. Projected Sales Forecast (2)'!S14,"") | Q18: =SUM(E18:P18)
B19: =B12 | E19: =IF('5. Projected Sales Forecast (2)'!$E$32>0,'5. Projected Sales Forecast (2)'!$E$32*'5. Projected Sales Forecast (2)'!H36,"") | F19: =IF('5. Projected Sales Forecast (2)'!$E$32>0,'5. Projected Sales Forecast (2)'!$E$32*'5. Projected Sales Forecast (2)'!I36,"") | G19: =IF('5. Projected Sales Forecast (2)'!$E$32>0,'5. Projected Sales Forecast (2)'!$E$32*'5. Projected Sales Forecast (2)'!J36,"") | H19: =IF('5. Projected Sales Forecast (2)'!$E$32>0,'5. Projected Sales Forecast (2)'!$E$32*'5. Projected Sales Forecast (2)'!K36,"") | I19: =IF('5. Projected Sales Forecast (2)'!$E$32>0,'5. Projected Sales Forecast (2)'!$E$32*'5. Projected Sales Forecast (2)'!L36,"") | J19: =IF('5. Projected Sales Forecast (2)'!$E$32>0,'5. Projected Sales Forecast (2)'!$E$32*'5. Projected Sales Forecast (2)'!M36,"") | K19: =IF('5. Projected Sales Forecast (2)'!$E$32>0,'5. Projected Sales Forecast (2)'!$E$32*'5. Projected Sales Forecast (2)'!N36,"") | L19: =IF('5. Projected Sales Forecast (2)'!$E$32>0,'5. Projected Sales Forecast (2)'!$E$32*'5. Projected Sales Forecast (2)'!O36,"") | ... P19: =IF('5. Projected Sales Forecast (2)'!$E$32>0,'5. Projected Sales Forecast (2)'!$E$32*'5. Projected Sales Forecast (2)'!S36,"") | Q19: =SUM(E19:P19)
A20: Total Cost of Sales | E20: =SUM(E16:E19) | F20: =SUM(F16:F19) | G20: =SUM(G16:G19) | H20: =SUM(H16:H19) | I20: =SUM(I16:I19) | J20: =SUM(J16:J19) | K20: =SUM(K16:K19) | L20: =SUM(L16:L19) | ... Q20: =SUM(Q16:Q19)
A22: Gross Margin | E22: =E13-E20 | F22: =F13-F20 | G22: =G13-G20 | H22: =H13-H20 | I22: =I13-I20 | J22: =J13-J20 | K22: =K13-K20 | L22: =L13-L20 | ... Q22: =Q13-Q20
A24: ='2. Salaries and Wages'!A10
B25: ='2. Salaries and Wages'!B11 | E25: ='2. Salaries and Wages'!K11 | F25: =E25 | G25: =F25 | H25: =G25 | I25: =H25 | J25: =I25 | K25: =J25 | L25: =K25 | M25: =L25 | ... P25: =O25 | Q25: =SUM(E25:P25)
B26: ='2. Salaries and Wages'!B12 | E26: ='2. Salaries and Wages'!K12 | F26: =E26 | G26: =F26 | H26: =G26 | I26: =H26 | J26: =I26 | K26: =J26 | L26: =K26 | M26: =L26 | ... P26: =O26 | Q26: =SUM(E26:P26)
B27: ='2. Salaries and Wages'!C14 | E27: ='2. Salaries and Wages'!K14 | F27: =E27 | G27: =F27 | H27: =G27 | I27: =H27 | J27: =I27 | K27: =J27 | L27: =K27 | M27: =L27 | ... P27: =O27 | Q27: =SUM(E27:P27)
B28: ='2. Salaries and Wages'!C17 | E28: ='2. Salaries and Wages'!K17 | F28: =E28 | G28: =F28 | H28: =G28 | I28: =H28 | J28: =I28 | K28: =J28 | L28: =K28 | M28: =L28 | ... P28: =O28 | Q28: =SUM(E28:P28)
B29: ='2. Salaries and Wages'!B20 | E29: ='2. Salaries and Wages'!K20 | F29: =E29 | G29: =F29 | H29: =G29 | I29: =H29 | J29: =I29 | K29: =J29 | L29: =K29 | M29: =L29 | ... P29: =O29 | Q29: =SUM(E29:P29)
B30: ='2. Salaries and Wages'!A23 | E30: ='2. Salaries and Wages'!K32 | F30: =E30 | G30: =F30 | H30: =G30 | I30: =H30 | J30: =I30 | K30: =J30 | L30: =K30 | M30: =L30 | ... P30: =O30 | Q30: =SUM(E30:P30)
A31: Total Salary and Wages | E31: =SUM(E25:E30) | F31: =SUM(F25:F30) | G31: =SUM(G25:G30) | H31: =SUM(H25:H30) | I31: =SUM(I25:I30) | J31: =SUM(J25:J30) | K31: =SUM(K25:K30) | L31: =SUM(L25:L30) | ... Q31: =SUM(Q25:Q30)
A33: Fixed Business Expenses
B34: ='3. Fixed Operating Expenses'!B11 | E34: ='3. Fixed Operating Expenses'!G11 | F34: =E34 | G34: =F34 | H34: =G34 | I34: =H34 | J34: =I34 | K34: =J34 | L34: =K34 | M34: =L34 | ... P34: =O34 | Q34: =SUM(E34:P34)
B35: ='3. Fixed Operating Expenses'!B12 | E35: ='3. Fixed Operating Expenses'!G12 | F35: =E35 | G35: =F35 | H35: =G35 | I35: =H35 | J35: =I35 | K35: =J35 | L35: =K35 | M35: =L35 | ... P35: =O35 | Q35: =SUM(E35:P35)
B36: ='3. Fixed Operating Expenses'!B13 | E36: ='3. Fixed Operating Expenses'!G13 | F36: =E36 | G36: =F36 | H36: =G36 | I36: =H36 | J36: =I36 | K36: =J36 | L36: =K36 | M36: =L36 | ... P36: =O36 | Q36: =SUM(E36:P36)
B37: ='3. Fixed Operating Expenses'!B14 | E37: ='3. Fixed Operating Expenses'!G14 | F37: =E37 | G37: =F37 | H37: =G37 | I37: =H37 | J37: =I37 | K37: =J37 | L37: =K37 | M37: =L37 | ... P37: =O37 | Q37: =SUM(E37:P37)
B38: ='3. Fixed Operating Expenses'!B15 | E38: ='3. Fixed Operating Expenses'!G15 | F38: =E38 | G38: =F38 | H38: =G38 | I38: =H38 | J38: =I38 | K38: =J38 | L38: =K38 | M38: =L38 | ... P38: =O38 | Q38: =SUM(E38:P38)
B39: ='3. Fixed Operating Expenses'!B16 | E39: ='3. Fixed Operating Expenses'!G16 | F39: =E39 | G39: =F39 | H39: =G39 | I39: =H39 | J39: =I39 | K39: =J39 | L39: =K39 | M39: =L39 | ... P39: =O39 | Q39: =SUM(E39:P39)
B40: ='3. Fixed Operating Expenses'!B17 | E40: ='3. Fixed Operating Expenses'!G17 | F40: =E40 | G40: =F40 | H40: =G40 | I40: =H40 | J40: =I40 | K40: =J40 | L40: =K40 | M40: =L40 | ... P40: =O40 | Q40: =SUM(E40:P40)
B41: ='3. Fixed Operating Expenses'!B18 | E41: ='3. Fixed Operating Expenses'!G18 | F41: =E41 | G41: =F41 | H41: =G41 | I41: =H41 | J41: =I41 | K41: =J41 | L41: =K41 | M41: =L41 | ... P41: =O41 | Q41: =SUM(E41:P41)
B42: ='3. Fixed Operating Expenses'!B19 | E42: ='3. Fixed Operating Expenses'!G19 | F42: =E42 | G42: =F42 | H42: =G42 | I42: =H42 | J42: =I42 | K42: =J42 | L42: =K42 | M42: =L42 | ... P42: =O42 | Q42: =SUM(E42:P42)
B43: ='3. Fixed Operating Expenses'!B20 | E43: ='3. Fixed Operating Expenses'!G20 | F43: =E43 | G43: =F43 | H43: =G43 | I43: =H43 | J43: =I43 | K43: =J43 | L43: =K43 | M43: =L43 | ... P43: =O43 | Q43: =SUM(E43:P43)
B44: ='3. Fixed Operating Expenses'!B21 | E44: ='3. Fixed Operating Expenses'!G21 | F44: =E44 | G44: =F44 | H44: =G44 | I44: =H44 | J44: =I44 | K44: =J44 | L44: =K44 | M44: =L44 | ... P44: =O44 | Q44: =SUM(E44:P44)
B45: ='3. Fixed Operating Expenses'!B22 | E45: ='3. Fixed Operating Expenses'!G22 | F45: =E45 | G45: =F45 | H45: =G45 | I45: =H45 | J45: =I45 | K45: =J45 | L45: =K45 | M45: =L45 | ... P45: =O45 | Q45: =SUM(E45:P45)
... B53: ='3. Fixed Operating Expenses'!B30 | E53: ='3. Fixed Operating Expenses'!G30 | F53: =E53 | G53: =F53 | H53: =G53 | I53: =H53 | J53: =I53 | K53: =J53 | L53: =K53 | M53: =L53 | ... P53: =O53 | Q53: =SUM(E53:P53)
A54: Total Fixed Business Expenses | E54: =SUM(E34:E53) | F54: =SUM(F34:F53) | G54: =SUM(G34:G53) | H54: =SUM(H34:H53) | I54: =SUM(I34:I53) | J54: =SUM(J34:J53) | K54: =SUM(K34:K53) | L54: =SUM(L34:L53) | ... Q54: =SUM(Q34:Q53)
A56: Other Expenses
B57: Amortized Start-up Expenses | E57: =IF('6. Cash Receipts-Disbursements'!$G$28>0,'6. Cash Receipts-Disbursements'!$K$28,0) | F57: =IF('6. Cash Receipts-Disbursements'!$G$28>0,'6. Cash Receipts-Disbursements'!$K$28,0) | G57: =IF('6. Cash Receipts-Disbursements'!$G$28>0,'6. Cash Receipts-Disbursements'!$K$28,0) | H57: =IF('6. Cash Receipts-Disbursements'!$G$28>0,'6. Cash Receipts-Disbursements'!$K$28,0) | I57: =IF('6. Cash Receipts-Disbursements'!$G$28>0,'6. Cash Receipts-Disbursements'!$K$28,0) | J57: =IF('6. Cash Receipts-Disbursements'!$G$28>0,'6. Cash Receipts-Disbursements'!$K$28,0) | K57: =IF('6. Cash Receipts-Disbursements'!$G$28>0,'6. Cash Receipts-Disbursements'!$K$28,0) | L57: =IF('6. Cash Receipts-Disbursements'!$G$28>0,'6. Cash Receipts-Disbursements'!$K$28,0) | ... P57: =IF('6. Cash Receipts-Disbursements'!$G$28>0,'6. Cash Receipts-Disbursements'!$K$28,0) | Q57: =SUM(E57:P57)
B58: Depreciation | E58: ='3. Fixed Operating Expenses'!G34 | F58: =E58 | G58: =F58 | H58: =G58 | I58: =H58 | J58: =I58 | K58: =J58 | L58: =K58 | M58: =L58 | ... P58: =O58 | Q58: =SUM(E58:P58)
B59: Interest
C60: Commercial Loan | E60: ='20. Amoritization Schedule'!G15 | F60: ='20. Amoritization Schedule'!H15 | G60: ='20. Amoritization Schedule'!I15 | H60: ='20. Amoritization Schedule'!J15 | I60: ='20. Amoritization Schedule'!K15 | J60: ='20. Amoritization Schedule'!L15 | K60: ='20. Amoritization Schedule'!M15 | L60: ='20. Amoritization Schedule'!N15 | ... P60: ='20. Amoritization Schedule'!R15 | Q60: =SUM(E60:P60)
C61: Commercial Mortgage | E61: ='20. Amoritization Schedule'!G35 | F61: ='20. Amoritization Schedule'!H35 | G61: ='20. Amoritization Schedule'!I35 | H61: ='20. Amoritization Schedule'!J35 | I61: ='20. Amoritization Schedule'!K35 | J61: ='20. Amoritization Schedule'!L35 | K61: ='20. Amoritization Schedule'!M35 | L61: ='20. Amoritization Schedule'!N35 | ... P61: ='20. Amoritization Schedule'!R35 | Q61: =SUM(E61:P61)
C62: Line of Credit | E62: ='9. Cash Flow Statement'!E26 | F62: ='9. Cash Flow Statement'!F26 | G62: ='9. Cash Flow Statement'!G26 | H62: ='9. Cash Flow Statement'!H26 | I62: ='9. Cash Flow Statement'!I26 | J62: ='9. Cash Flow Statement'!J26 | K62: ='9. Cash Flow Statement'!K26 | L62: ='9. Cash Flow Statement'!L26 | ... P62: ='9. Cash Flow Statement'!P26 | Q62: =SUM(E62:P62)
B63: Taxes | E63: =IF(E71>0,(E70)*'6. Cash Receipts-Disbursements'!G25,0) | F63: =IF(F71>0,IF(E71<0,(F70-ABS(E71))*'6. Cash Receipts-Disbursements'!$G$25,'8. Income Statement'!F70*'6. Cash Receipts-Disbursements'!$G$25),IF('8. Income Statement'!E71>0,-('8. Income Statement'!E71*'6. Cash Receipts-Disbursements'!$G$25),0)) | G63: =IF(G71>0,IF(F71<0,(G70-ABS(F71))*'6. Cash Receipts-Disbursements'!$G$25,'8. Income Statement'!G70*'6. Cash Receipts-Disbursements'!$G$25),IF('8. Income Statement'!F71>0,-('8. Income Statement'!F71*'6. Cash Receipts-Disbursements'!$G$25),0)) | H63: =IF(H71>0,IF(G71<0,(H70-ABS(G71))*'6. Cash Receipts-Disbursements'!$G$25,'8. Income Statement'!H70*'6. Cash Receipts-Disbursements'!$G$25),IF('8. Income Statement'!G71>0,-('8. Income Statement'!G71*'6. Cash Receipts-Disbursements'!$G$25),0)) | I63: =IF(I71>0,IF(H71<0,(I70-ABS(H71))*'6. Cash Receipts-Disbursements'!$G$25,'8. Income Statement'!I70*'6. Cash Receipts-Disbursements'!$G$25),IF('8. Income Statement'!H71>0,-('8. Income Statement'!H71*'6. Cash Receipts-Disbursements'!$G$25),0)) | J63: =IF(J71>0,IF(I71<0,(J70-ABS(I71))*'6. Cash Receipts-Disbursements'!$G$25,'8. Income Statement'!J70*'6. Cash Receipts-Disbursements'!$G$25),IF('8. Income Statement'!I71>0,-('8. Income Statement'!I71*'6. Cash Receipts-Disbursements'!$G$25),0)) | K63: =IF(K71>0,IF(J71<0,(K70-ABS(J71))*'6. Cash Receipts-Disbursements'!$G$25,'8. Income Statement'!K70*'6. Cash Receipts-Disbursements'!$G$25),IF('8. Income Statement'!J71>0,-('8. Income Statement'!J71*'6. Cash Receipts-Disbursements'!$G$25),0)) | L63: =IF(L71>0,IF(K71<0,(L70-ABS(K71))*'6. Cash Receipts-Disbursements'!$G$25,'8. Income Statement'!L70*'6. Cash Receipts-Disbursements'!$G$25),IF('8. Income Statement'!K71>0,-('8. Income Statement'!K71*'6. Cash Receipts-Disbursements'!$G$25),0)) | M63: =IF(M71>0,IF(L71<0,(M70-ABS(L71))*'6. Cash Receipts-Disbursements'!$G$25,'8. Income Statement'!M70*'6. Cash Receipts-Disbursements'!$G$25),IF('8. Income Statement'!L71>0,-('8. Income Statement'!L71*'6. Cash Receipts-Disbursements'!$G$25),0)) | ... P63: =IF(P71>0,IF(O71<0,(P70-ABS(O71))*'6. Cash Receipts-Disbursements'!$G$25,'8. Income Statement'!P70*'6. Cash Receipts-Disbursements'!$G$25),IF('8. Income Statement'!O71>0,-('8. Income Statement'!O71*'6. Cash Receipts-Disbursements'!$G$25),0)) | Q63: =SUM(E63:P63)
A64: Total Other Expenses | E64: =SUM(E57:E63) | F64: =SUM(F57:F63) | G64: =SUM(G57:G63) | H64: =SUM(H57:H63) | I64: =SUM(I57:I63) | J64: =SUM(J57:J63) | K64: =SUM(K57:K63) | L64: =SUM(L57:L63) | ... Q64: =SUM(Q57:Q63)
A66: Net Income | E66: =E22-E31-E54-E64 | F66: =F22-F31-F54-F64 | G66: =G22-G31-G54-G64 | H66: =H22-H31-H54-H64 | I66: =I22-I31-I54-I64 | J66: =J22-J31-J54-J64 | K66: =K22-K31-K54-K64 | L66: =L22-L31-L54-L64 | ... Q66: =Q22-Q31-Q54-Q64
E70: =E22-E31-E54-E58-E60-E61-E62 | F70: =F22-F31-F54-F58-F60-F61-F62 | G70: =G22-G31-G54-G58-G60-G61-G62 | H70: =H22-H31-H54-H58-H60-H61-H62 | I70: =I22-I31-I54-I58-I60-I61-I62 | J70: =J22-J31-J54-J58-J60-J61-J62 | K70: =K22-K31-K54-K58-K60-K61-K62 | L70: =L22-L31-L54-L58-L60-L61-L62 | ... P70: =P22-P31-P54-P58-P60-P61-P62
E71: =E70 | F71: =E71+F70 | G71: =F71+G70 | H71: =G71+H70 | I71: =H71+I70 | J71: =I71+J70 | K71: =J71+K70 | L71: =K71+L70 | M71: =L71+M70 | ... P71: =O71+P70

Sheet 9. Cash Flow Statement
A1: ='1. Required Start-Up Funds'!A1
A2: Projected Cash Flow Statement - Year One
E6: ='4. Projected Sales Forecast'!H6 | F6: ='4. Projected Sales Forecast'!I6 | G6: ='4. Projected Sales Forecast'!J6 | H6: ='4. Projected Sales Forecast'!K6 | I6: ='4. Projected Sales Forecast'!L6 | J6: ='4. Projected Sales Forecast'!M6 | K6: ='4. Projected Sales Forecast'!N6 | L6: ='4. Projected Sales Forecast'!O6 | ... P6: ='4. Projected Sales Forecast'!S6 | Q6: Totals
A8: Beginning Cash Balance | E8: ='10. Balance Sheet'!F10 | F8: =E37 | G8: =F37 | H8: =G37 | I8: =H37 | J8: =I37 | K8: =J37 | L8: =K37 | M8: =L37 | ... P8: =O37
A10: Cash Inflows
B11: Income from Sales | E11: ='8. Income Statement'!E13*'6. Cash Receipts-Disbursements'!$G$8 | F11: ='8. Income Statement'!F13*'6. Cash Receipts-Disbursements'!$G$8 | G11: ='8. Income Statement'!G13*'6. Cash Receipts-Disbursements'!$G$8 | H11: ='8. Income Statement'!H13*'6. Cash Receipts-Disbursements'!$G$8 | I11: ='8. Income Statement'!I13*'6. Cash Receipts-Disbursements'!$G$8 | J11: ='8. Income Statement'!J13*'6. Cash Receipts-Disbursements'!$G$8 | K11: ='8. Income Statement'!K13*'6. Cash Receipts-Disbursements'!$G$8 | L11: ='8. Income Statement'!L13*'6. Cash Receipts-Disbursements'!$G$8 | ... P11: ='8. Income Statement'!P13*'6. Cash Receipts-Disbursements'!$G$8 | Q11: =SUM(E11:P11)
B12: Accounts Receivable | E12: 0 | F12: ='8. Income Statement'!E13*'6. Cash Receipts-Disbursements'!G9 | G12: =('8. Income Statement'!F13*'6. Cash Receipts-Disbursements'!$G$9)+('8. Income Statement'!E13*'6. Cash Receipts-Disbursements'!$G$10) | H12: =('8. Income Statement'!G13*'6. Cash Receipts-Disbursements'!$G$9)+('8. Income Statement'!F13*'6. Cash Receipts-Disbursements'!$G$10) | I12: =('8. Income Statement'!H13*'6. Cash Receipts-Disbursements'!$G$9)+('8. Income Statement'!G13*'6. Cash Receipts-Disbursements'!$G$10) | J12: =('8. Income Statement'!I13*'6. Cash Receipts-Disbursements'!$G$9)+('8. Income Statement'!H13*'6. Cash Receipts-Disbursements'!$G$10) | K12: =('8. Income Statement'!J13*'6. Cash Receipts-Disbursements'!$G$9)+('8. Income Statement'!I13*'6. Cash Receipts-Disbursements'!$G$10) | L12: =('8. Income Statement'!K13*'6. Cash Receipts-Disbursements'!$G$9)+('8. Income Statement'!J13*'6. Cash Receipts-Disbursements'!$G$10) | M12: =('8. Income Statement'!L13*'6. Cash Receipts-Disbursements'!$G$9)+('8. Income Statement'!K13*'6. Cash Receipts-Disbursements'!$G$10) | N12: =('8. Income Statement'!M13*'6. Cash Receipts-Disbursements'!$G$9)+('8. Income Statement'!L13*'6. Cash Receipts-Disbursements'!$G$10) | ... P12: =('8. Income Statement'!O13*'6. Cash Receipts-Disbursements'!$G$9)+('8. Income Statement'!N13*'6. Cash Receipts-Disbursements'!$G$10) | Q12: =SUM(E12:P12)
A13: Total Cash Inflows | E13: =SUM(E11:E12) | F13: =SUM(F11:F12) | G13: =SUM(G11:G12) | H13: =SUM(H11:H12) | I13: =SUM(I11:I12) | J13: =SUM(J11:J12) | K13: =SUM(K11:K12) | L13: =SUM(L11:L12) | ... Q13: =SUM(Q11:Q12)
A15: Cash Outflows
B16: Investing Activities
C17: New Capital Purchases | E17: 0 | F17: 0 | G17: 0 | H17: 0 | I17: 0 | J17: 0 | K17: 0 | L17: 0 | M17: 0 | N17: 0 | O17: 0 | P17: 0 | Q17: =SUM(E17:P17)
C18: Inventory Purchases | E18: 0 | F18: 0 | G18: 0 | H18: 0 | I18: 0 | J18: 0 | K18: 0 | L18: 0 | M18: 0 | N18: 0 | O18: 0 | P18: 0 | Q18: =SUM(E18:P18)
C19: Cost of Sales | E19: ='8. Income Statement'!E20*'6. Cash Receipts-Disbursements'!G15 | F19: =('8. Income Statement'!F20*'6. Cash Receipts-Disbursements'!G15)+('8. Income Statement'!E20*'6. Cash Receipts-Disbursements'!G16) | G19: =('8. Income Statement'!G20*'6. Cash Receipts-Disbursements'!$G$15)+('8. Income Statement'!F20*'6. Cash Receipts-Disbursements'!$G$16)+('8. Income Statement'!E20*'6. Cash Receipts-Disbursements'!$G$17) | H19: =('8. Income Statement'!H20*'6. Cash Receipts-Disbursements'!$G$15)+('8. Income Statement'!G20*'6. Cash Receipts-Disbursements'!$G$16)+('8. Income Statement'!F20*'6. Cash Receipts-Disbursements'!$G$17) | I19: =('8. Income Statement'!I20*'6. Cash Receipts-Disbursements'!$G$15)+('8. Income Statement'!H20*'6. Cash Receipts-Disbursements'!$G$16)+('8. Income Statement'!G20*'6. Cash Receipts-Disbursements'!$G$17) | J19: =('8. Income Statement'!J20*'6. Cash Receipts-Disbursements'!$G$15)+('8. Income Statement'!I20*'6. Cash Receipts-Disbursements'!$G$16)+('8. Income Statement'!H20*'6. Cash Receipts-Disbursements'!$G$17) | K19: =('8. Income Statement'!K20*'6. Cash Receipts-Disbursements'!$G$15)+('8. Income Statement'!J20*'6. Cash Receipts-Disbursements'!$G$16)+('8. Income Statement'!I20*'6. Cash Receipts-Disbursements'!$G$17) | L19: =('8. Income Statement'!L20*'6. Cash Receipts-Disbursements'!$G$15)+('8. Income Statement'!K20*'6. Cash Receipts-Disbursements'!$G$16)+('8. Income Statement'!J20*'6. Cash Receipts-Disbursements'!$G$17) | M19: =('8. Income Statement'!M20*'6. Cash Receipts-Disbursements'!$G$15)+('8. Income Statement'!L20*'6. Cash Receipts-Disbursements'!$G$16)+('8. Income Statement'!K20*'6. Cash Receipts-Disbursements'!$G$17) | N19: =('8. Income Statement'!N20*'6. Cash Receipts-Disbursements'!$G$15)+('8. Income Statement'!M20*'6. Cash Receipts-Disbursements'!$G$16)+('8. Income Statement'!L20*'6. Cash Receipts-Disbursements'!$G$17) | ... P19: =('8. Income Statement'!P20*'6. Cash Receipts-Disbursements'!$G$15)+('8. Income Statement'!O20*'6. Cash Receipts-Disbursements'!$G$16)+('8. Income Statement'!N20*'6. Cash Receipts-Disbursements'!$G$17) | Q19: =SUM(E19:P19)
B20: Operating Activities
C21: ='8. Income Statement'!A24 | E21: ='8. Income Statement'!E31 | F21: ='8. Income Statement'!F31 | G21: ='8. Income Statement'!G31 | H21: ='8. Income Statement'!H31 | I21: ='8. Income Statement'!I31 | J21: ='8. Income Statement'!J31 | K21: ='8. Income Statement'!K31 | L21: ='8. Income Statement'!L31 | ... P21: ='8. Income Statement'!P31 | Q21: =SUM(E21:P21)
C22: ='8. Income Statement'!A33 | E22: ='8. Income Statement'!E54 | F22: ='8. Income Statement'!F54 | G22: ='8. Income Statement'!G54 | H22: ='8. Income Statement'!H54 | I22: ='8. Income Statement'!I54 | J22: ='8. Income Statement'!J54 | K22: ='8. Income Statement'!K54 | L22: ='8. Income Statement'!L54 | ... P22: ='8. Income Statement'!P54 | Q22: =SUM(E22:P22)
C23: Taxes | E23: 0 | F23: 0 | G23: =SUM('8. Income Statement'!E63:G63) | H23: 0 | I23: 0 | J23: =SUM('8. Income Statement'!H63:J63) | K23: 0 | L23: 0 | M23: =SUM('8. Income Statement'!K63:M63) | N23: 0 | O23: 0 | P23: =SUM('8. Income Statement'!N63:P63) | Q23: =SUM(E23:P23)
B24: Financing Activities | Q24: =SUM(E24:P24)
C25: Loan Payments | E25: ='1. Required Start-Up Funds'!J42 | F25: =E25 | G25: =F25 | H25: =G25 | I25: =H25 | J25: =I25 | K25: =J25 | L25: =K25 | M25: =L25 | ... P25: =O25 | Q25: =SUM(E25:P25)
C26: Line of Credit Interest | E26: 0 | F26: =('6. Cash Receipts-Disbursements'!$G$22/12)*E40 | G26: =('6. Cash Receipts-Disbursements'!$G$22/12)*F40 | H26: =('6. Cash Receipts-Disbursements'!$G$22/12)*G40 | I26: =('6. Cash Receipts-Disbursements'!$G$22/12)*H40 | J26: =('6. Cash Receipts-Disbursements'!$G$22/12)*I40 | K26: =('6. Cash Receipts-Disbursements'!$G$22/12)*J40 | L26: =('6. Cash Receipts-Disbursements'!$G$22/12)*K40 | M26: =('6. Cash Receipts-Disbursements'!$G$22/12)*L40 | ... P26: =('6. Cash Receipts-Disbursements'!$G$22/12)*O40 | Q26: =SUM(E26:P26)
C27: Line of Credit Repayments | E27: 0 | F27: 0 | G27: 0 | H27: 0 | I27: 0 | J27: 0 | K27: 0 | L27: 0 | M27: 0 | N27: 0 | O27: 0 | P27: 0 | Q27: =SUM(E27:P27)
C28: Dividends Paid | E28: 0 | F28: 0 | G28: 0 | H28: 0 | I28: 0 | J28: 0 | K28: 0 | L28: 0 | M28: 0 | N28: 0 | O28: 0 | P28: 0 | Q28: =SUM(E28:P28)
A29: Total Cash Outflows | E29: =SUM(E17:E28) | F29: =SUM(F17:F28) | G29: =SUM(G17:G28) | H29: =SUM(H17:H28) | I29: =SUM(I17:I28) | J29: =SUM(J17:J28) | K29: =SUM(K17:K28) | L29: =SUM(L17:L28) | ... Q29: =SUM(Q17:Q28)
A31: Cash Flow | E31: =E13-E29 | F31: =F13-F29 | G31: =G13-G29 | H31: =H13-H29 | I31: =I13-I29 | J31: =J13-J29 | K31: =K13-K29 | L31: =L13-L29 | ... Q31: =Q13-Q29
A33: Operating Cash Balance | E33: =E8+E31 | F33: =F8+F31 | G33: =G8+G31 | H33: =H8+H31 | I33: =I8+I31 | J33: =J8+J31 | K33: =K8+K31 | L33: =L8+L31 | ... P33: =P8+P31
A35: Line of Credit Drawdowns | E35: =IF((E33-'6. Cash Receipts-Disbursements'!$G$21)<0,'6. Cash Receipts-Disbursements'!$G$21-'9. Cash Flow Statement'!E33,0) | F35: =IF((F33-'6. Cash Receipts-Disbursements'!$G$21)<0,'6. Cash Receipts-Disbursements'!$G$21-'9. Cash Flow Statement'!F33,0) | G35: =IF((G33-'6. Cash Receipts-Disbursements'!$G$21)<0,'6. Cash Receipts-Disbursements'!$G$21-'9. Cash Flow Statement'!G33,0) | H35: =IF((H33-'6. Cash Receipts-Disbursements'!$G$21)<0,'6. Cash Receipts-Disbursements'!$G$21-'9. Cash Flow Statement'!H33,0) | I35: =IF((I33-'6. Cash Receipts-Disbursements'!$G$21)<0,'6. Cash Receipts-Disbursements'!$G$21-'9. Cash Flow Statement'!I33,0) | J35: =IF((J33-'6. Cash Receipts-Disbursements'!$G$21)<0,'6. Cash Receipts-Disbursements'!$G$21-'9. Cash Flow Statement'!J33,0) | K35: =IF((K33-'6. Cash Receipts-Disbursements'!$G$21)<0,'6. Cash Receipts-Disbursements'!$G$21-'9. Cash Flow Statement'!K33,0) | L35: =IF((L33-'6. Cash Receipts-Disbursements'!$G$21)<0,'6. Cash Receipts-Disbursements'!$G$21-'9. Cash Flow Statement'!L33,0) | ... P35: =IF((P33-'6. Cash Receipts-Disbursements'!$G$21)<0,'6. Cash Receipts-Disbursements'!$G$21-'9. Cash Flow Statement'!P33,0) | Q35: =SUM(E35:P35)
A37: Ending Cash Balance | E37: =E33+E35 | F37: =F33+F35 | G37: =G33+G35 | H37: =H33+H35 | I37: =I33+I35 | J37: =J33+J35 | K37: =K33+K35 | L37: =L33+L35 | ... P37: =P33+P35
A40: Line of Credit Balance | E40: =E35 | F40: =E40+F35-F27 | G40: =F40+G35-G27 | H40: =G40+H35-H27 | I40: =H40+I35-I27 | J40: =I40+J35-J27 | K40: =J40+K35-K27 | L40: =K40+L35-L27 | M40: =L40+M35-M27 | ... P40: =O40+P35-P27

Sheet 10. Balance Sheet
A1: ='1. Required Start-Up Funds'!A1
A2: Balance Sheet - Year One
F6: Base Period | I6: End of Year One
A8: Assets
B9: Current Assets
C10: Cash | F10: ='1. Required Start-Up Funds'!E28+'7. Beginning Balance Sheet'!F10 | I10: ='9. Cash Flow Statement'!P37
C11: Accounts Receivable | F11: ='7. Beginning Balance Sheet'!F11 | I11: =F11+'8. Income Statement'!Q13-'9. Cash Flow Statement'!Q13
C12: Inventory | F12: ='1. Required Start-Up Funds'!E20+'7. Beginning Balance Sheet'!F12 | I12: =F12
C13: Prepaid Expenses | F13: ='1. Required Start-Up Funds'!G29-'1. Required Start-Up Funds'!E28-'1. Required Start-Up Funds'!E20-'1. Required Start-Up Funds'!E27+'7. Beginning Balance Sheet'!F13 | I13: =F13-'6. Cash Receipts-Disbursements'!J26
C14: Other Current | F14: ='1. Required Start-Up Funds'!E27 | I14: =F14-'6. Cash Receipts-Disbursements'!J27
B15: Total Current Assets | F15: =SUM(F10:F14) | I15: =SUM(I10:I14)
B17: Fixed Assets
C18: ='1. Required Start-Up Funds'!C8 | F18: ='1. Required Start-Up Funds'!E8+'7. Beginning Balance Sheet'!F18 | I18: =F18
C19: ='1. Required Start-Up Funds'!C9 | F19: ='1. Required Start-Up Funds'!E9+'7. Beginning Balance Sheet'!F19 | I19: =F19
C20: ='1. Required Start-Up Funds'!C10 | F20: ='1. Required Start-Up Funds'!E10+'7. Beginning Balance Sheet'!F20 | I20: =F20
C21: ='1. Required Start-Up Funds'!C11 | F21: ='1. Required Start-Up Funds'!E11+'7. Beginning Balance Sheet'!F21 | I21: =F21
C22: ='1. Required Start-Up Funds'!C12 | F22: ='1. Required Start-Up Funds'!E12+'7. Beginning Balance Sheet'!F22 | I22: =F22
C23: ='1. Required Start-Up Funds'!C13 | F23: ='1. Required Start-Up Funds'!E13+'7. Beginning Balance Sheet'!F23 | I23: =F23
C24: ='1. Required Start-Up Funds'!C14 | F24: ='7. Beginning Balance Sheet'!F24+'1. Required Start-Up Funds'!E14 | I24: =F24+'9. Cash Flow Statement'!Q17
B25: Total Fixed Assets | F25: =SUM(F18:F24) | I25: =SUM(I18:I24)
B27: Less: Accumulated Depreciation | F27: ='7. Beginning Balance Sheet'!F27 | I27: =F27+'8. Income Statement'!Q58
A29: Total Assets | F29: =INT(F15+F25-F27) | I29: =INT(I15+I25-I27)
A33: Liabilities and Owner's Equity
B34: Liabilities
C35: Accounts Payable | F35: ='7. Beginning Balance Sheet'!F35 | I35: ='8. Income Statement'!Q20-'9. Cash Flow Statement'!Q19+F35
C36: Notes Payable | F36: ='1. Required Start-Up Funds'!G40+'7. Beginning Balance Sheet'!F36 | I36: ='20. Amoritization Schedule'!R17+'7. Beginning Balance Sheet'!F36
C37: Mortgage Payable | F37: ='1. Required Start-Up Funds'!G41+'7. Beginning Balance Sheet'!F37 | I37: ='20. Amoritization Schedule'!R37+'7. Beginning Balance Sheet'!F37
C38: Line of Credit Balance | F38: ='7. Beginning Balance Sheet'!F38 | I38: ='9. Cash Flow Statement'!P40+F38
B39: Total Liabilities | F39: =SUM(F35:F38) | I39: =SUM(I35:I38)
B41: Owner's Equity
C42: Common Stock | F42: ='1. Required Start-Up Funds'!G37+'1. Required Start-Up Funds'!G38+'7. Beginning Balance Sheet'!F42 | I42: =F42
C43: Retained Earnings | F43: ='7. Beginning Balance Sheet'!F43 | I43: ='8. Income Statement'!Q66+F43
C44: Dividends Dispersed | F44: ='7. Beginning Balance Sheet'!F44 | I44: ='9. Cash Flow Statement'!Q28+F44
B45: Total Owner's Equity | F45: =F42+F43-F44 | I45: =I42+I43-I44
A47: Total Liabilities and Owner's Equity | F47: =INT(F39+F45) | I47: =INT(I39+I45)
F50: =IF(F29=F47,"Statement Balances","Does Not Balance") | I50: =IF(I29-I47=0,"Statement Balances","Does Not Balance")

Sheet 11. Year End Summary
A1: ='1. Required Start-Up Funds'!A1
A2: Year End Summary
F6: Year One | G6: % | I6: Year Two | J6: % | L6: Year Three | M6: %
A8: ='8. Income Statement'!A8
B9: ='8. Income Statement'!B9 | F9: ='8. Income Statement'!Q9 | I9: ='12. Income Statement (2)'!Q9 | L9: ='15. Income Statement (3)'!Q9
B10: ='8. Income Statement'!B10 | F10: ='8. Income Statement'!Q10 | I10: ='12. Income Statement (2)'!Q10 | L10: ='15. Income Statement (3)'!Q10
B11: ='8. Income Statement'!B11 | F11: ='8. Income Statement'!Q11 | I11: ='12. Income Statement (2)'!Q11 | L11: ='15. Income Statement (3)'!Q11
B12: ='8. Income Statement'!B12 | F12: ='8. Income Statement'!Q12 | I12: ='12. Income Statement (2)'!Q12 | L12: ='15. Income Statement (3)'!Q12
A13: ='8. Income Statement'!A13 | F13: ='8. Income Statement'!Q13 | G13: 1 | I13: =SUM(I9:I12) | J13: 1 | L13: =SUM(L9:L12) | M13: 1
A15: ='8. Income Statement'!A15
B16: ='8. Income Statement'!B16 | F16: ='8. Income Statement'!Q16 | I16: ='12. Income Statement (2)'!Q16 | L16: ='15. Income Statement (3)'!Q16
B17: ='8. Income Statement'!B17 | F17: ='8. Income Statement'!Q17 | I17: ='12. Income Statement (2)'!Q17 | L17: ='15. Income Statement (3)'!Q17
B18: ='8. Income Statement'!B18 | F18: ='8. Income Statement'!Q18 | I18: ='12. Income Statement (2)'!Q18 | L18: ='15. Income Statement (3)'!Q18
B19: ='8. Income Statement'!B19 | F19: ='8. Income Statement'!Q19 | I19: ='12. Income Statement (2)'!Q19 | L19: ='15. Income Statement (3)'!Q19
A20: ='8. Income Statement'!A20 | F20: =SUM(F16:F19) | G20: =IF(F20=0,0,F20/F13) | I20: =SUM(I16:I19) | J20: =IF(I20=0,0,I20/I13) | L20: =SUM(L16:L19) | M20: =IF(L20=0,0,L20/L13)
A22: ='8. Income Statement'!A22 | F22: ='8. Income Statement'!Q22 | G22: =IF(F22=0,0,F22/F13) | I22: ='12. Income Statement (2)'!Q22 | J22: =IF(I22=0,0,I22/I13) | L22: ='15. Income Statement (3)'!Q22 | M22: =IF(L22=0,0,L22/L13)
A24: ='8. Income Statement'!A24
B25: ='8. Income Statement'!B25 | F25: ='8. Income Statement'!Q25 | I25: ='12. Income Statement (2)'!Q25 | L25: ='15. Income Statement (3)'!Q25
B26: ='8. Income Statement'!B26 | F26: ='8. Income Statement'!Q26 | I26: ='12. Income Statement (2)'!Q26 | L26: ='15. Income Statement (3)'!Q26
B27: ='8. Income Statement'!B27 | F27: ='8. Income Statement'!Q27 | I27: ='12. Income Statement (2)'!Q27 | L27: ='15. Income Statement (3)'!Q27
B28: ='8. Income Statement'!B28 | F28: ='8. Income Statement'!Q28 | I28: ='12. Income Statement (2)'!Q28 | L28: ='15. Income Statement (3)'!Q28
B29: ='8. Income Statement'!B29 | F29: ='8. Income Statement'!Q29 | I29: ='12. Income Statement (2)'!Q29 | L29: ='15. Income Statement (3)'!Q29
B30: ='8. Income Statement'!B30 | F30: ='8. Income Statement'!Q30 | I30: ='12. Income Statement (2)'!Q30 | L30: ='15. Income Statement (3)'!Q30
A31: ='8. Income Statement'!A31 | F31: =SUM(F25:F30) | G31: =IF(F31=0,0,F31/F13) | I31: =SUM(I25:I30) | J31: =IF(I31=0,0,I31/I13) | L31: =SUM(L25:L30) | M31: =IF(L31=0,0,L31/L13)
A33: ='8. Income Statement'!A33
B34: ='8. Income Statement'!B34 | F34: ='8. Income Statement'!Q34 | I34: ='12. Income Statement (2)'!Q34 | L34: ='15. Income Statement (3)'!Q34
B35: ='8. Income Statement'!B35 | F35: ='8. Income Statement'!Q35 | I35: ='12. Income Statement (2)'!Q35 | L35: ='15. Income Statement (3)'!Q35
B36: ='8. Income Statement'!B36 | F36: ='8. Income Statement'!Q36 | I36: ='12. Income Statement (2)'!Q36 | L36: ='15. Income Statement (3)'!Q36
B37: ='8. Income Statement'!B37 | F37: ='8. Income Statement'!Q37 | I37: ='12. Income Statement (2)'!Q37 | L37: ='15. Income Statement (3)'!Q37
B38: ='8. Income Statement'!B38 | F38: ='8. Income Statement'!Q38 | I38: ='12. Income Statement (2)'!Q38 | L38: ='15. Income Statement (3)'!Q38
B39: ='8. Income Statement'!B39 | F39: ='8. Income Statement'!Q39 | I39: ='12. Income Statement (2)'!Q39 | L39: ='15. Income Statement (3)'!Q39
B40: ='8. Income Statement'!B40 | F40: ='8. Income Statement'!Q40 | I40: ='12. Income Statement (2)'!Q40 | L40: ='15. Income Statement (3)'!Q40
B41: ='8. Income Statement'!B41 | F41: ='8. Income Statement'!Q41 | I41: ='12. Income Statement (2)'!Q41 | L41: ='15. Income Statement (3)'!Q41
B42: ='8. Income Statement'!B42 | F42: ='8. Income Statement'!Q42 | I42: ='12. Income Statement (2)'!Q42 | L42: ='15. Income Statement (3)'!Q42
B43: ='8. Income Statement'!B43 | F43: ='8. Income Statement'!Q43 | I43: ='12. Income Statement (2)'!Q43 | L43: ='15. Income Statement (3)'!Q43
B44: ='8. Income Statement'!B44 | F44: ='8. Income Statement'!Q44 | I44: ='12. Income Statement (2)'!Q44 | L44: ='15. Income Statement (3)'!Q44
B45: ='8. Income Statement'!B45 | F45: ='8. Income Statement'!Q45 | I45: ='12. Income Statement (2)'!Q45 | L45: ='15. Income Statement (3)'!Q45
... B53: ='8. Income Statement'!B53 | F53: ='8. Income Statement'!Q53 | I53: ='12. Income Statement (2)'!Q53 | L53: ='15. Income Statement (3)'!Q53
A54: ='8. Income Statement'!A54 | F54: =SUM(F34:F53) | G54: =IF(F54=0,0,F54/F13) | I54: =SUM(I34:I53) | J54: =IF(I54=0,0,I54/I13) | L54: =SUM(L34:L53) | M54: =IF(L54=0,0,L54/L13)
A56: ='8. Income Statement'!A56
B57: Amortized Start-up Expenses | F57: ='8. Income Statement'!Q57 | I57: ='12. Income Statement (2)'!Q57 | L57: ='15. Income Statement (3)'!Q57
B58: ='8. Income Statement'!B58 | F58: ='8. Income Statement'!Q58 | I58: ='12. Income Statement (2)'!Q58 | L58: ='15. Income Statement (3)'!Q58
B59: ='8. Income Statement'!B59
C60: ='8. Income Statement'!C60 | F60: ='8. Income Statement'!Q60 | I60: ='12. Income Statement (2)'!Q60 | L60: ='15. Income Statement (3)'!Q60
C61: ='8. Income Statement'!C61 | F61: ='8. Income Statement'!Q61 | I61: ='12. Income Statement (2)'!Q61 | L61: ='15. Income Statement (3)'!Q61
C62: ='8. Income Statement'!C62 | F62: ='8. Income Statement'!Q62 | I62: ='12. Income Statement (2)'!Q62 | L62: ='15. Income Statement (3)'!Q62
B63: ='8. Income Statement'!B63 | F63: ='8. Income Statement'!Q63 | I63: ='12. Income Statement (2)'!Q63 | L63: ='15. Income Statement (3)'!Q63
A64: ='8. Income Statement'!A64 | F64: =SUM(F57:F63) | G64: =IF(F64=0,0,F64/F13) | I64: =SUM(I57:I63) | J64: =IF(I64=0,0,I64/I13) | L64: =SUM(L57:L63) | M64: =IF(L64=0,0,L64/L13)
A66: ='8. Income Statement'!A66 | F66: ='8. Income Statement'!Q66 | G66: =IF(F66=0,0,F66/F13) | I66: ='12. Income Statement (2)'!Q66 | J66: =IF(I66=0,0,I66/I13) | L66: ='15. Income Statement (3)'!Q66 | M66: =IF(L66=0,0,L66/L13)

Sheet 12. Income Statement (2)
A1: ='1. Required Start-Up Funds'!A1
A2: Projected Income Statement - Year Two
E6: ='4. Projected Sales Forecast'!H6 | F6: ='4. Projected Sales Forecast'!I6 | G6: ='4. Projected Sales Forecast'!J6 | H6: ='4. Projected Sales Forecast'!K6 | I6: ='4. Projected Sales Forecast'!L6 | J6: ='4. Projected Sales Forecast'!M6 | K6: ='4. Projected Sales Forecast'!N6 | L6: ='4. Projected Sales Forecast'!O6 | ... P6: ='4. Projected Sales Forecast'!S6 | Q6: Totals
A8: Income
B9: ='4. Projected Sales Forecast'!A8 | E9: ='4. Projected Sales Forecast'!$E$9*'4. Projected Sales Forecast'!H15 | F9: ='4. Projected Sales Forecast'!$E$9*'4. Projected Sales Forecast'!I15 | G9: ='4. Projected Sales Forecast'!$E$9*'4. Projected Sales Forecast'!J15 | H9: ='4. Projected Sales Forecast'!$E$9*'4. Projected Sales Forecast'!K15 | I9: ='4. Projected Sales Forecast'!$E$9*'4. Projected Sales Forecast'!L15 | J9: ='4. Projected Sales Forecast'!$E$9*'4. Projected Sales Forecast'!M15 | K9: ='4. Projected Sales Forecast'!$E$9*'4. Projected Sales Forecast'!N15 | L9: ='4. Projected Sales Forecast'!$E$9*'4. Projected Sales Forecast'!O15 | ... P9: ='4. Projected Sales Forecast'!$E$9*'4. Projected Sales Forecast'!S15 | Q9: =SUM(E9:P9)
B10: ='4. Projected Sales Forecast'!A30 | E10: ='4. Projected Sales Forecast'!$E$31*'4. Projected Sales Forecast'!H37 | F10: ='4. Projected Sales Forecast'!$E$31*'4. Projected Sales Forecast'!I37 | G10: ='4. Projected Sales Forecast'!$E$31*'4. Projected Sales Forecast'!J37 | H10: ='4. Projected Sales Forecast'!$E$31*'4. Projected Sales Forecast'!K37 | I10: ='4. Projected Sales Forecast'!$E$31*'4. Projected Sales Forecast'!L37 | J10: ='4. Projected Sales Forecast'!$E$31*'4. Projected Sales Forecast'!M37 | K10: ='4. Projected Sales Forecast'!$E$31*'4. Projected Sales Forecast'!N37 | L10: ='4. Projected Sales Forecast'!$E$31*'4. Projected Sales Forecast'!O37 | ... P10: ='4. Projected Sales Forecast'!$E$31*'4. Projected Sales Forecast'!S37 | Q10: =SUM(E10:P10)
B11: =IF('5. Projected Sales Forecast (2)'!E9>0,'5. Projected Sales Forecast (2)'!A8,"") | E11: =IF('5. Projected Sales Forecast (2)'!$E$9>0,'5. Projected Sales Forecast (2)'!$E$9*'5. Projected Sales Forecast (2)'!H15,"") | F11: =IF('5. Projected Sales Forecast (2)'!$E$9>0,'5. Projected Sales Forecast (2)'!$E$9*'5. Projected Sales Forecast (2)'!I15,"") | G11: =IF('5. Projected Sales Forecast (2)'!$E$9>0,'5. Projected Sales Forecast (2)'!$E$9*'5. Projected Sales Forecast (2)'!J15,"") | H11: =IF('5. Projected Sales Forecast (2)'!$E$9>0,'5. Projected Sales Forecast (2)'!$E$9*'5. Projected Sales Forecast (2)'!K15,"") | I11: =IF('5. Projected Sales Forecast (2)'!$E$9>0,'5. Projected Sales Forecast (2)'!$E$9*'5. Projected Sales Forecast (2)'!L15,"") | J11: =IF('5. Projected Sales Forecast (2)'!$E$9>0,'5. Projected Sales Forecast (2)'!$E$9*'5. Projected Sales Forecast (2)'!M15,"") | K11: =IF('5. Projected Sales Forecast (2)'!$E$9>0,'5. Projected Sales Forecast (2)'!$E$9*'5. Projected Sales Forecast (2)'!N15,"") | L11: =IF('5. Projected Sales Forecast (2)'!$E$9>0,'5. Projected Sales Forecast (2)'!$E$9*'5. Projected Sales Forecast (2)'!O15,"") | ... P11: =IF('5. Projected Sales Forecast (2)'!$E$9>0,'5. Projected Sales Forecast (2)'!$E$9*'5. Projected Sales Forecast (2)'!S15,"") | Q11: =SUM(E11:P11)
B12: =IF('5. Projected Sales Forecast (2)'!E31>0,'5. Projected Sales Forecast (2)'!A30,"") | E12: =IF('5. Projected Sales Forecast (2)'!$E$31>0,'5. Projected Sales Forecast (2)'!$E$31*'5. Projected Sales Forecast (2)'!H37,"") | F12: =IF('5. Projected Sales Forecast (2)'!$E$31>0,'5. Projected Sales Forecast (2)'!$E$31*'5. Projected Sales Forecast (2)'!I37,"") | G12: =IF('5. Projected Sales Forecast (2)'!$E$31>0,'5. Projected Sales Forecast (2)'!$E$31*'5. Projected Sales Forecast (2)'!J37,"") | H12: =IF('5. Projected Sales Forecast (2)'!$E$31>0,'5. Projected Sales Forecast (2)'!$E$31*'5. Projected Sales Forecast (2)'!K37,"") | I12: =IF('5. Projected Sales Forecast (2)'!$E$31>0,'5. Projected Sales Forecast (2)'!$E$31*'5. Projected Sales Forecast (2)'!L37,"") | J12: =IF('5. Projected Sales Forecast (2)'!$E$31>0,'5. Projected Sales Forecast (2)'!$E$31*'5. Projected Sales Forecast (2)'!M37,"") | K12: =IF('5. Projected Sales Forecast (2)'!$E$31>0,'5. Projected Sales Forecast (2)'!$E$31*'5. Projected Sales Forecast (2)'!N37,"") | L12: =IF('5. Projected Sales Forecast (2)'!$E$31>0,'5. Projected Sales Forecast (2)'!$E$31*'5. Projected Sales Forecast (2)'!O37,"") | ... P12: =IF('5. Projected Sales Forecast (2)'!$E$31>0,'5. Projected Sales Forecast (2)'!$E$31*'5. Projected Sales Forecast (2)'!S37,"") | Q12: =SUM(E12:P12)
A13: Total Income | E13: =SUM(E9:E12) | F13: =SUM(F9:F12) | G13: =SUM(G9:G12) | H13: =SUM(H9:H12) | I13: =SUM(I9:I12) | J13: =SUM(J9:J12) | K13: =SUM(K9:K12) | L13: =SUM(L9:L12) | ... Q13: =SUM(Q9:Q12)
A15: Cost of Sales
B16: =B9 | E16: ='4. Projected Sales Forecast'!$E$10*'4. Projected Sales Forecast'!H15 | F16: ='4. Projected Sales Forecast'!$E$10*'4. Projected Sales Forecast'!I15 | G16: ='4. Projected Sales Forecast'!$E$10*'4. Projected Sales Forecast'!J15 | H16: ='4. Projected Sales Forecast'!$E$10*'4. Projected Sales Forecast'!K15 | I16: ='4. Projected Sales Forecast'!$E$10*'4. Projected Sales Forecast'!L15 | J16: ='4. Projected Sales Forecast'!$E$10*'4. Projected Sales Forecast'!M15 | K16: ='4. Projected Sales Forecast'!$E$10*'4. Projected Sales Forecast'!N15 | L16: ='4. Projected Sales Forecast'!$E$10*'4. Projected Sales Forecast'!O15 | ... P16: ='4. Projected Sales Forecast'!$E$10*'4. Projected Sales Forecast'!S15 | Q16: =SUM(E16:P16)
B17: =B10 | E17: ='4. Projected Sales Forecast'!$E$32*'4. Projected Sales Forecast'!H37 | F17: ='4. Projected Sales Forecast'!$E$32*'4. Projected Sales Forecast'!I37 | G17: ='4. Projected Sales Forecast'!$E$32*'4. Projected Sales Forecast'!J37 | H17: ='4. Projected Sales Forecast'!$E$32*'4. Projected Sales Forecast'!K37 | I17: ='4. Projected Sales Forecast'!$E$32*'4. Projected Sales Forecast'!L37 | J17: ='4. Projected Sales Forecast'!$E$32*'4. Projected Sales Forecast'!M37 | K17: ='4. Projected Sales Forecast'!$E$32*'4. Projected Sales Forecast'!N37 | L17: ='4. Projected Sales Forecast'!$E$32*'4. Projected Sales Forecast'!O37 | ... P17: ='4. Projected Sales Forecast'!$E$32*'4. Projected Sales Forecast'!S37 | Q17: =SUM(E17:P17)
B18: =B11 | E18: =IF('5. Projected Sales Forecast (2)'!$E$10>0,'5. Projected Sales Forecast (2)'!$E$10*'5. Projected Sales Forecast (2)'!H15,"") | F18: =IF('5. Projected Sales Forecast (2)'!$E$10>0,'5. Projected Sales Forecast (2)'!$E$10*'5. Projected Sales Forecast (2)'!I15,"") | G18: =IF('5. Projected Sales Forecast (2)'!$E$10>0,'5. Projected Sales Forecast (2)'!$E$10*'5. Projected Sales Forecast (2)'!J15,"") | H18: =IF('5. Projected Sales Forecast (2)'!$E$10>0,'5. Projected Sales Forecast (2)'!$E$10*'5. Projected Sales Forecast (2)'!K15,"") | I18: =IF('5. Projected Sales Forecast (2)'!$E$10>0,'5. Projected Sales Forecast (2)'!$E$10*'5. Projected Sales Forecast (2)'!L15,"") | J18: =IF('5. Projected Sales Forecast (2)'!$E$10>0,'5. Projected Sales Forecast (2)'!$E$10*'5. Projected Sales Forecast (2)'!M15,"") | K18: =IF('5. Projected Sales Forecast (2)'!$E$10>0,'5. Projected Sales Forecast (2)'!$E$10*'5. Projected Sales Forecast (2)'!N15,"") | L18: =IF('5. Projected Sales Forecast (2)'!$E$10>0,'5. Projected Sales Forecast (2)'!$E$10*'5. Projected Sales Forecast (2)'!O15,"") | ... P18: =IF('5. Projected Sales Forecast (2)'!$E$10>0,'5. Projected Sales Forecast (2)'!$E$10*'5. Projected Sales Forecast (2)'!S15,"") | Q18: =SUM(E18:P18)
B19: =B12 | E19: =IF('5. Projected Sales Forecast (2)'!$E$32>0,'5. Projected Sales Forecast (2)'!$E$32*'5. Projected Sales Forecast (2)'!H37,"") | F19: =IF('5. Projected Sales Forecast (2)'!$E$32>0,'5. Projected Sales Forecast (2)'!$E$32*'5. Projected Sales Forecast (2)'!I37,"") | G19: =IF('5. Projected Sales Forecast (2)'!$E$32>0,'5. Projected Sales Forecast (2)'!$E$32*'5. Projected Sales Forecast (2)'!J37,"") | H19: =IF('5. Projected Sales Forecast (2)'!$E$32>0,'5. Projected Sales Forecast (2)'!$E$32*'5. Projected Sales Forecast (2)'!K37,"") | I19: =IF('5. Projected Sales Forecast (2)'!$E$32>0,'5. Projected Sales Forecast (2)'!$E$32*'5. Projected Sales Forecast (2)'!L37,"") | J19: =IF('5. Projected Sales Forecast (2)'!$E$32>0,'5. Projected Sales Forecast (2)'!$E$32*'5. Projected Sales Forecast (2)'!M37,"") | K19: =IF('5. Projected Sales Forecast (2)'!$E$32>0,'5. Projected Sales Forecast (2)'!$E$32*'5. Projected Sales Forecast (2)'!N37,"") | L19: =IF('5. Projected Sales Forecast (2)'!$E$32>0,'5. Projected Sales Forecast (2)'!$E$32*'5. Projected Sales Forecast (2)'!O37,"") | ... P19: =IF('5. Projected Sales Forecast (2)'!$E$32>0,'5. Projected Sales Forecast (2)'!$E$32*'5. Projected Sales Forecast (2)'!S37,"") | Q19: =SUM(E19:P19)
A20: Total Cost of Sales | E20: =SUM(E16:E19) | F20: =SUM(F16:F19) | G20: =SUM(G16:G19) | H20: =SUM(H16:H19) | I20: =SUM(I16:I19) | J20: =SUM(J16:J19) | K20: =SUM(K16:K19) | L20: =SUM(L16:L19) | ... Q20: =SUM(Q16:Q19)
A22: Gross Margin | E22: =E13-E20 | F22: =F13-F20 | G22: =G13-G20 | H22: =H13-H20 | I22: =I13-I20 | J22: =J13-J20 | K22: =K13-K20 | L22: =L13-L20 | ... Q22: =Q13-Q20
A24: ='2. Salaries and Wages'!A10
B25: ='2. Salaries and Wages'!B11 | E25: ='2. Salaries and Wages'!N11/12 | F25: =E25 | G25: =F25 | H25: =G25 | I25: =H25 | J25: =I25 | K25: =J25 | L25: =K25 | M25: =L25 | ... P25: =O25 | Q25: =SUM(E25:P25)
B26: ='2. Salaries and Wages'!B12 | E26: ='2. Salaries and Wages'!N12/12 | F26: =E26 | G26: =F26 | H26: =G26 | I26: =H26 | J26: =I26 | K26: =J26 | L26: =K26 | M26: =L26 | ... P26: =O26 | Q26: =SUM(E26:P26)
B27: ='2. Salaries and Wages'!C14 | E27: ='2. Salaries and Wages'!N14/12 | F27: =E27 | G27: =F27 | H27: =G27 | I27: =H27 | J27: =I27 | K27: =J27 | L27: =K27 | M27: =L27 | ... P27: =O27 | Q27: =SUM(E27:P27)
B28: ='2. Salaries and Wages'!C17 | E28: ='2. Salaries and Wages'!N17/12 | F28: =E28 | G28: =F28 | H28: =G28 | I28: =H28 | J28: =I28 | K28: =J28 | L28: =K28 | M28: =L28 | ... P28: =O28 | Q28: =SUM(E28:P28)
B29: ='2. Salaries and Wages'!B20 | E29: ='2. Salaries and Wages'!N20/12 | F29: =E29 | G29: =F29 | H29: =G29 | I29: =H29 | J29: =I29 | K29: =J29 | L29: =K29 | M29: =L29 | ... P29: =O29 | Q29: =SUM(E29:P29)
B30: ='2. Salaries and Wages'!A23 | E30: ='2. Salaries and Wages'!N32/12 | F30: =E30 | G30: =F30 | H30: =G30 | I30: =H30 | J30: =I30 | K30: =J30 | L30: =K30 | M30: =L30 | ... P30: =O30 | Q30: =SUM(E30:P30)
A31: Total Salary and Wages | E31: =SUM(E25:E30) | F31: =SUM(F25:F30) | G31: =SUM(G25:G30) | H31: =SUM(H25:H30) | I31: =SUM(I25:I30) | J31: =SUM(J25:J30) | K31: =SUM(K25:K30) | L31: =SUM(L25:L30) | ... Q31: =SUM(Q25:Q30)
A33: Fixed Business Expenses
B34: ='3. Fixed Operating Expenses'!B11 | E34: ='3. Fixed Operating Expenses'!J11/12 | F34: =E34 | G34: =F34 | H34: =G34 | I34: =H34 | J34: =I34 | K34: =J34 | L34: =K34 | M34: =L34 | ... P34: =O34 | Q34: =SUM(E34:P34)
B35: ='3. Fixed Operating Expenses'!B12 | E35: ='3. Fixed Operating Expenses'!J12/12 | F35: =E35 | G35: =F35 | H35: =G35 | I35: =H35 | J35: =I35 | K35: =J35 | L35: =K35 | M35: =L35 | ... P35: =O35 | Q35: =SUM(E35:P35)
B36: ='3. Fixed Operating Expenses'!B13 | E36: ='3. Fixed Operating Expenses'!J13/12 | F36: =E36 | G36: =F36 | H36: =G36 | I36: =H36 | J36: =I36 | K36: =J36 | L36: =K36 | M36: =L36 | ... P36: =O36 | Q36: =SUM(E36:P36)
B37: ='3. Fixed Operating Expenses'!B14 | E37: ='3. Fixed Operating Expenses'!J14/12 | F37: =E37 | G37: =F37 | H37: =G37 | I37: =H37 | J37: =I37 | K37: =J37 | L37: =K37 | M37: =L37 | ... P37: =O37 | Q37: =SUM(E37:P37)
B38: ='3. Fixed Operating Expenses'!B15 | E38: ='3. Fixed Operating Expenses'!J15/12 | F38: =E38 | G38: =F38 | H38: =G38 | I38: =H38 | J38: =I38 | K38: =J38 | L38: =K38 | M38: =L38 | ... P38: =O38 | Q38: =SUM(E38:P38)
B39: ='3. Fixed Operating Expenses'!B16 | E39: ='3. Fixed Operating Expenses'!J16/12 | F39: =E39 | G39: =F39 | H39: =G39 | I39: =H39 | J39: =I39 | K39: =J39 | L39: =K39 | M39: =L39 | ... P39: =O39 | Q39: =SUM(E39:P39)
B40: ='3. Fixed Operating Expenses'!B17 | E40: ='3. Fixed Operating Expenses'!J17/12 | F40: =E40 | G40: =F40 | H40: =G40 | I40: =H40 | J40: =I40 | K40: =J40 | L40: =K40 | M40: =L40 | ... P40: =O40 | Q40: =SUM(E40:P40)
B41: ='3. Fixed Operating Expenses'!B18 | E41: ='3. Fixed Operating Expenses'!J18/12 | F41: =E41 | G41: =F41 | H41: =G41 | I41: =H41 | J41: =I41 | K41: =J41 | L41: =K41 | M41: =L41 | ... P41: =O41 | Q41: =SUM(E41:P41)
B42: ='3. Fixed Operating Expenses'!B19 | E42: ='3. Fixed Operating Expenses'!J19/12 | F42: =E42 | G42: =F42 | H42: =G42 | I42: =H42 | J42: =I42 | K42: =J42 | L42: =K42 | M42: =L42 | ... P42: =O42 | Q42: =SUM(E42:P42)
B43: ='3. Fixed Operating Expenses'!B20 | E43: ='3. Fixed Operating Expenses'!J20/12 | F43: =E43 | G43: =F43 | H43: =G43 | I43: =H43 | J43: =I43 | K43: =J43 | L43: =K43 | M43: =L43 | ... P43: =O43 | Q43: =SUM(E43:P43)
B44: ='3. Fixed Operating Expenses'!B21 | E44: ='3. Fixed Operating Expenses'!J21/12 | F44: =E44 | G44: =F44 | H44: =G44 | I44: =H44 | J44: =I44 | K44: =J44 | L44: =K44 | M44: =L44 | ... P44: =O44 | Q44: =SUM(E44:P44)
B45: ='3. Fixed Operating Expenses'!B22 | E45: ='3. Fixed Operating Expenses'!J22/12 | F45: =E45 | G45: =F45 | H45: =G45 | I45: =H45 | J45: =I45 | K45: =J45 | L45: =K45 | M45: =L45 | ... P45: =O45 | Q45: =SUM(E45:P45)
... B53: ='3. Fixed Operating Expenses'!B30 | E53: ='3. Fixed Operating Expenses'!J30/12 | F53: =E53 | G53: =F53 | H53: =G53 | I53: =H53 | J53: =I53 | K53: =J53 | L53: =K53 | M53: =L53 | ... P53: =O53 | Q53: =SUM(E53:P53)
A54: Total Fixed Business Expenses | E54: =SUM(E34:E53) | F54: =SUM(F34:F53) | G54: =SUM(G34:G53) | H54: =SUM(H34:H53) | I54: =SUM(I34:I53) | J54: =SUM(J34:J53) | K54: =SUM(K34:K53) | L54: =SUM(L34:L53) | ... Q54: =SUM(Q34:Q53)
A56: Other Expenses
B57: Amortized Start-up Expenses | E57: =IF('6. Cash Receipts-Disbursements'!$G$28>1,'6. Cash Receipts-Disbursements'!$K$28,0) | F57: =IF('6. Cash Receipts-Disbursements'!$G$28>1,'6. Cash Receipts-Disbursements'!$K$28,0) | G57: =IF('6. Cash Receipts-Disbursements'!$G$28>1,'6. Cash Receipts-Disbursements'!$K$28,0) | H57: =IF('6. Cash Receipts-Disbursements'!$G$28>1,'6. Cash Receipts-Disbursements'!$K$28,0) | I57: =IF('6. Cash Receipts-Disbursements'!$G$28>1,'6. Cash Receipts-Disbursements'!$K$28,0) | J57: =IF('6. Cash Receipts-Disbursements'!$G$28>1,'6. Cash Receipts-Disbursements'!$K$28,0) | K57: =IF('6. Cash Receipts-Disbursements'!$G$28>1,'6. Cash Receipts-Disbursements'!$K$28,0) | L57: =IF('6. Cash Receipts-Disbursements'!$G$28>1,'6. Cash Receipts-Disbursements'!$K$28,0) | ... P57: =IF('6. Cash Receipts-Disbursements'!$G$28>1,'6. Cash Receipts-Disbursements'!$K$28,0) | Q57: =SUM(E57:P57)
B58: Depreciation | E58: ='3. Fixed Operating Expenses'!G34 | F58: =E58 | G58: =F58 | H58: =G58 | I58: =H58 | J58: =I58 | K58: =J58 | L58: =K58 | M58: =L58 | ... P58: =O58 | Q58: =SUM(E58:P58)
B59: Interest
C60: Commercial Loan | E60: ='20. Amoritization Schedule'!G19 | F60: ='20. Amoritization Schedule'!H19 | G60: ='20. Amoritization Schedule'!I19 | H60: ='20. Amoritization Schedule'!J19 | I60: ='20. Amoritization Schedule'!K19 | J60: ='20. Amoritization Schedule'!L19 | K60: ='20. Amoritization Schedule'!M19 | L60: ='20. Amoritization Schedule'!N19 | ... P60: ='20. Amoritization Schedule'!R19 | Q60: =SUM(E60:P60)
C61: Commercial Mortgage | E61: ='20. Amoritization Schedule'!G39 | F61: ='20. Amoritization Schedule'!H39 | G61: ='20. Amoritization Schedule'!I39 | H61: ='20. Amoritization Schedule'!J39 | I61: ='20. Amoritization Schedule'!K39 | J61: ='20. Amoritization Schedule'!L39 | K61: ='20. Amoritization Schedule'!M39 | L61: ='20. Amoritization Schedule'!N39 | ... P61: ='20. Amoritization Schedule'!R39 | Q61: =SUM(E61:P61)
C62: Line of Credit | E62: ='13. Cash Flow Statement (2)'!E26 | F62: ='13. Cash Flow Statement (2)'!F26 | G62: ='13. Cash Flow Statement (2)'!G26 | H62: ='13. Cash Flow Statement (2)'!H26 | I62: ='13. Cash Flow Statement (2)'!I26 | J62: ='13. Cash Flow Statement (2)'!J26 | K62: ='13. Cash Flow Statement (2)'!K26 | L62: ='13. Cash Flow Statement (2)'!L26 | ... P62: ='13. Cash Flow Statement (2)'!P26 | Q62: =SUM(E62:P62)
B63: Taxes | E63: =IF(E71>0,(E70)*'6. Cash Receipts-Disbursements'!G25,0) | F63: =IF(F71>0,IF(E71<0,(F70-ABS(E71))*'6. Cash Receipts-Disbursements'!$G$25,'12. Income Statement (2)'!F70*'6. Cash Receipts-Disbursements'!$G$25),IF('12. Income Statement (2)'!E71>0,-('12. Income Statement (2)'!E71*'6. Cash Receipts-Disbursements'!$G$25),0)) | G63: =IF(G71>0,IF(F71<0,(G70-ABS(F71))*'6. Cash Receipts-Disbursements'!$G$25,'12. Income Statement (2)'!G70*'6. Cash Receipts-Disbursements'!$G$25),IF('12. Income Statement (2)'!F71>0,-('12. Income Statement (2)'!F71*'6. Cash Receipts-Disbursements'!$G$25),0)) | H63: =IF(H71>0,IF(G71<0,(H70-ABS(G71))*'6. Cash Receipts-Disbursements'!$G$25,'12. Income Statement (2)'!H70*'6. Cash Receipts-Disbursements'!$G$25),IF('12. Income Statement (2)'!G71>0,-('12. Income Statement (2)'!G71*'6. Cash Receipts-Disbursements'!$G$25),0)) | I63: =IF(I71>0,IF(H71<0,(I70-ABS(H71))*'6. Cash Receipts-Disbursements'!$G$25,'12. Income Statement (2)'!I70*'6. Cash Receipts-Disbursements'!$G$25),IF('12. Income Statement (2)'!H71>0,-('12. Income Statement (2)'!H71*'6. Cash Receipts-Disbursements'!$G$25),0)) | J63: =IF(J71>0,IF(I71<0,(J70-ABS(I71))*'6. Cash Receipts-Disbursements'!$G$25,'12. Income Statement (2)'!J70*'6. Cash Receipts-Disbursements'!$G$25),IF('12. Income Statement (2)'!I71>0,-('12. Income Statement (2)'!I71*'6. Cash Receipts-Disbursements'!$G$25),0)) | K63: =IF(K71>0,IF(J71<0,(K70-ABS(J71))*'6. Cash Receipts-Disbursements'!$G$25,'12. Income Statement (2)'!K70*'6. Cash Receipts-Disbursements'!$G$25),IF('12. Income Statement (2)'!J71>0,-('12. Income Statement (2)'!J71*'6. Cash Receipts-Disbursements'!$G$25),0)) | L63: =IF(L71>0,IF(K71<0,(L70-ABS(K71))*'6. Cash Receipts-Disbursements'!$G$25,'12. Income Statement (2)'!L70*'6. Cash Receipts-Disbursements'!$G$25),IF('12. Income Statement (2)'!K71>0,-('12. Income Statement (2)'!K71*'6. Cash Receipts-Disbursements'!$G$25),0)) | M63: =IF(M71>0,IF(L71<0,(M70-ABS(L71))*'6. Cash Receipts-Disbursements'!$G$25,'12. Income Statement (2)'!M70*'6. Cash Receipts-Disbursements'!$G$25),IF('12. Income Statement (2)'!L71>0,-('12. Income Statement (2)'!L71*'6. Cash Receipts-Disbursements'!$G$25),0)) | ... P63: =IF(P71>0,IF(O71<0,(P70-ABS(O71))*'6. Cash Receipts-Disbursements'!$G$25,'12. Income Statement (2)'!P70*'6. Cash Receipts-Disbursements'!$G$25),IF('12. Income Statement (2)'!O71>0,-('12. Income Statement (2)'!O71*'6. Cash Receipts-Disbursements'!$G$25),0)) | Q63: =SUM(E63:P63)
A64: Total Other Expenses | E64: =SUM(E57:E63) | F64: =SUM(F57:F63) | G64: =SUM(G57:G63) | H64: =SUM(H57:H63) | I64: =SUM(I57:I63) | J64: =SUM(J57:J63) | K64: =SUM(K57:K63) | L64: =SUM(L57:L63) | ... Q64: =SUM(Q57:Q63)
A66: Net Income | E66: =E22-E31-E54-E64 | F66: =F22-F31-F54-F64 | G66: =G22-G31-G54-G64 | H66: =H22-H31-H54-H64 | I66: =I22-I31-I54-I64 | J66: =J22-J31-J54-J64 | K66: =K22-K31-K54-K64 | L66: =L22-L31-L54-L64 | ... Q66: =Q22-Q31-Q54-Q64
E70: =E22-E31-E54-E58-E60-E61-E62 | F70: =F22-F31-F54-F58-F60-F61-F62 | G70: =G22-G31-G54-G58-G60-G61-G62 | H70: =H22-H31-H54-H58-H60-H61-H62 | I70: =I22-I31-I54-I58-I60-I61-I62 | J70: =J22-J31-J54-J58-J60-J61-J62 | K70: =K22-K31-K54-K58-K60-K61-K62 | L70: =L22-L31-L54-L58-L60-L61-L62 | ... P70: =P22-P31-P54-P58-P60-P61-P62
E71: =E70 | F71: =E71+F70 | G71: =F71+G70 | H71: =G71+H70 | I71: =H71+I70 | J71: =I71+J70 | K71: =J71+K70 | L71: =K71+L70 | M71: =L71+M70 | ... P71: =O71+P70

Sheet 13. Cash Flow Statement (2)
A1: ='1. Required Start-Up Funds'!A1
A2: Projected Cash Flow Statement - Year Two
E6: ='4. Projected Sales Forecast'!H6 | F6: ='4. Projected Sales Forecast'!I6 | G6: ='4. Projected Sales Forecast'!J6 | H6: ='4. Projected Sales Forecast'!K6 | I6: ='4. Projected Sales Forecast'!L6 | J6: ='4. Projected Sales Forecast'!M6 | K6: ='4. Projected Sales Forecast'!N6 | L6: ='4. Projected Sales Forecast'!O6 | ... P6: ='4. Projected Sales Forecast'!S6 | Q6: Totals
A8: Beginning Cash Balance | E8: ='9. Cash Flow Statement'!P37 | F8: =E37 | G8: =F37 | H8: =G37 | I8: =H37 | J8: =I37 | K8: =J37 | L8: =K37 | M8: =L37 | ... P8: =O37
A10: Cash Inflows
B11: Income from Sales | E11: ='12. Income Statement (2)'!E13*'6. Cash Receipts-Disbursements'!$G$8 | F11: ='12. Income Statement (2)'!F13*'6. Cash Receipts-Disbursements'!$G$8 | G11: ='12. Income Statement (2)'!G13*'6. Cash Receipts-Disbursements'!$G$8 | H11: ='12. Income Statement (2)'!H13*'6. Cash Receipts-Disbursements'!$G$8 | I11: ='12. Income Statement (2)'!I13*'6. Cash Receipts-Disbursements'!$G$8 | J11: ='12. Income Statement (2)'!J13*'6. Cash Receipts-Disbursements'!$G$8 | K11: ='12. Income Statement (2)'!K13*'6. Cash Receipts-Disbursements'!$G$8 | L11: ='12. Income Statement (2)'!L13*'6. Cash Receipts-Disbursements'!$G$8 | ... P11: ='12. Income Statement (2)'!P13*'6. Cash Receipts-Disbursements'!$G$8 | Q11: =SUM(E11:P11)
B12: Accounts Receivable | E12: =('8. Income Statement'!O13*'6. Cash Receipts-Disbursements'!G10)+('8. Income Statement'!P13*'6. Cash Receipts-Disbursements'!G9) | F12: =('8. Income Statement'!P13*'6. Cash Receipts-Disbursements'!G10)+('12. Income Statement (2)'!E13*'6. Cash Receipts-Disbursements'!G9) | G12: =('12. Income Statement (2)'!E13*'6. Cash Receipts-Disbursements'!$G$10)+('12. Income Statement (2)'!F13*'6. Cash Receipts-Disbursements'!$G$9) | H12: =('12. Income Statement (2)'!F13*'6. Cash Receipts-Disbursements'!$G$10)+('12. Income Statement (2)'!G13*'6. Cash Receipts-Disbursements'!$G$9) | I12: =('12. Income Statement (2)'!G13*'6. Cash Receipts-Disbursements'!$G$10)+('12. Income Statement (2)'!H13*'6. Cash Receipts-Disbursements'!$G$9) | J12: =('12. Income Statement (2)'!H13*'6. Cash Receipts-Disbursements'!$G$10)+('12. Income Statement (2)'!I13*'6. Cash Receipts-Disbursements'!$G$9) | K12: =('12. Income Statement (2)'!I13*'6. Cash Receipts-Disbursements'!$G$10)+('12. Income Statement (2)'!J13*'6. Cash Receipts-Disbursements'!$G$9) | L12: =('12. Income Statement (2)'!J13*'6. Cash Receipts-Disbursements'!$G$10)+('12. Income Statement (2)'!K13*'6. Cash Receipts-Disbursements'!$G$9) | M12: =('12. Income Statement (2)'!K13*'6. Cash Receipts-Disbursements'!$G$10)+('12. Income Statement (2)'!L13*'6. Cash Receipts-Disbursements'!$G$9) | N12: =('12. Income Statement (2)'!L13*'6. Cash Receipts-Disbursements'!$G$10)+('12. Income Statement (2)'!M13*'6. Cash Receipts-Disbursements'!$G$9) | ... P12: =('12. Income Statement (2)'!N13*'6. Cash Receipts-Disbursements'!$G$10)+('12. Income Statement (2)'!O13*'6. Cash Receipts-Disbursements'!$G$9) | Q12: =SUM(E12:P12)
A13: Total Cash Inflows | E13: =SUM(E11:E12) | F13: =SUM(F11:F12) | G13: =SUM(G11:G12) | H13: =SUM(H11:H12) | I13: =SUM(I11:I12) | J13: =SUM(J11:J12) | K13: =SUM(K11:K12) | L13: =SUM(L11:L12) | ... Q13: =SUM(Q11:Q12)
A15: Cash Outflows
B16: Investing Activities
C17: New Capital Purchases | E17: 0 | F17: 0 | G17: 0 | H17: 0 | I17: 0 | J17: 0 | K17: 0 | L17: 0 | M17: 0 | N17: 0 | O17: 0 | P17: 0 | Q17: =SUM(E17:P17)
C18: Inventory Purchases | E18: 0 | F18: 0 | G18: 0 | H18: 0 | I18: 0 | J18: 0 | K18: 0 | L18: 0 | M18: 0 | N18: 0 | O18: 0 | P18: 0 | Q18: =SUM(E18:P18)
C19: Cost of Sales | E19: =('6. Cash Receipts-Disbursements'!G15*'12. Income Statement (2)'!E20)+('6. Cash Receipts-Disbursements'!G16*'8. Income Statement'!P20)+('6. Cash Receipts-Disbursements'!G17*'8. Income Statement'!O13) | F19: =('6. Cash Receipts-Disbursements'!G15*'12. Income Statement (2)'!F20)+('6. Cash Receipts-Disbursements'!G16*'12. Income Statement (2)'!E20)+('6. Cash Receipts-Disbursements'!G17*'8. Income Statement'!P20) | G19: =('6. Cash Receipts-Disbursements'!$G$15*'12. Income Statement (2)'!G20)+('6. Cash Receipts-Disbursements'!$G$16*'12. Income Statement (2)'!F20)+('6. Cash Receipts-Disbursements'!$G$17*'12. Income Statement (2)'!E20) | H19: =('6. Cash Receipts-Disbursements'!$G$15*'12. Income Statement (2)'!H20)+('6. Cash Receipts-Disbursements'!$G$16*'12. Income Statement (2)'!G20)+('6. Cash Receipts-Disbursements'!$G$17*'12. Income Statement (2)'!F20) | I19: =('6. Cash Receipts-Disbursements'!$G$15*'12. Income Statement (2)'!I20)+('6. Cash Receipts-Disbursements'!$G$16*'12. Income Statement (2)'!H20)+('6. Cash Receipts-Disbursements'!$G$17*'12. Income Statement (2)'!G20) | J19: =('6. Cash Receipts-Disbursements'!$G$15*'12. Income Statement (2)'!J20)+('6. Cash Receipts-Disbursements'!$G$16*'12. Income Statement (2)'!I20)+('6. Cash Receipts-Disbursements'!$G$17*'12. Income Statement (2)'!H20) | K19: =('6. Cash Receipts-Disbursements'!$G$15*'12. Income Statement (2)'!K20)+('6. Cash Receipts-Disbursements'!$G$16*'12. Income Statement (2)'!J20)+('6. Cash Receipts-Disbursements'!$G$17*'12. Income Statement (2)'!I20) | L19: =('6. Cash Receipts-Disbursements'!$G$15*'12. Income Statement (2)'!L20)+('6. Cash Receipts-Disbursements'!$G$16*'12. Income Statement (2)'!K20)+('6. Cash Receipts-Disbursements'!$G$17*'12. Income Statement (2)'!J20) | M19: =('6. Cash Receipts-Disbursements'!$G$15*'12. Income Statement (2)'!M20)+('6. Cash Receipts-Disbursements'!$G$16*'12. Income Statement (2)'!L20)+('6. Cash Receipts-Disbursements'!$G$17*'12. Income Statement (2)'!K20) | N19: =('6. Cash Receipts-Disbursements'!$G$15*'12. Income Statement (2)'!N20)+('6. Cash Receipts-Disbursements'!$G$16*'12. Income Statement (2)'!M20)+('6. Cash Receipts-Disbursements'!$G$17*'12. Income Statement (2)'!L20) | ... P19: =('6. Cash Receipts-Disbursements'!$G$15*'12. Income Statement (2)'!P20)+('6. Cash Receipts-Disbursements'!$G$16*'12. Income Statement (2)'!O20)+('6. Cash Receipts-Disbursements'!$G$17*'12. Income Statement (2)'!N20) | Q19: =SUM(E19:P19)
B20: Operating Activities
C21: ='8. Income Statement'!A24 | E21: ='12. Income Statement (2)'!E31 | F21: ='12. Income Statement (2)'!F31 | G21: ='12. Income Statement (2)'!G31 | H21: ='12. Income Statement (2)'!H31 | I21: ='12. Income Statement (2)'!I31 | J21: ='12. Income Statement (2)'!J31 | K21: ='12. Income Statement (2)'!K31 | L21: ='12. Income Statement (2)'!L31 | ... P21: ='12. Income Statement (2)'!P31 | Q21: =SUM(E21:P21)
C22: ='8. Income Statement'!A33 | E22: ='12. Income Statement (2)'!E54 | F22: ='12. Income Statement (2)'!F54 | G22: ='12. Income Statement (2)'!G54 | H22: ='12. Income Statement (2)'!H54 | I22: ='12. Income Statement (2)'!I54 | J22: ='12. Income Statement (2)'!J54 | K22: ='12. Income Statement (2)'!K54 | L22: ='12. Income Statement (2)'!L54 | ... P22: ='12. Income Statement (2)'!P54 | Q22: =SUM(E22:P22)
C23: Taxes | E23: 0 | F23: 0 | G23: =SUM('12. Income Statement (2)'!E63:G63) | H23: 0 | I23: 0 | J23: =SUM('12. Income Statement (2)'!H63:J63) | K23: 0 | L23: 0 | M23: =SUM('12. Income Statement (2)'!K63:M63) | N23: 0 | O23: 0 | P23: =SUM('12. Income Statement (2)'!N63:P63) | Q23: =SUM(E23:P23)
B24: Financing Activities | Q24: =SUM(E24:P24)
C25: Loan Payments | E25: ='1. Required Start-Up Funds'!J42 | F25: =E25 | G25: =F25 | H25: =G25 | I25: =H25 | J25: =I25 | K25: =J25 | L25: =K25 | M25: =L25 | ... P25: =O25 | Q25: =SUM(E25:P25)
C26: Line of Credit Interest | E26: ='6. Cash Receipts-Disbursements'!G22/12*'9. Cash Flow Statement'!P40 | F26: ='6. Cash Receipts-Disbursements'!G22/12*'13. Cash Flow Statement (2)'!E40 | G26: =('6. Cash Receipts-Disbursements'!$G$22/12)*F40 | H26: =('6. Cash Receipts-Disbursements'!$G$22/12)*G40 | I26: =('6. Cash Receipts-Disbursements'!$G$22/12)*H40 | J26: =('6. Cash Receipts-Disbursements'!$G$22/12)*I40 | K26: =('6. Cash Receipts-Disbursements'!$G$22/12)*J40 | L26: =('6. Cash Receipts-Disbursements'!$G$22/12)*K40 | M26: =('6. Cash Receipts-Disbursements'!$G$22/12)*L40 | N26: =('6. Cash Receipts-Disbursements'!$G$22/12)*M40 | ... P26: =('6. Cash Receipts-Disbursements'!$G$22/12)*O40 | Q26: =SUM(E26:P26)
C27: Line of Credit Repayments | E27: 0 | F27: 0 | G27: 0 | H27: 0 | I27: 0 | J27: 0 | K27: 0 | L27: 0 | M27: 0 | N27: 0 | O27: 0 | P27: 0 | Q27: =SUM(E27:P27)
C28: Dividends Paid | E28: 0 | F28: 0 | G28: 0 | H28: 0 | I28: 0 | J28: 0 | K28: 0 | L28: 0 | M28: 0 | N28: 0 | O28: 0 | P28: 0 | Q28: =SUM(E28:P28)
A29: Total Cash Outflows | E29: =SUM(E17:E28) | F29: =SUM(F17:F28) | G29: =SUM(G17:G28) | H29: =SUM(H17:H28) | I29: =SUM(I17:I28) | J29: =SUM(J17:J28) | K29: =SUM(K17:K28) | L29: =SUM(L17:L28) | ... Q29: =SUM(Q17:Q28)
A31: Cash Flow | E31: =E13-E29 | F31: =F13-F29 | G31: =G13-G29 | H31: =H13-H29 | I31: =I13-I29 | J31: =J13-J29 | K31: =K13-K29 | L31: =L13-L29 | ... Q31: =Q13-Q29
A33: Operating Cash Balance | E33: =E8+E31 | F33: =F8+F31 | G33: =G8+G31 | H33: =H8+H31 | I33: =I8+I31 | J33: =J8+J31 | K33: =K8+K31 | L33: =L8+L31 | ... P33: =P8+P31
A35: Line of Credit Drawdowns | E35: =IF((E33-'6. Cash Receipts-Disbursements'!$G$21)<0,'6. Cash Receipts-Disbursements'!$G$21-'13. Cash Flow Statement (2)'!E33,0) | F35: =IF((F33-'6. Cash Receipts-Disbursements'!$G$21)<0,'6. Cash Receipts-Disbursements'!$G$21-'13. Cash Flow Statement (2)'!F33,0) | G35: =IF((G33-'6. Cash Receipts-Disbursements'!$G$21)<0,'6. Cash Receipts-Disbursements'!$G$21-'13. Cash Flow Statement (2)'!G33,0) | H35: =IF((H33-'6. Cash Receipts-Disbursements'!$G$21)<0,'6. Cash Receipts-Disbursements'!$G$21-'13. Cash Flow Statement (2)'!H33,0) | I35: =IF((I33-'6. Cash Receipts-Disbursements'!$G$21)<0,'6. Cash Receipts-Disbursements'!$G$21-'13. Cash Flow Statement (2)'!I33,0) | J35: =IF((J33-'6. Cash Receipts-Disbursements'!$G$21)<0,'6. Cash Receipts-Disbursements'!$G$21-'13. Cash Flow Statement (2)'!J33,0) | K35: =IF((K33-'6. Cash Receipts-Disbursements'!$G$21)<0,'6. Cash Receipts-Disbursements'!$G$21-'13. Cash Flow Statement (2)'!K33,0) | L35: =IF((L33-'6. Cash Receipts-Disbursements'!$G$21)<0,'6. Cash Receipts-Disbursements'!$G$21-'13. Cash Flow Statement (2)'!L33,0) | ... P35: =IF((P33-'6. Cash Receipts-Disbursements'!$G$21)<0,'6. Cash Receipts-Disbursements'!$G$21-'13. Cash Flow Statement (2)'!P33,0) | Q35: =SUM(E35:P35)
A37: Ending Cash Balance | E37: =E33+E35 | F37: =F33+F35 | G37: =G33+G35 | H37: =H33+H35 | I37: =I33+I35 | J37: =J33+J35 | K37: =K33+K35 | L37: =L33+L35 | ... P37: =P33+P35
A40: Line of Credit Balance | E40: =E35+'9. Cash Flow Statement'!P40-'13. Cash Flow Statement (2)'!E27 | F40: =E40+F35-F27 | G40: =F40+G35-G27 | H40: =G40+H35-H27 | I40: =H40+I35-I27 | J40: =I40+J35-J27 | K40: =J40+K35-K27 | L40: =K40+L35-L27 | M40: =L40+M35-M27 | ... P40: =O40+P35-P27

Sheet 14. Balance Sheet (2)
A1: ='1. Required Start-Up Funds'!A1
A2: Balance Sheet - Year Two
F6: End of Year One | I6: End of Year Two
A8: Assets
B9: Current Assets
C10: Cash | F10: ='10. Balance Sheet'!I10 | I10: ='13. Cash Flow Statement (2)'!P37
C11: Accounts Receivable | F11: ='10. Balance Sheet'!I11 | I11: =F11+'12. Income Statement (2)'!Q13-'13. Cash Flow Statement (2)'!Q13
C12: Inventory | F12: ='10. Balance Sheet'!I12 | I12: =F12
C13: Prepaid Expenses | F13: ='10. Balance Sheet'!I13 | I13: =IF(F13='7. Beginning Balance Sheet'!F13,'7. Beginning Balance Sheet'!F13,'14. Balance Sheet (2)'!F13-'6. Cash Receipts-Disbursements'!J26)
C14: Other Current | F14: ='10. Balance Sheet'!I14 | I14: =IF(F14='7. Beginning Balance Sheet'!F14,'7. Beginning Balance Sheet'!F14,'14. Balance Sheet (2)'!F14-'6. Cash Receipts-Disbursements'!J27)
B15: Total Current Assets | F15: =SUM(F10:F14) | I15: =SUM(I10:I14)
B17: Fixed Assets
C18: ='1. Required Start-Up Funds'!C8 | F18: ='10. Balance Sheet'!I18 | I18: =F18
C19: ='1. Required Start-Up Funds'!C9 | F19: ='10. Balance Sheet'!I19 | I19: =F19
C20: ='1. Required Start-Up Funds'!C10 | F20: ='10. Balance Sheet'!I20 | I20: =F20
C21: ='1. Required Start-Up Funds'!C11 | F21: ='10. Balance Sheet'!I21 | I21: =F21
C22: ='1. Required Start-Up Funds'!C12 | F22: ='10. Balance Sheet'!I22 | I22: =F22
C23: ='1. Required Start-Up Funds'!C13 | F23: ='10. Balance Sheet'!I23 | I23: =F23
C24: ='1. Required Start-Up Funds'!C14 | F24: ='10. Balance Sheet'!I24 | I24: =F24+'13. Cash Flow Statement (2)'!Q17
B25: Total Fixed Assets | F25: =SUM(F18:F24) | I25: =SUM(I18:I24)
B27: Less: Accumulated Depreciation | F27: ='10. Balance Sheet'!I27 | I27: =F27+'12. Income Statement (2)'!Q58
A29: Total Assets | F29: =INT(F15+F25-F27) | I29: =INT(I15+I25-I27)
A33: Liabilities and Owner's Equity
B34: Liabilities
C35: Accounts Payable | F35: ='10. Balance Sheet'!I35 | I35: =F35+'12. Income Statement (2)'!Q20-'13. Cash Flow Statement (2)'!Q19
C36: Notes Payable | F36: ='10. Balance Sheet'!I36 | I36: ='20. Amoritization Schedule'!R21+'7. Beginning Balance Sheet'!F36
C37: Mortgage Payable | F37: ='10. Balance Sheet'!I37 | I37: ='20. Amoritization Schedule'!R41+'7. Beginning Balance Sheet'!F37
C38: Line of Credit Balance | F38: ='10. Balance Sheet'!I38 | I38: ='13. Cash Flow Statement (2)'!P40+'7. Beginning Balance Sheet'!F38
B39: Total Liabilities | F39: =SUM(F35:F38) | I39: =SUM(I35:I38)
B41: Owner's Equity
C42: Common Stock | F42: ='10. Balance Sheet'!I42 | I42: =F42
C43: Retained Earnings | F43: ='10. Balance Sheet'!I43 | I43: =F43+'12. Income Statement (2)'!Q66
C44: Dividends Dispersed | F44: ='10. Balance Sheet'!I44 | I44: =F44+'13. Cash Flow Statement (2)'!Q28
B45: Total Owner's Equity | F45: =F42+F43-F44 | I45: =I42+I43-I44
A47: Total Liabilities and Owner's Equity | F47: =INT(F39+F45) | I47: =INT(I39+I45)
F50: =IF(F29=F47,"Statement Balances","Does Not Balance") | I50: =IF(I29-I47=0,"Statement Balances","Does Not Balance")

Sheet 15. Income Statement (3)
A1: ='1. Required Start-Up Funds'!A1
A2: Projected Income Statement - Year Three
E6: ='4. Projected Sales Forecast'!H6 | F6: ='4. Projected Sales Forecast'!I6 | G6: ='4. Projected Sales Forecast'!J6 | H6: ='4. Projected Sales Forecast'!K6 | I6: ='4. Projected Sales Forecast'!L6 | J6: ='4. Projected Sales Forecast'!M6 | K6: ='4. Projected Sales Forecast'!N6 | L6: ='4. Projected Sales Forecast'!O6 | ... P6: ='4. Projected Sales Forecast'!S6 | Q6: Totals
A8: Income
B9: ='4. Projected Sales Forecast'!A8 | E9: ='4. Projected Sales Forecast'!$E$9*'4. Projected Sales Forecast'!H16 | F9: ='4. Projected Sales Forecast'!$E$9*'4. Projected Sales Forecast'!I16 | G9: ='4. Projected Sales Forecast'!$E$9*'4. Projected Sales Forecast'!J16 | H9: ='4. Projected Sales Forecast'!$E$9*'4. Projected Sales Forecast'!K16 | I9: ='4. Projected Sales Forecast'!$E$9*'4. Projected Sales Forecast'!L16 | J9: ='4. Projected Sales Forecast'!$E$9*'4. Projected Sales Forecast'!M16 | K9: ='4. Projected Sales Forecast'!$E$9*'4. Projected Sales Forecast'!N16 | L9: ='4. Projected Sales Forecast'!$E$9*'4. Projected Sales Forecast'!O16 | ... P9: ='4. Projected Sales Forecast'!$E$9*'4. Projected Sales Forecast'!S16 | Q9: =SUM(E9:P9)
B10: ='4. Projected Sales Forecast'!A30 | E10: ='4. Projected Sales Forecast'!$E$31*'4. Projected Sales Forecast'!H38 | F10: ='4. Projected Sales Forecast'!$E$31*'4. Projected Sales Forecast'!I38 | G10: ='4. Projected Sales Forecast'!$E$31*'4. Projected Sales Forecast'!J38 | H10: ='4. Projected Sales Forecast'!$E$31*'4. Projected Sales Forecast'!K38 | I10: ='4. Projected Sales Forecast'!$E$31*'4. Projected Sales Forecast'!L38 | J10: ='4. Projected Sales Forecast'!$E$31*'4. Projected Sales Forecast'!M38 | K10: ='4. Projected Sales Forecast'!$E$31*'4. Projected Sales Forecast'!N38 | L10: ='4. Projected Sales Forecast'!$E$31*'4. Projected Sales Forecast'!O38 | ... P10: ='4. Projected Sales Forecast'!$E$31*'4. Projected Sales Forecast'!S38 | Q10: =SUM(E10:P10)
B11: =IF('5. Projected Sales Forecast (2)'!E9>0,'5. Projected Sales Forecast (2)'!A8,"") | E11: =IF('5. Projected Sales Forecast (2)'!$E$9>0,'5. Projected Sales Forecast (2)'!$E$9*'5. Projected Sales Forecast (2)'!H16,"") | F11: =IF('5. Projected Sales Forecast (2)'!$E$9>0,'5. Projected Sales Forecast (2)'!$E$9*'5. Projected Sales Forecast (2)'!I16,"") | G11: =IF('5. Projected Sales Forecast (2)'!$E$9>0,'5. Projected Sales Forecast (2)'!$E$9*'5. Projected Sales Forecast (2)'!J16,"") | H11: =IF('5. Projected Sales Forecast (2)'!$E$9>0,'5. Projected Sales Forecast (2)'!$E$9*'5. Projected Sales Forecast (2)'!K16,"") | I11: =IF('5. Projected Sales Forecast (2)'!$E$9>0,'5. Projected Sales Forecast (2)'!$E$9*'5. Projected Sales Forecast (2)'!L16,"") | J11: =IF('5. Projected Sales Forecast (2)'!$E$9>0,'5. Projected Sales Forecast (2)'!$E$9*'5. Projected Sales Forecast (2)'!M16,"") | K11: =IF('5. Projected Sales Forecast (2)'!$E$9>0,'5. Projected Sales Forecast (2)'!$E$9*'5. Projected Sales Forecast (2)'!N16,"") | L11: =IF('5. Projected Sales Forecast (2)'!$E$9>0,'5. Projected Sales Forecast (2)'!$E$9*'5. Projected Sales Forecast (2)'!O16,"") | ... P11: =IF('5. Projected Sales Forecast (2)'!$E$9>0,'5. Projected Sales Forecast (2)'!$E$9*'5. Projected Sales Forecast (2)'!S16,"") | Q11: =SUM(E11:P11)
B12: =IF('5. Projected Sales Forecast (2)'!E31>0,'5. Projected Sales Forecast (2)'!A30,"") | E12: =IF('5. Projected Sales Forecast (2)'!$E$31>0,'5. Projected Sales Forecast (2)'!$E$31*'5. Projected Sales Forecast (2)'!H38,"") | F12: =IF('5. Projected Sales Forecast (2)'!$E$31>0,'5. Projected Sales Forecast (2)'!$E$31*'5. Projected Sales Forecast (2)'!I38,"") | G12: =IF('5. Projected Sales Forecast (2)'!$E$31>0,'5. Projected Sales Forecast (2)'!$E$31*'5. Projected Sales Forecast (2)'!J38,"") | H12: =IF('5. Projected Sales Forecast (2)'!$E$31>0,'5. Projected Sales Forecast (2)'!$E$31*'5. Projected Sales Forecast (2)'!K38,"") | I12: =IF('5. Projected Sales Forecast (2)'!$E$31>0,'5. Projected Sales Forecast (2)'!$E$31*'5. Projected Sales Forecast (2)'!L38,"") | J12: =IF('5. Projected Sales Forecast (2)'!$E$31>0,'5. Projected Sales Forecast (2)'!$E$31*'5. Projected Sales Forecast (2)'!M38,"") | K12: =IF('5. Projected Sales Forecast (2)'!$E$31>0,'5. Projected Sales Forecast (2)'!$E$31*'5. Projected Sales Forecast (2)'!N38,"") | L12: =IF('5. Projected Sales Forecast (2)'!$E$31>0,'5. Projected Sales Forecast (2)'!$E$31*'5. Projected Sales Forecast (2)'!O38,"") | ... P12: =IF('5. Projected Sales Forecast (2)'!$E$31>0,'5. Projected Sales Forecast (2)'!$E$31*'5. Projected Sales Forecast (2)'!S38,"") | Q12: =SUM(E12:P12)
A13: Total Income | E13: =SUM(E9:E12) | F13: =SUM(F9:F12) | G13: =SUM(G9:G12) | H13: =SUM(H9:H12) | I13: =SUM(I9:I12) | J13: =SUM(J9:J12) | K13: =SUM(K9:K12) | L13: =SUM(L9:L12) | ... Q13: =SUM(Q9:Q12)
A15: Cost of Sales
B16: =B9 | E16: ='4. Projected Sales Forecast'!$E$10*'4. Projected Sales Forecast'!H16 | F16: ='4. Projected Sales Forecast'!$E$10*'4. Projected Sales Forecast'!I16 | G16: ='4. Projected Sales Forecast'!$E$10*'4. Projected Sales Forecast'!J16 | H16: ='4. Projected Sales Forecast'!$E$10*'4. Projected Sales Forecast'!K16 | I16: ='4. Projected Sales Forecast'!$E$10*'4. Projected Sales Forecast'!L16 | J16: ='4. Projected Sales Forecast'!$E$10*'4. Projected Sales Forecast'!M16 | K16: ='4. Projected Sales Forecast'!$E$10*'4. Projected Sales Forecast'!N16 | L16: ='4. Projected Sales Forecast'!$E$10*'4. Projected Sales Forecast'!O16 | ... P16: ='4. Projected Sales Forecast'!$E$10*'4. Projected Sales Forecast'!S16 | Q16: =SUM(E16:P16)
B17: =B10 | E17: ='4. Projected Sales Forecast'!$E$32*'4. Projected Sales Forecast'!H38 | F17: ='4. Projected Sales Forecast'!$E$32*'4. Projected Sales Forecast'!I38 | G17: ='4. Projected Sales Forecast'!$E$32*'4. Projected Sales Forecast'!J38 | H17: ='4. Projected Sales Forecast'!$E$32*'4. Projected Sales Forecast'!K38 | I17: ='4. Projected Sales Forecast'!$E$32*'4. Projected Sales Forecast'!L38 | J17: ='4. Projected Sales Forecast'!$E$32*'4. Projected Sales Forecast'!M38 | K17: ='4. Projected Sales Forecast'!$E$32*'4. Projected Sales Forecast'!N38 | L17: ='4. Projected Sales Forecast'!$E$32*'4. Projected Sales Forecast'!O38 | ... P17: ='4. Projected Sales Forecast'!$E$32*'4. Projected Sales Forecast'!S38 | Q17: =SUM(E17:P17)
B18: =B11 | E18: =IF('5. Projected Sales Forecast (2)'!$E$10>0,'5. Projected Sales Forecast (2)'!$E$10*'5. Projected Sales Forecast (2)'!H16,"") | F18: =IF('5. Projected Sales Forecast (2)'!$E$10>0,'5. Projected Sales Forecast (2)'!$E$10*'5. Projected Sales Forecast (2)'!I16,"") | G18: =IF('5. Projected Sales Forecast (2)'!$E$10>0,'5. Projected Sales Forecast (2)'!$E$10*'5. Projected Sales Forecast (2)'!J16,"") | H18: =IF('5. Projected Sales Forecast (2)'!$E$10>0,'5. Projected Sales Forecast (2)'!$E$10*'5. Projected Sales Forecast (2)'!K16,"") | I18: =IF('5. Projected Sales Forecast (2)'!$E$10>0,'5. Projected Sales Forecast (2)'!$E$10*'5. Projected Sales Forecast (2)'!L16,"") | J18: =IF('5. Projected Sales Forecast (2)'!$E$10>0,'5. Projected Sales Forecast (2)'!$E$10*'5. Projected Sales Forecast (2)'!M16,"") | K18: =IF('5. Projected Sales Forecast (2)'!$E$10>0,'5. Projected Sales Forecast (2)'!$E$10*'5. Projected Sales Forecast (2)'!N16,"") | L18: =IF('5. Projected Sales Forecast (2)'!$E$10>0,'5. Projected Sales Forecast (2)'!$E$10*'5. Projected Sales Forecast (2)'!O16,"") | ... P18: =IF('5. Projected Sales Forecast (2)'!$E$10>0,'5. Projected Sales Forecast (2)'!$E$10*'5. Projected Sales Forecast (2)'!S16,"") | Q18: =SUM(E18:P18)
B19: =B12 | E19: =IF('5. Projected Sales Forecast (2)'!$E$32>0,'5. Projected Sales Forecast (2)'!$E$32*'5. Projected Sales Forecast (2)'!H38,"") | F19: =IF('5. Projected Sales Forecast (2)'!$E$32>0,'5. Projected Sales Forecast (2)'!$E$32*'5. Projected Sales Forecast (2)'!I38,"") | G19: =IF('5. Projected Sales Forecast (2)'!$E$32>0,'5. Projected Sales Forecast (2)'!$E$32*'5. Projected Sales Forecast (2)'!J38,"") | H19: =IF('5. Projected Sales Forecast (2)'!$E$32>0,'5. Projected Sales Forecast (2)'!$E$32*'5. Projected Sales Forecast (2)'!K38,"") | I19: =IF('5. Projected Sales Forecast (2)'!$E$32>0,'5. Projected Sales Forecast (2)'!$E$32*'5. Projected Sales Forecast (2)'!L38,"") | J19: =IF('5. Projected Sales Forecast (2)'!$E$32>0,'5. Projected Sales Forecast (2)'!$E$32*'5. Projected Sales Forecast (2)'!M38,"") | K19: =IF('5. Projected Sales Forecast (2)'!$E$32>0,'5. Projected Sales Forecast (2)'!$E$32*'5. Projected Sales Forecast (2)'!N38,"") | L19: =IF('5. Projected Sales Forecast (2)'!$E$32>0,'5. Projected Sales Forecast (2)'!$E$32*'5. Projected Sales Forecast (2)'!O38,"") | ... P19: =IF('5. Projected Sales Forecast (2)'!$E$32>0,'5. Projected Sales Forecast (2)'!$E$32*'5. Projected Sales Forecast (2)'!S38,"") | Q19: =SUM(E19:P19)
A20: Total Cost of Sales | E20: =SUM(E16:E19) | F20: =SUM(F16:F19) | G20: =SUM(G16:G19) | H20: =SUM(H16:H19) | I20: =SUM(I16:I19) | J20: =SUM(J16:J19) | K20: =SUM(K16:K19) | L20: =SUM(L16:L19) | ... Q20: =SUM(Q16:Q19)
A22: Gross Margin | E22: =E13-E20 | F22: =F13-F20 | G22: =G13-G20 | H22: =H13-H20 | I22: =I13-I20 | J22: =J13-J20 | K22: =K13-K20 | L22: =L13-L20 | ... Q22: =Q13-Q20
A24: ='2. Salaries and Wages'!A10
B25: ='2. Salaries and Wages'!B11 | E25: ='2. Salaries and Wages'!O11/12 | F25: =E25 | G25: =F25 | H25: =G25 | I25: =H25 | J25: =I25 | K25: =J25 | L25: =K25 | M25: =L25 | ... P25: =O25 | Q25: =SUM(E25:P25)
B26: ='2. Salaries and Wages'!B12 | E26: ='2. Salaries and Wages'!O12/12 | F26: =E26 | G26: =F26 | H26: =G26 | I26: =H26 | J26: =I26 | K26: =J26 | L26: =K26 | M26: =L26 | ... P26: =O26 | Q26: =SUM(E26:P26)
B27: ='2. Salaries and Wages'!C14 | E27: ='2. Salaries and Wages'!O14/12 | F27: =E27 | G27: =F27 | H27: =G27 | I27: =H27 | J27: =I27 | K27: =J27 | L27: =K27 | M27: =L27 | ... P27: =O27 | Q27: =SUM(E27:P27)
B28: ='2. Salaries and Wages'!C17 | E28: ='2. Salaries and Wages'!O17/12 | F28: =E28 | G28: =F28 | H28: =G28 | I28: =H28 | J28: =I28 | K28: =J28 | L28: =K28 | M28: =L28 | ... P28: =O28 | Q28: =SUM(E28:P28)
B29: ='2. Salaries and Wages'!B20 | E29: ='2. Salaries and Wages'!O20/12 | F29: =E29 | G29: =F29 | H29: =G29 | I29: =H29 | J29: =I29 | K29: =J29 | L29: =K29 | M29: =L29 | ... P29: =O29 | Q29: =SUM(E29:P29)
B30: ='2. Salaries and Wages'!A23 | E30: ='2. Salaries and Wages'!O32/12 | F30: =E30 | G30: =F30 | H30: =G30 | I30: =H30 | J30: =I30 | K30: =J30 | L30: =K30 | M30: =L30 | ... P30: =O30 | Q30: =SUM(E30:P30)
A31: Total Salary and Wages | E31: =SUM(E25:E30) | F31: =SUM(F25:F30) | G31: =SUM(G25:G30) | H31: =SUM(H25:H30) | I31: =SUM(I25:I30) | J31: =SUM(J25:J30) | K31: =SUM(K25:K30) | L31: =SUM(L25:L30) | ... Q31: =SUM(Q25:Q30)
A33: Fixed Business Expenses
B34: ='3. Fixed Operating Expenses'!B11 | E34: ='3. Fixed Operating Expenses'!K11/12 | F34: =E34 | G34: =F34 | H34: =G34 | I34: =H34 | J34: =I34 | K34: =J34 | L34: =K34 | M34: =L34 | ... P34: =O34 | Q34: =SUM(E34:P34)
B35: ='3. Fixed Operating Expenses'!B12 | E35: ='3. Fixed Operating Expenses'!K12/12 | F35: =E35 | G35: =F35 | H35: =G35 | I35: =H35 | J35: =I35 | K35: =J35 | L35: =K35 | M35: =L35 | ... P35: =O35 | Q35: =SUM(E35:P35)
B36: ='3. Fixed Operating Expenses'!B13 | E36: ='3. Fixed Operating Expenses'!K13/12 | F36: =E36 | G36: =F36 | H36: =G36 | I36: =H36 | J36: =I36 | K36: =J36 | L36: =K36 | M36: =L36 | ... P36: =O36 | Q36: =SUM(E36:P36)
B37: ='3. Fixed Operating Expenses'!B14 | E37: ='3. Fixed Operating Expenses'!K14/12 | F37: =E37 | G37: =F37 | H37: =G37 | I37: =H37 | J37: =I37 | K37: =J37 | L37: =K37 | M37: =L37 | ... P37: =O37 | Q37: =SUM(E37:P37)
B38: ='3. Fixed Operating Expenses'!B15 | E38: ='3. Fixed Operating Expenses'!K15/12 | F38: =E38 | G38: =F38 | H38: =G38 | I38: =H38 | J38: =I38 | K38: =J38 | L38: =K38 | M38: =L38 | ... P38: =O38 | Q38: =SUM(E38:P38)
B39: ='3. Fixed Operating Expenses'!B16 | E39: ='3. Fixed Operating Expenses'!K16/12 | F39: =E39 | G39: =F39 | H39: =G39 | I39: =H39 | J39: =I39 | K39: =J39 | L39: =K39 | M39: =L39 | ... P39: =O39 | Q39: =SUM(E39:P39)
B40: ='3. Fixed Operating Expenses'!B17 | E40: ='3. Fixed Operating Expenses'!K17/12 | F40: =E40 | G40: =F40 | H40: =G40 | I40: =H40 | J40: =I40 | K40: =J40 | L40: =K40 | M40: =L40 | ... P40: =O40 | Q40: =SUM(E40:P40)
B41: ='3. Fixed Operating Expenses'!B18 | E41: ='3. Fixed Operating Expenses'!K18/12 | F41: =E41 | G41: =F41 | H41: =G41 | I41: =H41 | J41: =I41 | K41: =J41 | L41: =K41 | M41: =L41 | ... P41: =O41 | Q41: =SUM(E41:P41)
B42: ='3. Fixed Operating Expenses'!B19 | E42: ='3. Fixed Operating Expenses'!K19/12 | F42: =E42 | G42: =F42 | H42: =G42 | I42: =H42 | J42: =I42 | K42: =J42 | L42: =K42 | M42: =L42 | ... P42: =O42 | Q42: =SUM(E42:P42)
B43: ='3. Fixed Operating Expenses'!B20 | E43: ='3. Fixed Operating Expenses'!K20/12 | F43: =E43 | G43: =F43 | H43: =G43 | I43: =H43 | J43: =I43 | K43: =J43 | L43: =K43 | M43: =L43 | ... P43: =O43 | Q43: =SUM(E43:P43)
B44: ='3. Fixed Operating Expenses'!B21 | E44: ='3. Fixed Operating Expenses'!K21/12 | F44: =E44 | G44: =F44 | H44: =G44 | I44: =H44 | J44: =I44 | K44: =J44 | L44: =K44 | M44: =L44 | ... P44: =O44 | Q44: =SUM(E44:P44)
B45: ='3. Fixed Operating Expenses'!B22 | E45: ='3. Fixed Operating Expenses'!K22/12 | F45: =E45 | G45: =F45 | H45: =G45 | I45: =H45 | J45: =I45 | K45: =J45 | L45: =K45 | M45: =L45 | ... P45: =O45 | Q45: =SUM(E45:P45)
... B53: ='3. Fixed Operating Expenses'!B30 | E53: ='3. Fixed Operating Expenses'!K30/12 | F53: =E53 | G53: =F53 | H53: =G53 | I53: =H53 | J53: =I53 | K53: =J53 | L53: =K53 | M53: =L53 | ... P53: =O53 | Q53: =SUM(E53:P53)
A54: Total Fixed Business Expenses | E54: =SUM(E34:E53) | F54: =SUM(F34:F53) | G54: =SUM(G34:G53) | H54: =SUM(H34:H53) | I54: =SUM(I34:I53) | J54: =SUM(J34:J53) | K54: =SUM(K34:K53) | L54: =SUM(L34:L53) | ... Q54: =SUM(Q34:Q53)
A56: Other Expenses
B57: Amortized Start-up Expenses | E57: =IF('6. Cash Receipts-Disbursements'!$G$28>2,'6. Cash Receipts-Disbursements'!$K$28,0) | F57: =IF('6. Cash Receipts-Disbursements'!$G$28>2,'6. Cash Receipts-Disbursements'!$K$28,0) | G57: =IF('6. Cash Receipts-Disbursements'!$G$28>2,'6. Cash Receipts-Disbursements'!$K$28,0) | H57: =IF('6. Cash Receipts-Disbursements'!$G$28>2,'6. Cash Receipts-Disbursements'!$K$28,0) | I57: =IF('6. Cash Receipts-Disbursements'!$G$28>2,'6. Cash Receipts-Disbursements'!$K$28,0) | J57: =IF('6. Cash Receipts-Disbursements'!$G$28>2,'6. Cash Receipts-Disbursements'!$K$28,0) | K57: =IF('6. Cash Receipts-Disbursements'!$G$28>2,'6. Cash Receipts-Disbursements'!$K$28,0) | L57: =IF('6. Cash Receipts-Disbursements'!$G$28>2,'6. Cash Receipts-Disbursements'!$K$28,0) | ... P57: =IF('6. Cash Receipts-Disbursements'!$G$28>2,'6. Cash Receipts-Disbursements'!$K$28,0) | Q57: =SUM(E57:P57)
B58: Depreciation | E58: ='3. Fixed Operating Expenses'!G34 | F58: =E58 | G58: =F58 | H58: =G58 | I58: =H58 | J58: =I58 | K58: =J58 | L58: =K58 | M58: =L58 | ... P58: =O58 | Q58: =SUM(E58:P58)
B59: Interest
C60: Commercial Loan | E60: ='20. Amoritization Schedule'!G23 | F60: ='20. Amoritization Schedule'!H23 | G60: ='20. Amoritization Schedule'!I23 | H60: ='20. Amoritization Schedule'!J23 | I60: ='20. Amoritization Schedule'!K23 | J60: ='20. Amoritization Schedule'!L23 | K60: ='20. Amoritization Schedule'!M23 | L60: ='20. Amoritization Schedule'!N23 | ... P60: ='20. Amoritization Schedule'!R23 | Q60: =SUM(E60:P60)
C61: Commercial Mortgage | E61: ='20. Amoritization Schedule'!G43 | F61: ='20. Amoritization Schedule'!H43 | G61: ='20. Amoritization Schedule'!I43 | H61: ='20. Amoritization Schedule'!J43 | I61: ='20. Amoritization Schedule'!K43 | J61: ='20. Amoritization Schedule'!L43 | K61: ='20. Amoritization Schedule'!M43 | L61: ='20. Amoritization Schedule'!N43 | ... P61: ='20. Amoritization Schedule'!R43 | Q61: =SUM(E61:P61)
C62: Line of Credit | E62: ='16. Cash Flow Statement (3)'!E26 | F62: ='16. Cash Flow Statement (3)'!F26 | G62: ='16. Cash Flow Statement (3)'!G26 | H62: ='16. Cash Flow Statement (3)'!H26 | I62: ='16. Cash Flow Statement (3)'!I26 | J62: ='16. Cash Flow Statement (3)'!J26 | K62: ='16. Cash Flow Statement (3)'!K26 | L62: ='16. Cash Flow Statement (3)'!L26 | ... P62: ='16. Cash Flow Statement (3)'!P26 | Q62: =SUM(E62:P62)
B63: Taxes | E63: =IF(E71>0,(E70)*'6. Cash Receipts-Disbursements'!G25,0) | F63: =IF(F71>0,IF(E71<0,(F70-ABS(E71))*'6. Cash Receipts-Disbursements'!$G$25,'15. Income Statement (3)'!F70*'6. Cash Receipts-Disbursements'!$G$25),IF('15. Income Statement (3)'!E71>0,-('15. Income Statement (3)'!E71*'6. Cash Receipts-Disbursements'!$G$25),0)) | G63: =IF(G71>0,IF(F71<0,(G70-ABS(F71))*'6. Cash Receipts-Disbursements'!$G$25,'15. Income Statement (3)'!G70*'6. Cash Receipts-Disbursements'!$G$25),IF('15. Income Statement (3)'!F71>0,-('15. Income Statement (3)'!F71*'6. Cash Receipts-Disbursements'!$G$25),0)) | H63: =IF(H71>0,IF(G71<0,(H70-ABS(G71))*'6. Cash Receipts-Disbursements'!$G$25,'15. Income Statement (3)'!H70*'6. Cash Receipts-Disbursements'!$G$25),IF('15. Income Statement (3)'!G71>0,-('15. Income Statement (3)'!G71*'6. Cash Receipts-Disbursements'!$G$25),0)) | I63: =IF(I71>0,IF(H71<0,(I70-ABS(H71))*'6. Cash Receipts-Disbursements'!$G$25,'15. Income Statement (3)'!I70*'6. Cash Receipts-Disbursements'!$G$25),IF('15. Income Statement (3)'!H71>0,-('15. Income Statement (3)'!H71*'6. Cash Receipts-Disbursements'!$G$25),0)) | J63: =IF(J71>0,IF(I71<0,(J70-ABS(I71))*'6. Cash Receipts-Disbursements'!$G$25,'15. Income Statement (3)'!J70*'6. Cash Receipts-Disbursements'!$G$25),IF('15. Income Statement (3)'!I71>0,-('15. Income Statement (3)'!I71*'6. Cash Receipts-Disbursements'!$G$25),0)) | K63: =IF(K71>0,IF(J71<0,(K70-ABS(J71))*'6. Cash Receipts-Disbursements'!$G$25,'15. Income Statement (3)'!K70*'6. Cash Receipts-Disbursements'!$G$25),IF('15. Income Statement (3)'!J71>0,-('15. Income Statement (3)'!J71*'6. Cash Receipts-Disbursements'!$G$25),0)) | L63: =IF(L71>0,IF(K71<0,(L70-ABS(K71))*'6. Cash Receipts-Disbursements'!$G$25,'15. Income Statement (3)'!L70*'6. Cash Receipts-Disbursements'!$G$25),IF('15. Income Statement (3)'!K71>0,-('15. Income Statement (3)'!K71*'6. Cash Receipts-Disbursements'!$G$25),0)) | M63: =IF(M71>0,IF(L71<0,(M70-ABS(L71))*'6. Cash Receipts-Disbursements'!$G$25,'15. Income Statement (3)'!M70*'6. Cash Receipts-Disbursements'!$G$25),IF('15. Income Statement (3)'!L71>0,-('15. Income Statement (3)'!L71*'6. Cash Receipts-Disbursements'!$G$25),0)) | ... P63: =IF(P71>0,IF(O71<0,(P70-ABS(O71))*'6. Cash Receipts-Disbursements'!$G$25,'15. Income Statement (3)'!P70*'6. Cash Receipts-Disbursements'!$G$25),IF('15. Income Statement (3)'!O71>0,-('15. Income Statement (3)'!O71*'6. Cash Receipts-Disbursements'!$G$25),0)) | Q63: =SUM(E63:P63)
A64: Total Other Expenses | E64: =SUM(E57:E63) | F64: =SUM(F57:F63) | G64: =SUM(G57:G63) | H64: =SUM(H57:H63) | I64: =SUM(I57:I63) | J64: =SUM(J57:J63) | K64: =SUM(K57:K63) | L64: =SUM(L57:L63) | ... Q64: =SUM(Q57:Q63)
A66: Net Income | E66: =E22-E31-E54-E64 | F66: =F22-F31-F54-F64 | G66: =G22-G31-G54-G64 | H66: =H22-H31-H54-H64 | I66: =I22-I31-I54-I64 | J66: =J22-J31-J54-J64 | K66: =K22-K31-K54-K64 | L66: =L22-L31-L54-L64 | ... Q66: =Q22-Q31-Q54-Q64
E70: =E22-E31-E54-E58-E60-E61-E62 | F70: =F22-F31-F54-F58-F60-F61-F62 | G70: =G22-G31-G54-G58-G60-G61-G62 | H70: =H22-H31-H54-H58-H60-H61-H62 | I70: =I22-I31-I54-I58-I60-I61-I62 | J70: =J22-J31-J54-J58-J60-J61-J62 | K70: =K22-K31-K54-K58-K60-K61-K62 | L70: =L22-L31-L54-L58-L60-L61-L62 | ... P70: =P22-P31-P54-P58-P60-P61-P62
E71: =E70 | F71: =E71+F70 | G71: =F71+G70 | H71: =G71+H70 | I71: =H71+I70 | J71: =I71+J70 | K71: =J71+K70 | L71: =K71+L70 | M71: =L71+M70 | ... P71: =O71+P70

Sheet 16. Cash Flow Statement (3)
A1: ='1. Required Start-Up Funds'!A1
A2: Projected Cash Flow Statement - Year Three
E6: ='4. Projected Sales Forecast'!H6 | F6: ='4. Projected Sales Forecast'!I6 | G6: ='4. Projected Sales Forecast'!J6 | H6: ='4. Projected Sales Forecast'!K6 | I6: ='4. Projected Sales Forecast'!L6 | J6: ='4. Projected Sales Forecast'!M6 | K6: ='4. Projected Sales Forecast'!N6 | L6: ='4. Projected Sales Forecast'!O6 | ... P6: ='4. Projected Sales Forecast'!S6 | Q6: Totals
A8: Beginning Cash Balance | E8: ='13. Cash Flow Statement (2)'!P37 | F8: =E37 | G8: =F37 | H8: =G37 | I8: =H37 | J8: =I37 | K8: =J37 | L8: =K37 | M8: =L37 | ... P8: =O37
A10: Cash Inflows
B11: Income from Sales | E11: ='15. Income Statement (3)'!E13*'6. Cash Receipts-Disbursements'!$G$8 | F11: ='15. Income Statement (3)'!F13*'6. Cash Receipts-Disbursements'!$G$8 | G11: ='15. Income Statement (3)'!G13*'6. Cash Receipts-Disbursements'!$G$8 | H11: ='15. Income Statement (3)'!H13*'6. Cash Receipts-Disbursements'!$G$8 | I11: ='15. Income Statement (3)'!I13*'6. Cash Receipts-Disbursements'!$G$8 | J11: ='15. Income Statement (3)'!J13*'6. Cash Receipts-Disbursements'!$G$8 | K11: ='15. Income Statement (3)'!K13*'6. Cash Receipts-Disbursements'!$G$8 | L11: ='15. Income Statement (3)'!L13*'6. Cash Receipts-Disbursements'!$G$8 | ... P11: ='15. Income Statement (3)'!P13*'6. Cash Receipts-Disbursements'!$G$8 | Q11: =SUM(E11:P11)
B12: Accounts Receivable | E12: =('12. Income Statement (2)'!O13*'6. Cash Receipts-Disbursements'!G10)+('12. Income Statement (2)'!P13*'6. Cash Receipts-Disbursements'!G9) | F12: =('12. Income Statement (2)'!P13*'6. Cash Receipts-Disbursements'!G10)+('15. Income Statement (3)'!E13*'6. Cash Receipts-Disbursements'!G9) | G12: =('15. Income Statement (3)'!E13*'6. Cash Receipts-Disbursements'!$G$10)+('15. Income Statement (3)'!F13*'6. Cash Receipts-Disbursements'!$G$9) | H12: =('15. Income Statement (3)'!F13*'6. Cash Receipts-Disbursements'!$G$10)+('15. Income Statement (3)'!G13*'6. Cash Receipts-Disbursements'!$G$9) | I12: =('15. Income Statement (3)'!G13*'6. Cash Receipts-Disbursements'!$G$10)+('15. Income Statement (3)'!H13*'6. Cash Receipts-Disbursements'!$G$9) | J12: =('15. Income Statement (3)'!H13*'6. Cash Receipts-Disbursements'!$G$10)+('15. Income Statement (3)'!I13*'6. Cash Receipts-Disbursements'!$G$9) | K12: =('15. Income Statement (3)'!I13*'6. Cash Receipts-Disbursements'!$G$10)+('15. Income Statement (3)'!J13*'6. Cash Receipts-Disbursements'!$G$9) | L12: =('15. Income Statement (3)'!J13*'6. Cash Receipts-Disbursements'!$G$10)+('15. Income Statement (3)'!K13*'6. Cash Receipts-Disbursements'!$G$9) | M12: =('15. Income Statement (3)'!K13*'6. Cash Receipts-Disbursements'!$G$10)+('15. Income Statement (3)'!L13*'6. Cash Receipts-Disbursements'!$G$9) | N12: =('15. Income Statement (3)'!L13*'6. Cash Receipts-Disbursements'!$G$10)+('15. Income Statement (3)'!M13*'6. Cash Receipts-Disbursements'!$G$9) | ... P12: =('15. Income Statement (3)'!N13*'6. Cash Receipts-Disbursements'!$G$10)+('15. Income Statement (3)'!O13*'6. Cash Receipts-Disbursements'!$G$9) | Q12: =SUM(E12:P12)
A13: Total Cash Inflows | E13: =SUM(E11:E12) | F13: =SUM(F11:F12) | G13: =SUM(G11:G12) | H13: =SUM(H11:H12) | I13: =SUM(I11:I12) | J13: =SUM(J11:J12) | K13: =SUM(K11:K12) | L13: =SUM(L11:L12) | ... Q13: =SUM(Q11:Q12)
A15: Cash Outflows
B16: Investing Activities
C17: New Capital Purchases | E17: 0 | F17: 0 | G17: 0 | H17: 0 | I17: 0 | J17: 0 | K17: 0 | L17: 0 | M17: 0 | N17: 0 | O17: 0 | P17: 0 | Q17: =SUM(E17:P17)
C18: Inventory Purchases | E18: 0 | F18: 0 | G18: 0 | H18: 0 | I18: 0 | J18: 0 | K18: 0 | L18: 0 | M18: 0 | N18: 0 | O18: 0 | P18: 0 | Q18: =SUM(E18:P18)
C19: Cost of Sales | E19: =('6. Cash Receipts-Disbursements'!G15*'15. Income Statement (3)'!E20)+('6. Cash Receipts-Disbursements'!G16*'12. Income Statement (2)'!P20)+('6. Cash Receipts-Disbursements'!G17*'12. Income Statement (2)'!O13) | F19: =('6. Cash Receipts-Disbursements'!G15*'15. Income Statement (3)'!F20)+('6. Cash Receipts-Disbursements'!G16*'15. Income Statement (3)'!E20)+('6. Cash Receipts-Disbursements'!G17*'12. Income Statement (2)'!P20) | G19: =('6. Cash Receipts-Disbursements'!$G$15*'15. Income Statement (3)'!G20)+('6. Cash Receipts-Disbursements'!$G$16*'15. Income Statement (3)'!F20)+('6. Cash Receipts-Disbursements'!$G$17*'15. Income Statement (3)'!E20) | H19: =('6. Cash Receipts-Disbursements'!$G$15*'15. Income Statement (3)'!H20)+('6. Cash Receipts-Disbursements'!$G$16*'15. Income Statement (3)'!G20)+('6. Cash Receipts-Disbursements'!$G$17*'15. Income Statement (3)'!F20) | I19: =('6. Cash Receipts-Disbursements'!$G$15*'15. Income Statement (3)'!I20)+('6. Cash Receipts-Disbursements'!$G$16*'15. Income Statement (3)'!H20)+('6. Cash Receipts-Disbursements'!$G$17*'15. Income Statement (3)'!G20) | J19: =('6. Cash Receipts-Disbursements'!$G$15*'15. Income Statement (3)'!J20)+('6. Cash Receipts-Disbursements'!$G$16*'15. Income Statement (3)'!I20)+('6. Cash Receipts-Disbursements'!$G$17*'15. Income Statement (3)'!H20) | K19: =('6. Cash Receipts-Disbursements'!$G$15*'15. Income Statement (3)'!K20)+('6. Cash Receipts-Disbursements'!$G$16*'15. Income Statement (3)'!J20)+('6. Cash Receipts-Disbursements'!$G$17*'15. Income Statement (3)'!I20) | L19: =('6. Cash Receipts-Disbursements'!$G$15*'15. Income Statement (3)'!L20)+('6. Cash Receipts-Disbursements'!$G$16*'15. Income Statement (3)'!K20)+('6. Cash Receipts-Disbursements'!$G$17*'15. Income Statement (3)'!J20) | M19: =('6. Cash Receipts-Disbursements'!$G$15*'15. Income Statement (3)'!M20)+('6. Cash Receipts-Disbursements'!$G$16*'15. Income Statement (3)'!L20)+('6. Cash Receipts-Disbursements'!$G$17*'15. Income Statement (3)'!K20) | N19: =('6. Cash Receipts-Disbursements'!$G$15*'15. Income Statement (3)'!N20)+('6. Cash Receipts-Disbursements'!$G$16*'15. Income Statement (3)'!M20)+('6. Cash Receipts-Disbursements'!$G$17*'15. Income Statement (3)'!L20) | ... P19: =('6. Cash Receipts-Disbursements'!$G$15*'15. Income Statement (3)'!P20)+('6. Cash Receipts-Disbursements'!$G$16*'15. Income Statement (3)'!O20)+('6. Cash Receipts-Disbursements'!$G$17*'15. Income Statement (3)'!N20) | Q19: =SUM(E19:P19)
B20: Operating Activities
C21: ='8. Income Statement'!A24 | E21: ='15. Income Statement (3)'!E31 | F21: ='15. Income Statement (3)'!F31 | G21: ='15. Income Statement (3)'!G31 | H21: ='15. Income Statement (3)'!H31 | I21: ='15. Income Statement (3)'!I31 | J21: ='15. Income Statement (3)'!J31 | K21: ='15. Income Statement (3)'!K31 | L21: ='15. Income Statement (3)'!L31 | ... P21: ='15. Income Statement (3)'!P31 | Q21: =SUM(E21:P21)
C22: ='8. Income Statement'!A33 | E22: ='15. Income Statement (3)'!E54 | F22: ='15. Income Statement (3)'!F54 | G22: ='15. Income Statement (3)'!G54 | H22: ='15. Income Statement (3)'!H54 | I22: ='15. Income Statement (3)'!I54 | J22: ='15. Income Statement (3)'!J54 | K22: ='15. Income Statement (3)'!K54 | L22: ='15. Income Statement (3)'!L54 | ... P22: ='15. Income Statement (3)'!P54 | Q22: =SUM(E22:P22)
C23: Taxes | E23: 0 | F23: 0 | G23: =SUM('15. Income Statement (3)'!E63:G63) | H23: 0 | I23: 0 | J23: =SUM('15. Income Statement (3)'!H63:J63) | K23: 0 | L23: 0 | M23: =SUM('15. Income Statement (3)'!K63:M63) | N23: 0 | O23: 0 | P23: =SUM('15. Income Statement (3)'!N63:P63) | Q23: =SUM(E23:P23)
B24: Financing Activities | Q24: =SUM(E24:P24)
C25: Loan Payments | E25: ='1. Required Start-Up Funds'!J42 | F25: =E25 | G25: =F25 | H25: =G25 | I25: =H25 | J25: =I25 | K25: =J25 | L25: =K25 | M25: =L25 | ... P25: =O25 | Q25: =SUM(E25:P25)
C26: Line of Credit Interest | E26: ='6. Cash Receipts-Disbursements'!G22/12*'13. Cash Flow Statement (2)'!P40 | F26: ='6. Cash Receipts-Disbursements'!G22/12*'16. Cash Flow Statement (3)'!E40 | G26: =('6. Cash Receipts-Disbursements'!$G$22/12)*F40 | H26: =('6. Cash Receipts-Disbursements'!$G$22/12)*G40 | I26: =('6. Cash Receipts-Disbursements'!$G$22/12)*H40 | J26: =('6. Cash Receipts-Disbursements'!$G$22/12)*I40 | K26: =('6. Cash Receipts-Disbursements'!$G$22/12)*J40 | L26: =('6. Cash Receipts-Disbursements'!$G$22/12)*K40 | M26: =('6. Cash Receipts-Disbursements'!$G$22/12)*L40 | N26: =('6. Cash Receipts-Disbursements'!$G$22/12)*M40 | ... P26: =('6. Cash Receipts-Disbursements'!$G$22/12)*O40 | Q26: =SUM(E26:P26)
C27: Line of Credit Repayments | E27: 0 | F27: 0 | G27: 0 | H27: 0 | I27: 0 | J27: 0 | K27: 0 | L27: 0 | M27: 0 | N27: 0 | O27: 0 | P27: 0 | Q27: =SUM(E27:P27)
C28: Dividends Paid | E28: 0 | F28: 0 | G28: 0 | H28: 0 | I28: 0 | J28: 0 | K28: 0 | L28: 0 | M28: 0 | N28: 0 | O28: 0 | P28: 0 | Q28: =SUM(E28:P28)
A29: Total Cash Outflows | E29: =SUM(E17:E28) | F29: =SUM(F17:F28) | G29: =SUM(G17:G28) | H29: =SUM(H17:H28) | I29: =SUM(I17:I28) | J29: =SUM(J17:J28) | K29: =SUM(K17:K28) | L29: =SUM(L17:L28) | ... Q29: =SUM(Q17:Q28)
A31: Cash Flow | E31: =E13-E29 | F31: =F13-F29 | G31: =G13-G29 | H31: =H13-H29 | I31: =I13-I29 | J31: =J13-J29 | K31: =K13-K29 | L31: =L13-L29 | ... Q31: =Q13-Q29
A33: Operating Cash Balance | E33: =E8+E31 | F33: =F8+F31 | G33: =G8+G31 | H33: =H8+H31 | I33: =I8+I31 | J33: =J8+J31 | K33: =K8+K31 | L33: =L8+L31 | ... P33: =P8+P31
A35: Line of Credit Drawdowns | E35: =IF((E33-'6. Cash Receipts-Disbursements'!$G$21)<0,'6. Cash Receipts-Disbursements'!$G$21-'16. Cash Flow Statement (3)'!E33,0) | F35: =IF((F33-'6. Cash Receipts-Disbursements'!$G$21)<0,'6. Cash Receipts-Disbursements'!$G$21-'16. Cash Flow Statement (3)'!F33,0) | G35: =IF((G33-'6. Cash Receipts-Disbursements'!$G$21)<0,'6. Cash Receipts-Disbursements'!$G$21-'16. Cash Flow Statement (3)'!G33,0) | H35: =IF((H33-'6. Cash Receipts-Disbursements'!$G$21)<0,'6. Cash Receipts-Disbursements'!$G$21-'16. Cash Flow Statement (3)'!H33,0) | I35: =IF((I33-'6. Cash Receipts-Disbursements'!$G$21)<0,'6. Cash Receipts-Disbursements'!$G$21-'16. Cash Flow Statement (3)'!I33,0) | J35: =IF((J33-'6. Cash Receipts-Disbursements'!$G$21)<0,'6. Cash Receipts-Disbursements'!$G$21-'16. Cash Flow Statement (3)'!J33,0) | K35: =IF((K33-'6. Cash Receipts-Disbursements'!$G$21)<0,'6. Cash Receipts-Disbursements'!$G$21-'16. Cash Flow Statement (3)'!K33,0) | L35: =IF((L33-'6. Cash Receipts-Disbursements'!$G$21)<0,'6. Cash Receipts-Disbursements'!$G$21-'16. Cash Flow Statement (3)'!L33,0) | ... P35: =IF((P33-'6. Cash Receipts-Disbursements'!$G$21)<0,'6. Cash Receipts-Disbursements'!$G$21-'16. Cash Flow Statement (3)'!P33,0) | Q35: =SUM(E35:P35)
A37: Ending Cash Balance | E37: =E33+E35 | F37: =F33+F35 | G37: =G33+G35 | H37: =H33+H35 | I37: =I33+I35 | J37: =J33+J35 | K37: =K33+K35 | L37: =L33+L35 | ... P37: =P33+P35
A40: Line of Credit Balance | E40: =E35+'13. Cash Flow Statement (2)'!P40-'16. Cash Flow Statement (3)'!E27 | F40: =E40+F35-F27 | G40: =F40+G35-G27 | H40: =G40+H35-H27 | I40: =H40+I35-I27 | J40: =I40+J35-J27 | K40: =J40+K35-K27 | L40: =K40+L35-L27 | M40: =L40+M35-M27 | ... P40: =O40+P35-P27

Sheet 17. Balance Sheet (3)
A1: ='1. Required Start-Up Funds'!A1
A2: Balance Sheet - Year Three
F6: End of Year Two | I6: End of Year Three
A8: Assets
B9: Current Assets
C10: Cash | F10: ='14. Balance Sheet (2)'!I10 | I10: ='16. Cash Flow Statement (3)'!P37
C11: Accounts Receivable | F11: ='14. Balance Sheet (2)'!I11 | I11: =F11+'15. Income Statement (3)'!Q13-'16. Cash Flow Statement (3)'!Q13
C12: Inventory | F12: ='14. Balance Sheet (2)'!I12 | I12: =F12
C13: Prepaid Expenses | F13: ='14. Balance Sheet (2)'!I13 | I13: =IF(F13='7. Beginning Balance Sheet'!F14,'7. Beginning Balance Sheet'!F14,'17. Balance Sheet (3)'!F13-'6. Cash Receipts-Disbursements'!J26)
C14: Other Current | F14: ='14. Balance Sheet (2)'!I14 | I14: =IF(F14='7. Beginning Balance Sheet'!F14,'7. Beginning Balance Sheet'!F14,'17. Balance Sheet (3)'!F14-'6. Cash Receipts-Disbursements'!J27)
B15: Total Current Assets | F15: =SUM(F10:F14) | I15: =SUM(I10:I14)
B17: Fixed Assets
C18: ='1. Required Start-Up Funds'!C8 | F18: ='14. Balance Sheet (2)'!I18 | I18: =F18
C19: ='1. Required Start-Up Funds'!C9 | F19: ='14. Balance Sheet (2)'!I19 | I19: =F19
C20: ='1. Required Start-Up Funds'!C10 | F20: ='14. Balance Sheet (2)'!I20 | I20: =F20
C21: ='1. Required Start-Up Funds'!C11 | F21: ='14. Balance Sheet (2)'!I21 | I21: =F21
C22: ='1. Required Start-Up Funds'!C12 | F22: ='14. Balance Sheet (2)'!I22 | I22: =F22
C23: ='1. Required Start-Up Funds'!C13 | F23: ='14. Balance Sheet (2)'!I23 | I23: =F23
C24: ='1. Required Start-Up Funds'!C14 | F24: ='14. Balance Sheet (2)'!I24 | I24: =F24+'16. Cash Flow Statement (3)'!Q17
B25: Total Fixed Assets | F25: =SUM(F18:F24) | I25: =SUM(I18:I24)
B27: Less: Accumulated Depreciation | F27: ='14. Balance Sheet (2)'!I27 | I27: =F27+'15. Income Statement (3)'!Q58
A29: Total Assets | F29: =INT(F15+F25-F27) | I29: =INT(I15+I25-I27)
A33: Liabilities and Owner's Equity
B34: Liabilities
C35: Accounts Payable | F35: ='14. Balance Sheet (2)'!I35 | I35: =F35+'15. Income Statement (3)'!Q20-'16. Cash Flow Statement (3)'!Q19
C36: Notes Payable | F36: ='14. Balance Sheet (2)'!I36 | I36: ='20. Amoritization Schedule'!R25+'7. Beginning Balance Sheet'!F36
C37: Mortgage Payable | F37: ='14. Balance Sheet (2)'!I37 | I37: ='20. Amoritization Schedule'!R45+'7. Beginning Balance Sheet'!F37
C38: Line of Credit Balance | F38: ='14. Balance Sheet (2)'!I38 | I38: ='16. Cash Flow Statement (3)'!P40+'7. Beginning Balance Sheet'!F38
B39: Total Liabilities | F39: =SUM(F35:F38) | I39: =SUM(I35:I38)
B41: Owner's Equity
C42: Common Stock | F42: ='14. Balance Sheet (2)'!I42 | I42: =F42
C43: Retained Earnings | F43: ='14. Balance Sheet (2)'!I43 | I43: =F43+'15. Income Statement (3)'!Q66
C44: Dividends Dispersed | F44: ='14. Balance Sheet (2)'!I44 | I44: =F44+'16. Cash Flow Statement (3)'!Q28
B45: Total Owner's Equity | F45: =F42+F43-F44 | I45: =I42+I43-I44
A47: Total Liabilities and Owner's Equity | F47: =INT(F39+F45) | I47: =INT(I39+I45)
F50: =IF(F29=F47,"Statement Balances","Does Not Balance") | I50: =IF(I29-I47=0,"Statement Balances","Does Not Balance")

Sheet 18. Financial Ratios
A1: ='1. Required Start-Up Funds'!A1
A2: Financial Ratios
A6: Ratio | G6: Year One | I6: Year Two | K6: Year Three
B7: Liquidity
C8: Current Ratio | G8: =IF('10. Balance Sheet'!I39=0,0,'10. Balance Sheet'!I15/'10. Balance Sheet'!I39) | I8: =IF('14. Balance Sheet (2)'!I39=0,0,'14. Balance Sheet (2)'!I15/'14. Balance Sheet (2)'!I39) | K8: =IF('17. Balance Sheet (3)'!I39=0,0,'17. Balance Sheet (3)'!I15/'17. Balance Sheet (3)'!I39)
C9: Quick Ratio | G9: =IF('10. Balance Sheet'!I39=0,0,('10. Balance Sheet'!I10+'10. Balance Sheet'!I11)/'10. Balance Sheet'!I39) | I9: =IF('14. Balance Sheet (2)'!I39=0,0,('14. Balance Sheet (2)'!I10+'14. Balance Sheet (2)'!I11)/'14. Balance Sheet (2)'!I39) | K9: =IF('17. Balance Sheet (3)'!I39=0,0,('17. Balance Sheet (3)'!I10+'17. Balance Sheet (3)'!I11)/'17. Balance Sheet (3)'!I39)
B10: Safety
C11: Debt to Equity Ratio | G11: =IF('10. Balance Sheet'!I45=0,0,'10. Balance Sheet'!I39/'10. Balance Sheet'!I45) | I11: =IF('14. Balance Sheet (2)'!I45=0,0,'14. Balance Sheet (2)'!I39/'14. Balance Sheet (2)'!I45) | K11: =IF('17. Balance Sheet (3)'!I45=0,0,'17. Balance Sheet (3)'!I39/'17. Balance Sheet (3)'!I45)
C12: Debt to Coverage Ratio | G12: =IF('10. Balance Sheet'!I39=0,0,('8. Income Statement'!Q66+'8. Income Statement'!Q58)/'10. Balance Sheet'!I39) | I12: =IF('14. Balance Sheet (2)'!I39=0,0,('12. Income Statement (2)'!Q66+'12. Income Statement (2)'!Q58)/'14. Balance Sheet (2)'!I39) | K12: =IF('17. Balance Sheet (3)'!I39=0,0,('15. Income Statement (3)'!Q66+'15. Income Statement (3)'!Q58)/'17. Balance Sheet (3)'!I39)
B13: Profitability
C14: Sales Growth | G14: 0 | I14: =IF('8. Income Statement'!Q13=0,0,('12. Income Statement (2)'!Q13-'8. Income Statement'!Q13)/'8. Income Statement'!Q13) | K14: =IF('12. Income Statement (2)'!Q13=0,0,('15. Income Statement (3)'!Q13-'12. Income Statement (2)'!Q13)/'12. Income Statement (2)'!Q13)
C15: COGS to Sales | G15: =IF('8. Income Statement'!Q13=0,0,'8. Income Statement'!Q20/'8. Income Statement'!Q13) | I15: =IF('12. Income Statement (2)'!Q13=0,0,'12. Income Statement (2)'!Q20/'12. Income Statement (2)'!Q13) | K15: =IF('15. Income Statement (3)'!Q13=0,0,'15. Income Statement (3)'!Q20/'15. Income Statement (3)'!Q13)
C16: Gross Profit Margin | G16: =IF('8. Income Statement'!Q13=0,0,'8. Income Statement'!Q22/'8. Income Statement'!Q13) | I16: =IF('12. Income Statement (2)'!Q13=0,0,'12. Income Statement (2)'!Q22/'12. Income Statement (2)'!Q13) | K16: =IF('15. Income Statement (3)'!Q13=0,0,'15. Income Statement (3)'!Q22/'15. Income Statement (3)'!Q13)
C17: SG&A to Sales | G17: =IF('8. Income Statement'!Q13=0,0,('8. Income Statement'!Q31+'8. Income Statement'!Q54)/'8. Income Statement'!Q13) | I17: =IF('12. Income Statement (2)'!Q13=0,0,('12. Income Statement (2)'!Q31+'12. Income Statement (2)'!Q54)/'12. Income Statement (2)'!Q13) | K17: =IF('15. Income Statement (3)'!Q13=0,0,('15. Income Statement (3)'!Q31+'15. Income Statement (3)'!Q54)/'15. Income Statement (3)'!Q13)
C18: Net Profit Margin | G18: =IF('8. Income Statement'!Q13=0,0,'8. Income Statement'!Q66/'8. Income Statement'!Q13) | I18: =IF('12. Income Statement (2)'!Q13=0,0,'12. Income Statement (2)'!Q66/'12. Income Statement (2)'!Q13) | K18: =IF('15. Income Statement (3)'!Q13=0,0,'15. Income Statement (3)'!Q66/'15. Income Statement (3)'!Q13)
C19: Return on Equity | G19: =IF('10. Balance Sheet'!I45=0,0,'8. Income Statement'!Q66/'10. Balance Sheet'!I45) | I19: =IF('14. Balance Sheet (2)'!I45=0,0,'12. Income Statement (2)'!Q66/'14. Balance Sheet (2)'!I45) | K19: =IF('17. Balance Sheet (3)'!I45=0,0,'15. Income Statement (3)'!Q66/'17. Balance Sheet (3)'!I45)
C20: Return on Assets | G20: =IF('10. Balance Sheet'!I29=0,0,'8. Income Statement'!Q66/'10. Balance Sheet'!I29) | I20: =IF('14. Balance Sheet (2)'!I29=0,0,'12. Income Statement (2)'!Q66/'14. Balance Sheet (2)'!I29) | K20: =IF('17. Balance Sheet (3)'!I29=0,0,'15. Income Statement (3)'!Q66/'17. Balance Sheet (3)'!I29)
C21: Owner's Compensation to Sales | G21: =IF('8. Income Statement'!Q13=0,0,'8. Income Statement'!Q25/'8. Income Statement'!Q13) | I21: =IF('12. Income Statement (2)'!Q13=0,0,'12. Income Statement (2)'!Q25/'12. Income Statement (2)'!Q13) | K21: =IF('15. Income Statement (3)'!Q13=0,0,'15. Income Statement (3)'!Q25/'15. Income Statement (3)'!Q13)
B22: Efficiency
C23: Days in Receivables | G23: =IF('8. Income Statement'!Q13=0,0,('10. Balance Sheet'!I11/'8. Income Statement'!Q13)*360) | I23: =IF('12. Income Statement (2)'!Q13=0,0,('14. Balance Sheet (2)'!I11/'12. Income Statement (2)'!Q13)*360) | K23: =IF('15. Income Statement (3)'!Q13=0,0,('17. Balance Sheet (3)'!I11/'15. Income Statement (3)'!Q13)*360)
C24: Accounts Receivable Turnover | G24: =IF('10. Balance Sheet'!I11=0,0,'8. Income Statement'!Q13/'10. Balance Sheet'!I11) | I24: =IF('14. Balance Sheet (2)'!I11=0,0,'12. Income Statement (2)'!Q13/'14. Balance Sheet (2)'!I11) | K24: =IF('17. Balance Sheet (3)'!I11=0,0,'15. Income Statement (3)'!Q13/'17. Balance Sheet (3)'!I11)
C25: Days in Inventory | G25: =IF('8. Income Statement'!Q20=0,0,('10. Balance Sheet'!I12/'8. Income Statement'!Q20)*360) | I25: =IF('12. Income Statement (2)'!Q20=0,0,('14. Balance Sheet (2)'!I12/'12. Income Statement (2)'!Q20)*360) | K25: =IF('15. Income Statement (3)'!Q20=0,0,('17. Balance Sheet (3)'!I12/'15. Income Statement (3)'!Q20)*360)
C26: Inventory Turnover | G26: =IF('10. Balance Sheet'!I12=0,0,'8. Income Statement'!Q20/'10. Balance Sheet'!I12) | I26: =IF('14. Balance Sheet (2)'!I12=0,0,'12. Income Statement (2)'!Q20/'14. Balance Sheet (2)'!I12) | K26: =IF('17. Balance Sheet (3)'!I12=0,0,'15. Income Statement (3)'!Q20/'17. Balance Sheet (3)'!I12)
C27: Sales to Total Assets | G27: =IF('10. Balance Sheet'!I29=0,0,'8. Income Statement'!Q13/'10. Balance Sheet'!I29) | I27: =IF('14. Balance Sheet (2)'!I29=0,0,'12. Income Statement (2)'!Q13/'14. Balance Sheet (2)'!I29) | K27: =IF('17. Balance Sheet (3)'!I29=0,0,'15. Income Statement (3)'!Q13/'17. Balance Sheet (3)'!I29)

Sheet 19. Breakeven Analysis
A1: ='1. Required Start-Up Funds'!A1
A2: Breakeven Analysis
A6: Breakeven Analysis | G6: Dollars | I6: Percent
B7: Annual Sales Revenue | G7: ='8. Income Statement'!Q13 | I7: 1
B8: Cost of Sales | G8: ='8. Income Statement'!Q20 | I8: =IF(G8=0,0,G8/G7)
B9: Gross Margin | G9: ='8. Income Statement'!Q22 | I9: =IF(G9=0,0,G9/G7)
B11: Salaries and Wages | G11: ='2. Salaries and Wages'!M35
B12: Fixed Operating Expenses | G12: ='3. Fixed Operating Expenses'!I41
B13: Total Fixed Business Expenses | G13: =SUM(G11:G12)
B15: Breakeven Sales Calculation | G15: =G13
G16: =I9
B18: Breakeven Sales in Dollars | G18: =IF(G16=0,0,G15/G16)

Sheet 20. Amoritization Schedule
A1: ='1. Required Start-Up Funds'!A1
A2: Amortization Schedule
A6: Loan Type | E6: Assumptions | G6: ='4. Projected Sales Forecast'!H6 | H6: ='4. Projected Sales Forecast'!I6 | I6: ='4. Projected Sales Forecast'!J6 | J6: ='4. Projected Sales Forecast'!K6 | K6: ='4. Projected Sales Forecast'!L6 | L6: ='4. Projected Sales Forecast'!M6 | M6: ='4. Projected Sales Forecast'!N6 | N6: ='4. Projected Sales Forecast'!O6 | ... R6: ='4. Projected Sales Forecast'!S6 | S6: Totals
A8: Commercial Loan
B9: Principal Amount | E9: ='1. Required Start-Up Funds'!G40
B10: Interest Rate | E10: ='1. Required Start-Up Funds'!H40
B11: Loan Term in Months | E11: ='1. Required Start-Up Funds'!I40
B12: Monthly Payment Amount | E12: =ABS(PMT(E10/12,E11,E9))
B14: Year One
C15: Interest | G15: =ABS(IPMT($E$10/12,1,$E$11,$E$9)) | H15: =ABS(IPMT($E$10/12,2,$E$11,$E$9)) | I15: =ABS(IPMT($E$10/12,3,$E$11,$E$9)) | J15: =ABS(IPMT($E$10/12,4,$E$11,$E$9)) | K15: =ABS(IPMT($E$10/12,5,$E$11,$E$9)) | L15: =ABS(IPMT($E$10/12,6,$E$11,$E$9)) | M15: =ABS(IPMT($E$10/12,7,$E$11,$E$9)) | N15: =ABS(IPMT($E$10/12,8,$E$11,$E$9)) | O15: =ABS(IPMT($E$10/12,9,$E$11,$E$9)) | P15: =ABS(IPMT($E$10/12,10,$E$11,$E$9)) | Q15: =ABS(IPMT($E$10/12,11,$E$11,$E$9)) | R15: =ABS(IPMT($E$10/12,12,$E$11,$E$9)) | S15: =SUM(G15:R15)
C16: Principal | G16: =ABS(PPMT($E$10/12,1,$E$11,$E$9)) | H16: =ABS(PPMT($E$10/12,2,$E$11,$E$9)) | I16: =ABS(PPMT($E$10/12,3,$E$11,$E$9)) | J16: =ABS(PPMT($E$10/12,4,$E$11,$E$9)) | K16: =ABS(PPMT($E$10/12,5,$E$11,$E$9)) | L16: =ABS(PPMT($E$10/12,6,$E$11,$E$9)) | M16: =ABS(PPMT($E$10/12,7,$E$11,$E$9)) | N16: =ABS(PPMT($E$10/12,8,$E$11,$E$9)) | O16: =ABS(PPMT($E$10/12,9,$E$11,$E$9)) | P16: =ABS(PPMT($E$10/12,10,$E$11,$E$9)) | Q16: =ABS(PPMT($E$10/12,11,$E$11,$E$9)) | R16: =ABS(PPMT($E$10/12,12,$E$11,$E$9)) | S16: =SUM(G16:R16)
C17: Loan Balance | G17: =$E$9-G16 | H17: =G17-H16 | I17: =H17-I16 | J17: =I17-J16 | K17: =J17-K16 | L17: =K17-L16 | M17: =L17-M16 | N17: =M17-N16 | O17: =N17-O16 | ... R17: =Q17-R16
B18: Year Two
C19: Interest | G19: =ABS(IPMT($E$10/12,13,$E$11,$E$9)) | H19: =ABS(IPMT($E$10/12,14,$E$11,$E$9)) | I19: =ABS(IPMT($E$10/12,15,$E$11,$E$9)) | J19: =ABS(IPMT($E$10/12,16,$E$11,$E$9)) | K19: =ABS(IPMT($E$10/12,17,$E$11,$E$9)) | L19: =ABS(IPMT($E$10/12,18,$E$11,$E$9)) | M19: =ABS(IPMT($E$10/12,19,$E$11,$E$9)) | N19: =ABS(IPMT($E$10/12,20,$E$11,$E$9)) | O19: =ABS(IPMT($E$10/12,21,$E$11,$E$9)) | P19: =ABS(IPMT($E$10/12,22,$E$11,$E$9)) | Q19: =ABS(IPMT($E$10/12,23,$E$11,$E$9)) | R19: =ABS(IPMT($E$10/12,24,$E$11,$E$9)) | S19: =SUM(G19:R19)
C20: Principal | G20: =ABS(PPMT($E$10/12,13,$E$11,$E$9)) | H20: =ABS(PPMT($E$10/12,14,$E$11,$E$9)) | I20: =ABS(PPMT($E$10/12,15,$E$11,$E$9)) | J20: =ABS(PPMT($E$10/12,16,$E$11,$E$9)) | K20: =ABS(PPMT($E$10/12,17,$E$11,$E$9)) | L20: =ABS(PPMT($E$10/12,18,$E$11,$E$9)) | M20: =ABS(PPMT($E$10/12,19,$E$11,$E$9)) | N20: =ABS(PPMT($E$10/12,20,$E$11,$E$9)) | O20: =ABS(PPMT($E$10/12,21,$E$11,$E$9)) | P20: =ABS(PPMT($E$10/12,22,$E$11,$E$9)) | Q20: =ABS(PPMT($E$10/12,23,$E$11,$E$9)) | R20: =ABS(PPMT($E$10/12,24,$E$11,$E$9)) | S20: =SUM(G20:R20)
C21: Loan Balance | G21: =R17-G20 | H21: =G21-H20 | I21: =H21-I20 | J21: =I21-J20 | K21: =J21-K20 | L21: =K21-L20 | M21: =L21-M20 | N21: =M21-N20 | O21: =N21-O20 | ... R21: =Q21-R20
B22: Year Three
C23: Interest | G23: =ABS(IPMT($E$10/12,25,$E$11,$E$9)) | H23: =ABS(IPMT($E$10/12,26,$E$11,$E$9)) | I23: =ABS(IPMT($E$10/12,27,$E$11,$E$9)) | J23: =ABS(IPMT($E$10/12,28,$E$11,$E$9)) | K23: =ABS(IPMT($E$10/12,29,$E$11,$E$9)) | L23: =ABS(IPMT($E$10/12,30,$E$11,$E$9)) | M23: =ABS(IPMT($E$10/12,31,$E$11,$E$9)) | N23: =ABS(IPMT($E$10/12,32,$E$11,$E$9)) | O23: =ABS(IPMT($E$10/12,33,$E$11,$E$9)) | P23: =ABS(IPMT($E$10/12,34,$E$11,$E$9)) | Q23: =ABS(IPMT($E$10/12,35,$E$11,$E$9)) | R23: =ABS(IPMT($E$10/12,36,$E$11,$E$9)) | S23: =SUM(G23:R23)
C24: Principal | G24: =ABS(PPMT($E$10/12,25,$E$11,$E$9)) | H24: =ABS(PPMT($E$10/12,26,$E$11,$E$9)) | I24: =ABS(PPMT($E$10/12,27,$E$11,$E$9)) | J24: =ABS(PPMT($E$10/12,28,$E$11,$E$9)) | K24: =ABS(PPMT($E$10/12,29,$E$11,$E$9)) | L24: =ABS(PPMT($E$10/12,30,$E$11,$E$9)) | M24: =ABS(PPMT($E$10/12,31,$E$11,$E$9)) | N24: =ABS(PPMT($E$10/12,32,$E$11,$E$9)) | O24: =ABS(PPMT($E$10/12,33,$E$11,$E$9)) | P24: =ABS(PPMT($E$10/12,34,$E$11,$E$9)) | Q24: =ABS(PPMT($E$10/12,35,$E$11,$E$9)) | R24: =ABS(PPMT($E$10/12,36,$E$11,$E$9)) | S24: =SUM(G24:R24)
C25: Loan Balance | G25: =R21-G24 | H25: =G25-H24 | I25: =H25-I24 | J25: =I25-J24 | K25: =J25-K24 | L25: =K25-L24 | M25: =L25-M24 | N25: =M25-N24 | O25: =N25-O24 | ... R25: =Q25-R24
A28: Commercial Mortgage
B29: Principal Amount | E29: ='1. Required Start-Up Funds'!G41
B30: Interest Rate | E30: ='1. Required Start-Up Funds'!H41
B31: Loan Term in Months | E31: ='1. Required Start-Up Funds'!I41
B32: Monthly Payment Amount | E32: =ABS(PMT(E30/12,E31,E29))
B34: Year One
C35: Interest | G35: =ABS(IPMT($E$30/12,1,$E$31,$E$29)) | H35: =ABS(IPMT($E$30/12,2,$E$31,$E$29)) | I35: =ABS(IPMT($E$30/12,3,$E$31,$E$29)) | J35: =ABS(IPMT($E$30/12,4,$E$31,$E$29)) | K35: =ABS(IPMT($E$30/12,5,$E$31,$E$29)) | L35: =ABS(IPMT($E$30/12,6,$E$31,$E$29)) | M35: =ABS(IPMT($E$30/12,7,$E$31,$E$29)) | N35: =ABS(IPMT($E$30/12,8,$E$31,$E$29)) | O35: =ABS(IPMT($E$30/12,9,$E$31,$E$29)) | P35: =ABS(IPMT($E$30/12,10,$E$31,$E$29)) | Q35: =ABS(IPMT($E$30/12,11,$E$31,$E$29)) | R35: =ABS(IPMT($E$30/12,12,$E$31,$E$29)) | S35: =SUM(G35:R35)
C36: Principal | G36: =ABS(PPMT($E$30/12,1,$E$31,$E$29)) | H36: =ABS(PPMT($E$30/12,2,$E$31,$E$29)) | I36: =ABS(PPMT($E$30/12,3,$E$31,$E$29)) | J36: =ABS(PPMT($E$30/12,4,$E$31,$E$29)) | K36: =ABS(PPMT($E$30/12,5,$E$31,$E$29)) | L36: =ABS(PPMT($E$30/12,6,$E$31,$E$29)) | M36: =ABS(PPMT($E$30/12,7,$E$31,$E$29)) | N36: =ABS(PPMT($E$30/12,8,$E$31,$E$29)) | O36: =ABS(PPMT($E$30/12,9,$E$31,$E$29)) | P36: =ABS(PPMT($E$30/12,10,$E$31,$E$29)) | Q36: =ABS(PPMT($E$30/12,11,$E$31,$E$29)) | R36: =ABS(PPMT($E$30/12,12,$E$31,$E$29)) | S36: =SUM(G36:R36)
C37: Loan Balance | G37: =E29-G36 | H37: =G37-H36 | I37: =H37-I36 | J37: =I37-J36 | K37: =J37-K36 | L37: =K37-L36 | M37: =L37-M36 | N37: =M37-N36 | O37: =N37-O36 | ... R37: =Q37-R36
B38: Year Two
C39: Interest | G39: =ABS(IPMT($E$30/12,13,$E$31,$E$29)) | H39: =ABS(IPMT($E$30/12,14,$E$31,$E$29)) | I39: =ABS(IPMT($E$30/12,15,$E$31,$E$29)) | J39: =ABS(IPMT($E$30/12,16,$E$31,$E$29)) | K39: =ABS(IPMT($E$30/12,17,$E$31,$E$29)) | L39: =ABS(IPMT($E$30/12,18,$E$31,$E$29)) | M39: =ABS(IPMT($E$30/12,19,$E$31,$E$29)) | N39: =ABS(IPMT($E$30/12,20,$E$31,$E$29)) | O39: =ABS(IPMT($E$30/12,21,$E$31,$E$29)) | P39: =ABS(IPMT($E$30/12,22,$E$31,$E$29)) | Q39: =ABS(IPMT($E$30/12,23,$E$31,$E$29)) | R39: =ABS(IPMT($E$30/12,24,$E$31,$E$29)) | S39: =SUM(G39:R39)
C40: Principal | G40: =ABS(PPMT($E$30/12,13,$E$31,$E$29)) | H40: =ABS(PPMT($E$30/12,14,$E$31,$E$29)) | I40: =ABS(PPMT($E$30/12,15,$E$31,$E$29)) | J40: =ABS(PPMT($E$30/12,16,$E$31,$E$29)) | K40: =ABS(PPMT($E$30/12,17,$E$31,$E$29)) | L40: =ABS(PPMT($E$30/12,18,$E$31,$E$29)) | M40: =ABS(PPMT($E$30/12,19,$E$31,$E$29)) | N40: =ABS(PPMT($E$30/12,20,$E$31,$E$29)) | O40: =ABS(PPMT($E$30/12,21,$E$31,$E$29)) | P40: =ABS(PPMT($E$30/12,22,$E$31,$E$29)) | Q40: =ABS(PPMT($E$30/12,23,$E$31,$E$29)) | R40: =ABS(PPMT($E$30/12,24,$E$31,$E$29)) | S40: =SUM(G40:R40)
C41: Loan Balance | G41: =R37-G40 | H41: =G41-H40 | I41: =H41-I40 | J41: =I41-J40 | K41: =J41-K40 | L41: =K41-L40 | M41: =L41-M40 | N41: =M41-N40 | O41: =N41-O40 | ... R41: =Q41-R40
B42: Year Three
C43: Interest | G43: =ABS(IPMT($E$30/12,25,$E$31,$E$29)) | H43: =ABS(IPMT($E$30/12,26,$E$31,$E$29)) | I43: =ABS(IPMT($E$30/12,27,$E$31,$E$29)) | J43: =ABS(IPMT($E$30/12,28,$E$31,$E$29)) | K43: =ABS(IPMT($E$30/12,29,$E$31,$E$29)) | L43: =ABS(IPMT($E$30/12,30,$E$31,$E$29)) | M43: =ABS(IPMT($E$30/12,31,$E$31,$E$29)) | N43: =ABS(IPMT($E$30/12,32,$E$31,$E$29)) | O43: =ABS(IPMT($E$30/12,33,$E$31,$E$29)) | P43: =ABS(IPMT($E$30/12,34,$E$31,$E$29)) | Q43: =ABS(IPMT($E$30/12,35,$E$31,$E$29)) | R43: =ABS(IPMT($E$30/12,36,$E$31,$E$29)) | S43: =SUM(G43:R43)
C44: Principal | G44: =ABS(PPMT($E$30/12,25,$E$31,$E$29)) | H44: =ABS(PPMT($E$30/12,26,$E$31,$E$29)) | I44: =ABS(PPMT($E$30/12,27,$E$31,$E$29)) | J44: =ABS(PPMT($E$30/12,28,$E$31,$E$29)) | K44: =ABS(PPMT($E$30/12,29,$E$31,$E$29)) | L44: =ABS(PPMT($E$30/12,30,$E$31,$E$29)) | M44: =ABS(PPMT($E$30/12,31,$E$31,$E$29)) | N44: =ABS(PPMT($E$30/12,32,$E$31,$E$29)) | O44: =ABS(PPMT($E$30/12,33,$E$31,$E$29)) | P44: =ABS(PPMT($E$30/12,34,$E$31,$E$29)) | Q44: =ABS(PPMT($E$30/12,35,$E$31,$E$29)) | R44: =ABS(PPMT($E$30/12,36,$E$31,$E$29)) | S44: =SUM(G44:R44)
C45: Loan Balance | G45: =R41-G44 | H45: =G45-H44 | I45: =H45-I44 | J45: =I45-J44 | K45: =J45-K44 | L45: =K45-L44 | M45: =L45-M44 | N45: =M45-N44 | O45: =N45-O44 | ... R45: =Q45-R44

Sheet 21. Financial Diagnostics
A1: ='1. Required Start-Up Funds'!A1
A2: Financial Diagnostics
A6: This sheet performs a few tests on your numbers to see if they seem within certain reasonable ranges.
A7: Remember, no computer can tell whether your projections are truly well-constructed, only a human can do that.
A8: But these tests can at least look for values that are critically out of range.
A11: Financial Diagnostics | G11: Value | I11: Findings
B12: General Financing Assumptions
C13: Owner's Cash Injection into the Business | G13: =IF('1. Required Start-Up Funds'!G42=0,0,'1. Required Start-Up Funds'!G37/'1. Required Start-Up Funds'!G42) | I13: =IF(G13>0.2,"Owner's injection is reasonable","Owner's injection might be too low in relation to the amount of money needed")
C14: Cash Request as percent of Total Required Funds | G14: =IF('1. Required Start-Up Funds'!G31=0,0,'1. Required Start-Up Funds'!E28/'1. Required Start-Up Funds'!G31) | I14: =IF(G14<0.2,"Cash request seems reasonable with respect to total request","Cash request exceeds 20% which might be high")
B16: Loan Assumptions
C17: Commercial Loan Interest rate | G17: ='1. Required Start-Up Funds'!H40 | I17: =IF(G17<0.06,"Interest rate may be too low for the type of loan requested","Interest rate seems reasonable")
C18: Commercial Loan Term in Months | G18: ='1. Required Start-Up Funds'!I40 | I18: =IF(G18>120,"Loan term may be too high for this type of loan","Loan term seems within range for this type of loan")
C20: Commercial Mortgage Interest rate | G20: ='1. Required Start-Up Funds'!H41 | I20: =IF(G20<0.06,"Interest rate may be too low for type of loan requested","Interest rate seems reasonable")
C21: Commercial Mortgage Term in Months | G21: ='1. Required Start-Up Funds'!I41 | I21: =IF(G21>240,"Loan term may be too high for this type of loan","Loan term seems within range for this type of loan")
C23: Loan Payments as a Percent of Projected Sales | G23: =IF('8. Income Statement'!Q13=0,0,'1. Required Start-Up Funds'!J42/'8. Income Statement'!Q13) | I23: =IF(G23>10,"Calculated loan payments as a percent of sales may be too high","Calculated loan payments as a percent of sales seem resonable")
B25: Income Statement
C26: Gross Margin as a Percent of Sales | G26: ='11. Year End Summary'!G22 | I26: =IF(G26<0.2,"Gross margin percentage seems very low","Gross margin percentage seems reasonable")
C27: Owner's Compensation Lower Limit Check | G27: ='2. Salaries and Wages'!M11 | I27: =IF(G27>0,"An owner's compensation amount has been established","An owner's compensation amount has not been established")
C28: Owner's Compensation Upper Limit Check | G28: =IF('8. Income Statement'!Q66=0,0,G27/'8. Income Statement'!Q66) | I28: =IF(G28>1,"Owner's compensation may be too high relative to profitability of business","Owner's compensation seems reasonable")
C29: Advertising Expense Levels as a Percent of Sales | G29: =IF('8. Income Statement'!Q13=0,0,'8. Income Statement'!Q34/'8. Income Statement'!Q13) | I29: =IF(G29<0.2,"Advertising as a percent of sales may be too low","Advertising as a percent of sales seems reasonable")
C30: Profitability Levels | G30: ='8. Income Statement'!Q66 | I30: =IF(G30<0,"The business is not showing a profit","The business is showing a profit")
C31: Profitability as a Percent of Sales | G31: ='11. Year End Summary'!G66 | I31: =IF(G31>0.2,"The projection may be too aggressive in stating profitability","The projection does not seem highly unreasonable")
B33: Cash Flow Statement
C34: Desired Operating cash Flow Levels | G34: ='9. Cash Flow Statement'!Q35 | I34: =IF(G34>0,"The financial projection does not provide the desired level of cash flow","The financial projection provides the desired level of cash flow")
C35: Line of Credit Drawdowns | G35: =G34 | I35: =IF(G35>0,"The business will need at least this level of a line of credit","The business doesn't seem to require a line of credit")
C36: Accounts Receivable Ratio to Sales | G36: =IF('8. Income Statement'!Q13=0,0,'10. Balance Sheet'!I11/'8. Income Statement'!Q13) | I36: =IF(G36>0.3,"Accounts receivable amounts seem high","Accounts receivable amount as a percent of sales seems reasonable")
B38: Balance Sheet
C39: Does the Base Period Balance Sheet Balance? | G39: ='10. Balance Sheet'!F29-'10. Balance Sheet'!F47 | I39: =IF(G39<>0,"The balance sheet is not in balance","The balance sheet does balance")
C40: Does the Final Balance Sheet Balance | G40: ='10. Balance Sheet'!I29-'10. Balance Sheet'!I47 | I40: =IF(G40<>0,"The balance sheet is not in balance","The balance sheet does balance")
C41: Debt to Equity Ratio | G41: =IF('10. Balance Sheet'!I45=0,0,'10. Balance Sheet'!I39/'10. Balance Sheet'!I45) | I41: =IF(G41>5,"Most banks would consider there to be too much debt for the overall amount of equity or ownership","The debt to equity ratio seems reasonable")
B43: Breakeven Analysis
C44: Breakeven Levels | G44: ='8. Income Statement'!Q13-'19. Breakeven Analysis'!G18 | I44: =IF(G44>0,"The sales projection exceeds the projected break-even sales level","The sales projection is less than the break-even amount")
